Workbook

Sheet ORIGINAL
D3: Redevances C&S 2026 à Facturer
J5: =SUM(J8:J351) -> 666538
A7: N° Compte | B7: Nom du compte | C7: Nom SF | D7: External ID | E7: Products ID | F7: Article SF | G7: Fréquence facturation | H7: Quantité | I7: Prix unitaire | J7: Montant 2026 | K7: Commentaires | L7: Commentaires
A8: CHVR-01881 | B8: CHEMVIRON | C8: CHEMVIRON sas | D8: 001IV000015S8iQYAS | E8: 01tIV00000GyVCbYAN | F8: Redevance d'utilisation - Tranche 25 ETP - Cas 2 | G8: Annuelle | H8: 1 | I8: 1000 | J8: 1000 | K8: 0 | L8: 0
A9: EIET-01859 | B9: EURO INFORMATION SERVICES | C9: EIS - EURO INFORMATION | D9: 001IV000015SADoYAO | E9: 01tIV00000GOfP6YAL | F9: Redevance d'utilisation - ETP EU | G9: Annuelle | H9: 1 | I9: 1080 | J9: 1080 | K9: 0 | L9: 0
A10: EUFR-01878 | B10: EURIAL ULTRA-FRAIS | C10: EURIAL ULTRA-FRAIS - Château Salins | D10: 001IV000015S2eZYAS | E10: 01tIV00000GyVCbYAN | F10: Redevance d'utilisation - Tranche 25 ETP - Cas 2 | G10: Annuelle | H10: 1 | I10: 3000 | J10: 3000 | K10: 0 | L10: 0
A11: CHRD-01609 | B11: CHARENTAISE DE DECOR | C11: CHARENTAISE DE DECOR | D11: 001IV000015S6a5YAC | E11: 01tIV00000GOfP6YAL | F11: Redevance d'utilisation - ETP EU | G11: Annuelle | H11: 1 | I11: 1000 | J11: 1000 | K11: 0 | L11: 0
A12: VRLF-01972 | B12: VERALLIA France | C12: VERALLIA France | D12: 001IV000015S9GIYA0 | E12: 01tIV00000GOfP6YAL | F12: Redevance d'utilisation - ETP EU | G12: Autre | H12: 1 | I12: 3440 | J12: 3440 | K12: 0 | L12: 0
A13: EPHG-01823 | B13: EPHIGEA GRAIN DE MALICE | C13: EPHIGEA GRAIN DE MALICE sasu | D13: 001IV000015SAHlYAO | E13: 01tIV00000GOfP6YAL | F13: Redevance d'utilisation - ETP EU | G13: Annuelle | H13: 1 | I13: 4200 | J13: 4200 | K13: 0 | L13: 0
A14: EMGP-01816 | B14: EM LYON EMG | C14: EMG-EARLY MAKERS GROUP | D14: 001IV000015SAHkYAO | E14: 01tIV00000GyVCbYAN | F14: Redevance d'utilisation - Tranche 25 ETP - Cas 2 | H14: 1 | I14: 1000 | J14: 1000
A15: SFRT-01772 | B15: SEYFERT | C15: SEYFERT SAS | D15: 001IV000015RyDnYAK | E15: 01tIV00000GyVCbYAN | F15: Redevance d'utilisation - Tranche 25 ETP - Cas 2 | G15: Annuelle | H15: 1 | I15: 4000 | J15: 4000 | K15: 0 | L15: 0
A16: IPSA-01585 | B16: INTERNATIONAL PAPER France | C16: INTERNATIONAL PAPER France | D16: 001IV000015SAFhYAO | E16: 01tIV00000GOfP1YAL | F16: Redevance d'utilisation - Tranche 25 ETP - Cas 1 | G16: Annuelle | H16: 1 | I16: 2000 | J16: 2000 | K16: 0 | L16: 0
A17: GCPC-01584 | B17: CHRYSO FRANCE | C17: CHRYSO FRANCE (ex GCP PRODUITS DE CONSTRUCTION) | D17: 001IV000015S2eRYAS | E17: 01tIV00000GyVCbYAN | F17: Redevance d'utilisation - Tranche 25 ETP - Cas 2 | G17: Annuelle | H17: 1 | I17: 1000 | J17: 1000 | K17: 0 | L17: 0
A18: ABSD-01564 | B18: ABRISUD | C18: ABRISUD | D18: 001IV000015S6ZxYAK | E18: 01tIV00000GOfP6YAL | F18: Redevance d'utilisation - ETP EU | G18: Annuelle | H18: 1 | I18: 1800 | J18: 1800 | K18: 0 | L18: 0
A19: ACIA-01692 | B19: ACIAL | C19: ACIAL | D19: 001IV000015S85xYAC | E19: 01tIV00000GyVCbYAN | F19: Redevance d'utilisation - Tranche 25 ETP - Cas 2 | G19: Annuelle | H19: 1 | I19: 1000 | J19: 1000 | K19: 0 | L19: 0
A20: ALMG-01848 | B20: ALMA GROUPE | C20: ALMA GROUPE | D20: 001IV000015RyDjYAK | E20: 01tIV00000GyVCbYAN | F20: Redevance d'utilisation - Tranche 25 ETP - Cas 2 | G20: Annuelle | H20: 1 | I20: 9000 | J20: 9000 | K20: 0 | L20: 0
A21: ANGD-01672 | B21: ANGDM | C21: ANGDM | D21: 001IV000015S50QYAS | E21: 01tIV00000GyVCbYAN | F21: Redevance d'utilisation - Tranche 25 ETP - Cas 2 | G21: Annuelle | H21: 1 | I21: 1000 | J21: 1000
A22: AMPR-01765 | B22: SOFIVO | C22: ARMOR PROTEINES | D22: 001IV000015RewHYAS | E22: 01tIV00000GyVCbYAN | F22: Redevance d'utilisation - Tranche 25 ETP - Cas 2 | G22: Annuelle | H22: 1 | I22: 3000 | J22: 3000 | K22: 0 | L22: 0
A23: ATSX-01481 | B23: APPLICATION TRAVAUX SPECIAUX | C23: ATS | D23: 001IV000015Rew7YAC | E23: 01tIV00000GOfP6YAL | F23: Redevance d'utilisation - ETP EU | G23: Annuelle | H23: 1 | I23: 1800 | J23: 1800 | K23: 0 | L23: 0
A24: AXGR-01774 | B24: AXE GROUP | C24: AXE GROUP | D24: 001IV000015S50NYAS | E24: 01tIV00000GyVCbYAN | F24: Redevance d'utilisation - Tranche 25 ETP - Cas 2 | G24: Annuelle | H24: 1 | I24: 1000 | J24: 1000 | K24: 0 | L24: 0
A25: BPEF-01789 | B25: BALL PACKAGING EUROPE | C25: BALL PACKAGING GROUPE | D25: 001IV000015RhU5YAK | E25: 01tIV00000GOfP6YAL | F25: Redevance d'utilisation - ETP EU | G25: Annuelle | H25: 1 | I25: 1080 | J25: 1080 | K25: 0 | L25: 0
A26: BBGR-01651 | B26: BARBIER PLASTIQUES | C26: BARBIER GROUPE | D26: 001IV000015RzTfYAK | E26: 01tIV00000GyVCbYAN | F26: Redevance d'utilisation - Tranche 25 ETP - Cas 2 | G26: Annuelle | H26: 1 | I26: 8000 | J26: 8000 | K26: 0 | L26: 0
A27: BSFA-01740 | B27: BASF AGRI PRODUCTION | C27: BASF AGRIPRODUCTION | D27: 001IV000015RyDgYAK | E27: 01tIV00000GyVCbYAN | F27: Redevance d'utilisation - Tranche 25 ETP - Cas 2 | G27: Annuelle | H27: 1 | I27: 2000 | J27: 2000 | K27: 0 | L27: 0
A28: BICR-01561 | B28: BIC RASOIRS | C28: BIC RASOIRS | D28: 001IV000015S50CYAS | E28: 01tIV00000GyVCbYAN | F28: Redevance d'utilisation - Tranche 25 ETP - Cas 2 | G28: Annuelle | H28: 1 | I28: 1000 | J28: 1000 | K28: 0 | L28: 0
A29: BIOH-01734 | B29: BIO HABITAT | C29: BIO HABITAT | D29: 001IV000015S6a8YAC | E29: 01tIV00000GOfP1YAL | F29: Redevance d'utilisation - Tranche 25 ETP - Cas 1 | G29: Annuelle | H29: 1 | I29: 2500 | J29: 2500 | K29: 0 | L29: 0
A30: BLCH-01662 | B30: BLANCHON SA | C30: BLANCHON (GROUPE) | D30: 001IV000015RewMYAS | E30: 01tIV00000GyVCbYAN | F30: Redevance d'utilisation - Tranche 25 ETP - Cas 2 | G30: Annuelle | H30: 1 | I30: 3000 | J30: 3000 | K30: 0 | L30: 0
A31: BGRD-01647 | B31: BONGARD | C31: BONGARD | D31: 001IV000015S2eNYAS | E31: 01tIV00000GyVCbYAN | F31: Redevance d'utilisation - Tranche 25 ETP - Cas 2 | G31: Annuelle | H31: 1 | I31: 1000 | J31: 1000 | K31: 0 | L31: 0
A32: BNFY-01575 | B32: BONNEFOY SAS | C32: BONNEFOY SAS | D32: 001IV000015S8imYAC | E32: 01tIV00000GyVCbYAN | F32: Redevance d'utilisation - Tranche 25 ETP - Cas 2 | G32: Annuelle | H32: 1 | I32: 2000 | J32: 2000 | K32: 0 | L32: 0
A33: CEKC-01875 | B33: C ET K COMPONENTS SAS | C33: C&K COMPONENTS SAS | D33: 001IV000015S8iPYAS | E33: 01tIV00000GyVCbYAN | F33: Redevance d'utilisation - Tranche 25 ETP - Cas 2 | G33: Annuelle | H33: 1 | I33: 2000 | J33: 2000 | K33: 0 | L33: 0
... A41: DNAG-01749 | B41: DIANA | C41: DIANA GROUP | D41: 001IV000015S8j4YAC | E41: 01tIV00000GOfP6YAL | F41: Redevance d'utilisation - ETP EU | G41: Annuelle | H41: 1 | I41: 3840 | J41: 3840 | K41: 0 | L41: 0
A42: DKFR-01494 | B42: DOKA FRANCE | C42: DOKA FRANCE | D42: 001IV000015Rew8YAC | E42: 01tIV00000GOfP6YAL | F42: Redevance d'utilisation - ETP EU | G42: Annuelle | H42: 1 | I42: 2232 | J42: 2232
A43: DSPX-01537 | B43: DSP | C43: DSP | D43: 001IV000015RyDhYAK | E43: 01tIV00000GyVCbYAN | F43: Redevance d'utilisation - Tranche 25 ETP - Cas 2 | G43: Annuelle | H43: 1 | I43: 1000 | J43: 1000 | K43: 0 | L43: 0
A44: ELDN-01899 | B44: ELYDAN SAS | C44: ELYDAN sas | D44: 001IV000015SAI9YAO | E44: 01tIV00000GyVCbYAN | F44: Redevance d'utilisation - Tranche 25 ETP - Cas 2 | G44: Annuelle | H44: 1 | I44: 3000 | J44: 3000 | K44: 0 | L44: 0
A45: FLDT-01645 | B45: FIELDTURF TARKETT | C45: FIELDTURF TARKETT | D45: 001IV000015S2eDYAS | E45: 01tIV00000GOfP1YAL | F45: Redevance d'utilisation - Tranche 25 ETP - Cas 1 | G45: Annuelle | H45: 1 | I45: 1000 | J45: 1000 | K45: 0 | L45: 0
A46: FNLM-01536 | B46: FINE LAME | C46: FINE LAME | D46: 001IV000015S6a1YAC | E46: 01tIV00000GyVCbYAN | F46: Redevance d'utilisation - Tranche 25 ETP - Cas 2 | G46: Annuelle | H46: 1 | I46: 1000 | J46: 1000 | K46: 0 | L46: 0
A47: FLIP-01667 | B47: FLIP | C47: FLIP SAS | D47: 001IV000015S2ePYAS | E47: 01tIV00000GyVCbYAN | F47: Redevance d'utilisation - Tranche 25 ETP - Cas 2 | G47: Annuelle | H47: 1 | I47: 1000 | J47: 1000 | K47: 0 | L47: 0
A48: FMCF-01656 | B48: GROUPE FMC | C48: FMC FRANCE | D48: 001IV000015S2eSYAS | E48: 01tIV00000GOfP6YAL | F48: Redevance d'utilisation - ETP EU | G48: Annuelle | H48: 1 | I48: 2232 | J48: 2232 | K48: 0 | L48: 0
A49: FRCS-01805 | B49: SISLEY INDUSTRIE | C49: FRANCOS - (SISLEY) | D49: 001IV000015RyDwYAK | E49: 01tIV00000GyVCbYAN | F49: Redevance d'utilisation - Tranche 25 ETP - Cas 2 | G49: Annuelle | H49: 1 | I49: 1000 | J49: 1000 | K49: 0 | L49: 0
A50: FRST-01862 | B50: FREUDENBERG SEALING TECHNOLOGIES SA | C50: FREUDENBERG SEALING TECHNOLOGIES sas | D50: 001IV000015RyE1YAK | E50: 01tIV00000GyVCbYAN | F50: Redevance d'utilisation - Tranche 25 ETP - Cas 2 | G50: Annuelle | H50: 1 | I50: 1000 | J50: 1000 | K50: 0 | L50: 0
A51: GHSF-01558 | B51: GEORGES HELFER | C51: GEORGES HELFER | D51: 001IV000015S50BYAS | E51: 01tIV00000GOfP6YAL | F51: Redevance d'utilisation - ETP EU | G51: Annuelle | H51: 1 | I51: 4120 | J51: 4120 | K51: 0 | L51: 0
A52: GCPS-01511 | B52: COFIDIS GROUP | C52: GROUPE COFIDIS PARTICIPATIONS (SYNERGIE GEIE) | D52: 001IV000015SAHRYA4 | E52: 01tIV00000GyVCbYAN | F52: Redevance d'utilisation - Tranche 25 ETP - Cas 2 | G52: Annuelle | H52: 1 | I52: 1000 | J52: 1000 | K52: 0 | L52: 0
A53: GDFP-01797 | B53: GROUPE DIFFUSION PLUS | C53: GROUPE DIFFUSION PLUS sas | D53: 001IV000015S2SVYA0 | E53: 01tIV00000GOfP1YAL | F53: Redevance d'utilisation - Tranche 25 ETP - Cas 1 | G53: Annuelle | H53: 1 | I53: 2500 | J53: 2500 | K53: 0 | L53: 0
A54: GRLD-01542 | B54: LUCAY MAROQUINERIE | C54: GROUPE RIOLAND | D54: 001IV000015S6a7YAC | E54: 01tIV00000GyVCbYAN | F54: Redevance d'utilisation - Tranche 25 ETP - Cas 2 | G54: Annuelle | H54: 1 | I54: 2000 | J54: 2000 | K54: 0 | L54: 0
... A75: LMBG-01911 | B75: LOC MARIA BISCUITS | C75: LOC MARIA BISCUITS (GROUPE) | D75: 001IV000015SAHtYAO | E75: 01tIV00000GyVCbYAN | F75: Redevance d'utilisation - Tranche 25 ETP - Cas 2 | G75: Annuelle | H75: 1 | I75: 3000 | J75: 3000 | K75: 0 | L75: 0
A76: SMVC-01528 | B76: MAVIC GROUP | C76: MAVIC GROUP | D76: 001IV000015SAFaYAO | E76: 01tIV00000GOfP6YAL | F76: Redevance d'utilisation - ETP EU | G76: Annuelle | H76: 1 | I76: 1080 | J76: 1080
A77: MCBD-01903 | B77: MCBRIDE S.A.S | C77: MC BRIDE SAS | D77: 001IV000015RyE0YAK | E77: 01tIV00000GyVCbYAN | F77: Redevance d'utilisation - Tranche 25 ETP - Cas 2 | G77: Annuelle | H77: 1 | I77: 3000 | J77: 3000 | K77: 0 | L77: 0
A78: MDSX-01864 | B78: MDS | C78: MDS sa | D78: 001IV000015S86DYAS | E78: 01tIV00000GyVCbYAN | F78: Redevance d'utilisation - Tranche 25 ETP - Cas 2 | G78: Annuelle | H78: 1 | I78: 3000 | J78: 3000 | K78: 0 | L78: 0
A79: MRSN-01830 | B79: MERSEN FRANCE | C79: MERSEN | D79: 001IV000015SAI8YAO | E79: 01tIV00000GyVCbYAN | F79: Redevance d'utilisation - Tranche 25 ETP - Cas 2 | G79: Annuelle | H79: 1 | I79: 6000 | J79: 6000 | K79: 0 | L79: 0
A80: MTEF-01520 | B80: METALOR TECHNOLOGIES | C80: METALOR TECHNOLOGIES | D80: 001IV000015SAFcYAO | E80: 01tIV00000GyVCbYAN | F80: Redevance d'utilisation - Tranche 25 ETP - Cas 2 | G80: Annuelle | H80: 1 | I80: 2000 | J80: 2000 | K80: 0 | L80: 0
A81: MTSF-01652 | B81: METSO FRANCE SAS | C81: METSO FRANCE SAS | D81: 001IV000015S50RYAS | E81: 01tIV00000GOfP6YAL | F81: Redevance d'utilisation - ETP EU | G81: Annuelle | H81: 1 | I81: 2232 | J81: 2232 | K81: 0 | L81: 0
A82: MMPP-01589 | B82: MMP SAS | C82: MMP PACKETIS | D82: 001IV000015S8ioYAC | E82: 01tIV00000GyVCbYAN | F82: Redevance d'utilisation - Tranche 25 ETP - Cas 2 | G82: Annuelle | H82: 1 | I82: 4000 | J82: 4000 | K82: 0 | L82: 0
A83: MTBL-01521 | B83: MONT BLANC | C83: MONT BLANC | D83: 001IV000015S2eOYAS | E83: 01tIV00000GyVCbYAN | F83: Redevance d'utilisation - Tranche 25 ETP - Cas 2 | G83: Annuelle | H83: 1 | I83: 2000 | J83: 2000 | K83: 0 | L83: 0
A84: LMDV-01522 | B84: MOULINS BOURGEOIS | C84: MOULINS BOURGEOIS (DE VERDELOT) | D84: 001IV000015Rew9YAC | E84: 01tIV00000GyVCbYAN | F84: Redevance d'utilisation - Tranche 25 ETP - Cas 2 | G84: Annuelle | H84: 1 | I84: 1000 | J84: 1000 | K84: 0 | L84: 0
A85: NFBP-01498 | B85: NEFAB | C85: NEFAB PACKAGING | D85: 001IV000015RewAYAS | E85: 01tIV00000GyVCbYAN | F85: Redevance d'utilisation - Tranche 25 ETP - Cas 2 | G85: Annuelle | H85: 1 | I85: 2000 | J85: 2000 | K85: 0 | L85: 0
A86: NRCG-01620 | B86: NORAC SA | C86: NORAC GROUPE | D86: 001IV000015RxtaYAC | E86: 01tIV00000GyVCbYAN | F86: Redevance d'utilisation - Tranche 25 ETP - Cas 2 | G86: Annuelle | H86: 1 | I86: 21000 | J86: 21000 | K86: 0 | L86: 0
A87: NSTF-01804 | B87: NYRSTAR | C87: NYRSTAR FRANCE | D87: 001IV000015S8j2YAC | E87: 01tIV00000GyVCbYAN | F87: Redevance d'utilisation - Tranche 25 ETP - Cas 2 | G87: Annuelle | H87: 1 | I87: 2000 | J87: 2000 | K87: 0 | L87: 0
A88: OLCH-01706 | B88: OLICHON | C88: OLICHON GROUPE (TSO ...) | D88: 001IV000015S2eBYAS | E88: 01tIV00000GyVCbYAN | F88: Redevance d'utilisation - Tranche 25 ETP - Cas 2 | G88: Annuelle | H88: 1 | I88: 1000 | J88: 1000
A89: VPKC-01531 | B89: ONDULYS (VPK Group) | C89: ONDULYS (VPK Group) | D89: 001IV000015RewBYAS | E89: 01tIV00000GyVCbYAN | F89: Redevance d'utilisation - Tranche 25 ETP - Cas 2 | G89: Annuelle | H89: 1 | I89: 1000 | J89: 1000 | K89: 0 | L89: 0
A90: OECO-01733 | B90: ORECO | C90: ORECO | D90: 001IV000015S8iqYAC | E90: 01tIV00000GyVCbYAN | F90: Redevance d'utilisation - Tranche 25 ETP - Cas 2 | G90: Annuelle | H90: 1 | I90: 1000 | J90: 1000 | K90: 0 | L90: 0
A91: OTRF-01794 | B91: O TERRA FRANCE COSSE | C91: OTERRA FRANCE | D91: 001IV000015S8j9YAC | E91: 01tIV00000GyVCbYAN | F91: Redevance d'utilisation - Tranche 25 ETP - Cas 2 | G91: Annuelle | H91: 1 | I91: 1000 | J91: 1000
A92: PAPM-01628 | B92: GROUPE PAPIN | C92: PAPIN GROUPE | D92: 001IV000015S85iYAC | E92: 01tIV00000GyVCbYAN | F92: Redevance d'utilisation - Tranche 25 ETP - Cas 2 | G92: Annuelle | H92: 1 | I92: 4000 | J92: 4000 | K92: 0 | L92: 0
A93: PDGP-01507 | B93: PDG Plastiques | C93: PDG PLASTIQUES | D93: 001IV000015S6ZyYAK | E93: 01tIV00000GyVCbYAN | F93: Redevance d'utilisation - Tranche 25 ETP - Cas 2 | G93: Annuelle | H93: 1 | I93: 1000 | J93: 1000 | K93: 0 | L93: 0
A94: PRIF-01578 | B94: PERNOD RICARD FRANCE | C94: PERNOD RICARD FRANCE | D94: 001IV000015S8ieYAC | E94: 01tIV00000GyVCbYAN | F94: Redevance d'utilisation - Tranche 25 ETP - Cas 2 | G94: Annuelle | H94: 1 | I94: 1000 | J94: 1000 | K94: 0 | L94: 0
A95: PLJI-01563 | B95: PILEJE SAS | C95: PILEJE SAS | D95: 001IV000015S8ijYAC | E95: 01tIV00000GyVCbYAN | F95: Redevance d'utilisation - Tranche 25 ETP - Cas 2 | G95: Annuelle | H95: 1 | I95: 1000 | J95: 1000 | K95: 0 | L95: 0
A96: PLCH-01717 | B96: PLACOPLATRE CHAMBERY | C96: PLACOPLATRE CHAMBERY | D96: 001IV000015S8iwYAC | E96: 01tIV00000GyVCbYAN | F96: Redevance d'utilisation - Tranche 25 ETP - Cas 2 | G96: Annuelle | H96: 1 | I96: 1000 | J96: 1000 | K96: 0 | L96: 0
A97: BRGR-01509 | B97: PRODUITS BERGER SAS | C97: PRODUITS BERGER SAS | D97: 001IV000015S8icYAC | E97: 01tIV00000GyVCbYAN | F97: Redevance d'utilisation - Tranche 25 ETP - Cas 2 | G97: Annuelle | H97: 1 | I97: 1000 | J97: 1000 | K97: 0 | L97: 0
A98: PMAF-01775 | B98: PUMA | C98: PUMA FRANCE SAS | D98: 001IV000015RyDlYAK | E98: 01tIV00000GyVCbYAN | F98: Redevance d'utilisation - Tranche 25 ETP - Cas 2 | G98: Annuelle | H98: 1 | I98: 1000 | J98: 1000 | K98: 0 | L98: 0
A99: RVMA-01671 | B99: REVIMA | C99: REVIMA | D99: 001IV000015RyL0YAK | E99: 01tIV00000GOfP6YAL | F99: Redevance d'utilisation - ETP EU | G99: Annuelle | H99: 1 | I99: 2000 | J99: 2000 | K99: 0 | L99: 0
A100: RCHF-01548 | B100: RICOH FRANCE | C100: RICOH FRANCE | D100: 001IV000015RzTVYA0 | E100: 01tIV00000GyVCbYAN | F100: Redevance d'utilisation - Tranche 25 ETP - Cas 2 | G100: Annuelle | H100: 1 | I100: 1000 | J100: 1000 | K100: 0 | L100: 0
A101: RGIN-01658 | B101: ROCHLING INDUSTRIAL | C101: ROCHLING INDUSTRIAL NANCY | D101: 001IV000015RzTWYA0 | E101: 01tIV00000GyVCbYAN | F101: Redevance d'utilisation - Tranche 25 ETP - Cas 2 | G101: Annuelle | H101: 1 | I101: 1000 | J101: 1000 | K101: 0 | L101: 0
A102: RSGN-01895 | B102: GROUPE ROSSIGNOL | C102: ROSSIGNOL (GROUPE) | D102: 001IV000015S86FYAS | E102: 01tIV00000GyVCbYAN | F102: Redevance d'utilisation - Tranche 25 ETP - Cas 2 | G102: Annuelle | H102: 1 | I102: 4000 | J102: 4000 | K102: 0 | L102: 0
A103: RVAL-01597 | B103: ROVAL | C103: ROVAL | D103: 001IV000015RhU7YAK | E103: 01tIV00000GyVCbYAN | F103: Redevance d'utilisation - Tranche 25 ETP - Cas 2 | G103: Annuelle | H103: 1 | I103: 7000 | J103: 7000 | K103: 0 | L103: 0
... A109: TIES-01480 | B109: TOYO INK EUROPE SPEC CHEMICALS | C109: TOYO INK EUROPE | D109: 001IV000015S6ZvYAK | E109: 01tIV00000GyVCbYAN | F109: Redevance d'utilisation - Tranche 25 ETP - Cas 2 | G109: Annuelle | H109: 1 | I109: 1000 | J109: 1000 | K109: 0 | L109: 0
A110: UCOY-01702 | B110: UNIVERSITE CATHOLIQUE OUEST | C110: UNIVERSITE CATHOLIQUE DE L'OUEST - (ASS ST-YVES - UCO) | D110: 001IV000015S861YAC | E110: 01tIV00000GyVCbYAN | F110: Redevance d'utilisation - Tranche 25 ETP - Cas 2 | G110: Annuelle | H110: 1 | I110: 1000 | J110: 1000
A111: UPSA-01768 | B111: UPSA SAS | C111: UPSA | D111: 001IV000015RyL1YAK | E111: 01tIV00000GyVCbYAN | F111: Redevance d'utilisation - Tranche 25 ETP - Cas 2 | G111: Annuelle | H111: 1 | I111: 3000 | J111: 3000 | K111: 0 | L111: 0
A112: VRNT-01701 | B112: VERNET | C112: VERNET | D112: 001IV000015SAHxYAO | E112: 01tIV00000GyVCbYAN | F112: Redevance d'utilisation - Tranche 25 ETP - Cas 2 | G112: Annuelle | H112: 1 | I112: 4000 | J112: 4000 | K112: 0 | L112: 0
A113: VMDC-01524 | B113: VIANT MEDICAL | C113: VIANT MEDICAL - (CHAUMONT) | D113: 001IV000015S508YAC | E113: 01tIV00000GyVCbYAN | F113: Redevance d'utilisation - Tranche 25 ETP - Cas 2 | G113: Annuelle | H113: 1 | I113: 2000 | J113: 2000 | K113: 0 | L113: 0
A114: VWBK-01490 | B114: VOLKSWAGEN BANK | C114: VW BANK | D114: 001IV000015S1XOYA0 | E114: 01tIV00000GyVCbYAN | F114: Redevance d'utilisation - Tranche 25 ETP - Cas 2 | G114: Annuelle | H114: 1 | I114: 3000 | J114: 3000 | K114: 0 | L114: 0
A115: WESR-01594 | B115: WESER | C115: WESER | D115: 001IV000015S2eUYAS | E115: 01tIV00000GOfP6YAL | F115: Redevance d'utilisation - ETP EU | G115: Annuelle | H115: 1 | I115: 3120 | J115: 3120 | K115: 0 | L115: 0
A116: WRTF-01708 | B116: WURTH FRANCE | C116: WURTH FRANCE SAS | D116: 001IV000015S4lEYAS | E116: 01tIV00000GOfP6YAL | F116: Redevance d'utilisation - ETP EU | G116: Annuelle | H116: 1 | I116: 4000 | J116: 4000 | K116: 0 | L116: 0
A117: LGLF-01857 | B117: LFB FRANCE | C117: LFB FRANCE (ex LENNOX ex LGL) | D117: 001IV000015S869YAC | E117: 01tIV00000GyVCbYAN | F117: Redevance d'utilisation - Tranche 25 ETP - Cas 2 | G117: Annuelle | H117: 1 | I117: 4000 | J117: 4000 | K117: 0 | L117: 0
A118: NPPA-01898 | B118: NESTLE PURINA | C118: NESTLE PURINA PETCARE AUBIGNY | D118: 001IV000015RvVPYA0 | E118: 01tIV00000GOfP1YAL | F118: Redevance d'utilisation - Tranche 25 ETP - Cas 1 | G118: Semestrielle | H118: 1 | I118: 3500 | J118: 3500 | K118: 0 | L118: 0
A119: ABBF-01693 | B119: ABB FRANCE | C119: ABB FRANCE | D119: 001IV000015S8ixYAC | E119: 01tIV00000GOfP1YAL | F119: Redevance d'utilisation - Tranche 25 ETP - Cas 1 | G119: Annuelle | H119: 1 | I119: 1000 | J119: 1000 | K119: 0 | L119: 0
A120: AFCB-01660 | B120: AMPHENOL FCI BESANCON | C120: AMPHENOL FCI | D120: 001IV000015SAHqYAO | E120: 01tIV00000GOfP1YAL | F120: Redevance d'utilisation - Tranche 25 ETP - Cas 1 | G120: Annuelle | H120: 1 | I120: 1000 | J120: 1000 | K120: 0 | L120: 0
A121: ANTS-01879 | B121: AGCE NAT DES TITRES SECURISES | C121: ANTS | D121: 001IV000015S8izYAC | E121: 01tIV00000GOfP1YAL | F121: Redevance d'utilisation - Tranche 25 ETP - Cas 1 | G121: Annuelle | H121: 1 | I121: 500 | J121: 500 | K121: 0 | L121: 0
A122: AAAM-02046 | B122: APERAM | C122: 0 | D122: 001IV00001OqxYmYAJ | E122: 01tIV00000GOfP1YAL | F122: Redevance d'utilisation - Tranche 25 ETP - Cas 1 | G122: Annuelle | H122: 1 | I122: 4000 | J122: 4000 | K122: 0 | L122: 0
A123: ARFR-02021 | B123: ARAYMOND SARL | C123: ARAYMOND FRANCE | D123: 001IV000015SAI2YAO | E123: 01tIV00000GOfP1YAL | F123: Redevance d'utilisation - Tranche 25 ETP - Cas 1 | G123: Annuelle | H123: 1 | I123: 3500 | J123: 3500 | K123: 0 | L123: 0
A124: ARCO-01885 | B124: ARCO | C124: ARCO | D124: 001IV000015S86EYAS | E124: 01tIV00000GyVFpYAN | F124: Redevance d'utilisation - Tranche 25 ETP / EU canal indirect (facturation ETT) - Cas 1 | G124: Annuelle | H124: 1 | I124: 2000 | J124: 2000 | K124: Facturation Adecco | L124: 0
A125: MBSA-01612 | B125: Association MBS | C125: MBS ASSOCIATION | D125: 001IV000015RewDYAS | E125: 01tIV00000GOfP1YAL | F125: Redevance d'utilisation - Tranche 25 ETP - Cas 1 | G125: Annuelle | H125: 1 | I125: 500 | J125: 500 | K125: 0 | L125: 0
A126: AUBI-01723 | B126: AUBIN IMPRIMEUR | C126: AUBIN IMPRIMEUR | D126: 001IV000015RewOYAS | E126: 01tIV00000GOfP1YAL | F126: Redevance d'utilisation - Tranche 25 ETP - Cas 1 | G126: Annuelle | H126: 1 | I126: 500 | J126: 500
A127: BPMD-01549 | B127: BANQUE POPULAIRE MEDITERRANEE | C127: BANQUE POPULAIRE MEDITERRANEE | D127: 001IV000015SAFiYAO | E127: 01tIV00000GOfP1YAL | F127: Redevance d'utilisation - Tranche 25 ETP - Cas 1 | G127: Annuelle | H127: 1 | I127: 500 | J127: 500
A128: BASV-01744 | B128: BARILLA FRANCE ST VULBAS | C128: BARILLA ST VULBAS | D128: 001IV000015RewPYAS | E128: 01tIV00000GOfP1YAL | F128: Redevance d'utilisation - Tranche 25 ETP - Cas 1 | G128: Annuelle | H128: 1 | I128: 1000 | J128: 1000 | K128: 0 | L128: 0
A129: BBHA-01773 | B129: BAUMER BOURDON HAENNI S.A.S | C129: BAUMER BOURDON HAENNI (PME) | D129: 001IV000015S2SOYA0 | E129: 01tIV00000GOfP1YAL | F129: Redevance d'utilisation - Tranche 25 ETP - Cas 1 | G129: Annuelle | H129: 1 | I129: 500 | J129: 500 | K129: 0 | L129: 0
A130: PRMS-01766 | B130: BERRY BEAUTE MAROLLES | C130: BERRY GLOBAL - PROMENS - (EX PGI) | D130: 001IV000015S867YAC | E130: 01tIV00000GOfP1YAL | F130: Redevance d'utilisation - Tranche 25 ETP - Cas 1 | G130: Annuelle | H130: 1 | I130: 1500 | J130: 1500 | K130: 0 | L130: 0
A131: BRDF-01782 | B131: BRANDT France | C131: BRANDT FRANCE | D131: 001IV000015RzTaYAK | E131: 01tIV00000GOfP1YAL | F131: Redevance d'utilisation - Tranche 25 ETP - Cas 1 | G131: Annuelle | H131: 1 | I131: 1000 | J131: 1000 | K131: 0 | L131: 0
A132: CEBF-01654 | B132: CAISSE D'EPARGNE BOURGOGNE FRANCHE COMTE | C132: CAISSE D'EPARGNE BOURGOGNE FRANCHE COMTE (CEBFC) | D132: 001IV000015S8ipYAC | E132: 01tIV00000GOfP1YAL | F132: Redevance d'utilisation - Tranche 25 ETP - Cas 1 | G132: Annuelle | H132: 1 | I132: 1000 | J132: 1000 | K132: 0 | L132: 0
A133: SHRP-01576 | B133: CALIDA GROUP | C133: SHERPA LOGISTIQUE (CALIDA GROUP) | D133: 001IV000015S8ilYAC | E133: 01tIV00000GOfP1YAL | F133: Redevance d'utilisation - Tranche 25 ETP - Cas 1 | G133: Annuelle | H133: 1 | I133: 500 | J133: 500
A134: CLGM-01513 | B134: GROUPE CAMUS | C134: CAMUS | D134: 001IV000015SAHQYA4 | E134: 01tIV00000GOfP1YAL | F134: Redevance d'utilisation - Tranche 25 ETP - Cas 1 | G134: Annuelle | H134: 1 | I134: 500 | J134: 500
A135: CARG-01700 | B135: CAREA GROUPE | C135: CAREA GROUPE | D135: 001IV000015RewNYAS | E135: 01tIV00000GOfP1YAL | F135: Redevance d'utilisation - Tranche 25 ETP - Cas 1 | G135: Annuelle | H135: 1 | I135: 500 | J135: 500 | K135: 0 | L135: 0
A136: CBNE-01515 | B136: CHABANNE | C136: CHABANNE | D136: 001IV000015S2eQYAS | E136: 01tIV00000GOfP1YAL | F136: Redevance d'utilisation - Tranche 25 ETP - Cas 1 | G136: Annuelle | H136: 1 | I136: 500 | J136: 500 | K136: 0 | L136: 0
...

Sheet DOCUMENT DE TRAVAIL
D3: Redevances C&S 2026 à Facturer
AP5: =SUM(AP8:AP350) -> 641538
A7: N° Compte | B7: Nom du compte | C7: Nom SF | D7: External ID | E7: Products ID | F7: Article SF | G7: Line description | H7: Billing schedule | I7: Terme | J7: Billling start date | K7: End date | L7: Activity | M7: Offer | N7: Closing Date | O7: Legacy ID | P7: VAT Number | Q7: Registration number | R7: Invoice sending method | S7: Send invoice to | T7: Payment method | U7: Charge map type | V7: Billing Business Name | W7: Billing Department | X7: Billing Street | Y7: Billing City | Z7: Billing Postal code | AA7: Billing instruction | AB7: Billing conditions | AC7: PO Required? | AD7: PO Reference | AE7: PO Request Date | AF7: Shipping Business Name | AG7: Shipping Department | AH7: Shipping street | AI7: Shipping City | AJ7: Billing Contact ID | AK7: Billing Contact | AL7: Cash collection ID | AM7: Cash collection Contact | AN7: Quantité | AO7: Prix unitaire | AP7: Montant 2026 | AQ7: Commentaires | AR7: Commentaires
A8: PLCH-01717 | B8: PLACOPLATRE CHAMBERY | C8: PLACOPLATRE CHAMBERY | D8: 001IV000015S8iwYAC | E8: 01tIV00000GyVCbYAN | F8: Redevance d'utilisation - Tranche 25 ETP - Cas 2 | H8: Annual | I8: In advance | J8: 46023 | K8: 46387 | L8: Pixid France | M8: Pack C&S | N8: 46023 | O8: =VLOOKUP(D8,records!$A:$U,10,FALSE) -> 001SZ0000017fU7YAI | P8: =VLOOKUP(D8,records!$A:$V,20,FALSE) -> FR95729800706 | Q8: =VLOOKUP(D8,records!$A:$V,12,FALSE) -> 72 980 070 600 040 | R8: Email | S8: =VLOOKUP(D8,records!$A:$W,19,FALSE) -> 0nly.invoices.placoplatre@saint-gobain.com | T8: Transfer | U8: Renewal | V8: =VLOOKUP($D8,records!$A:$V,3,FALSE) -> PLACOPLATRE sa - Usine Placo de Chambéry | W8: =IFERROR(VLOOKUP($D8,records!$A:$V,6,FALSE),) -> Ressources Humaines | X8: =VLOOKUP($D8,records!$A:$V,9,FALSE) -> Z.I de Bissy - 456 rue Emile Romanet | Y8: =VLOOKUP($D8,records!$A:$V,4,FALSE) -> CHAMBERY | Z8: =VLOOKUP($D8,records!$A:$V,7,FALSE) -> 73026 | AA8: Redevance 2026 | AB8: =VLOOKUP(O8,'records (2)'!$A:$Z,8,FALSE) -> 30 | AC8: FALSE | AF8: =VLOOKUP($D8,records!$A:$V,13,FALSE) -> PLACOPLATRE sa - Usine Placo de Chambéry | AG8: =VLOOKUP($D8,records!$A:$V,16,FALSE) -> Facture originale électronique à | AH8: =VLOOKUP($D8,records!$A:$V,19,FALSE) -> 0nly.invoices.placoplatre@saint-gobain.com | AI8: =VLOOKUP($D8,records!$A:$V,14,FALSE) -> . | AJ8: =VLOOKUP($O8,'records (2)'!$A:$Z,14,FALSE) -> 003IV000010tSmVYAU | AK8: =VLOOKUP($O8,'records (2)'!$A:$Z,15,FALSE) -> Lucie GRANGER | AL8: =VLOOKUP($O8,'records (2)'!$A:$Z,10,FALSE) -> 003IV000010tSmVYAU | AM8: =VLOOKUP($O8,'records (2)'!$A:$Z,11,FALSE) -> Lucie GRANGER | AN8: 1 | AO8: 1000 | AP8: 1000 | AQ8: 0 | AR8: 0
A9: SABG-01649 | B9: GROUPE SAB | C9: SAB GROUPE | D9: 001IV000015SAHsYAO | E9: 01tIV00000GOfP1YAL | F9: Redevance d'utilisation - Tranche 25 ETP - Cas 1 | H9: Annual | I9: In advance | J9: 46023 | K9: 46387 | L9: Pixid France | M9: Pack C&S | N9: 46023 | O9: =VLOOKUP(D9,records!$A:$U,10,FALSE) -> 0012p00004TwEORAA3 | P9: =VLOOKUP(D9,records!$A:$V,20,FALSE) -> FR46305148884 | Q9: =VLOOKUP(D9,records!$A:$V,12,FALSE) -> 30 514 888 400 029 | R9: Paper | T9: Transfer | U9: Renewal | V9: =VLOOKUP($D9,records!$A:$V,3,FALSE) -> GROUPE SAB - FINANCIERE D'AZOLETTE sa | X9: =VLOOKUP($D9,records!$A:$V,9,FALSE) -> 1077 Route des 4 vents | Y9: =VLOOKUP($D9,records!$A:$V,4,FALSE) -> BELMONT DE LA LOIRE | Z9: =VLOOKUP($D9,records!$A:$V,7,FALSE) -> 42670 | AA9: Redevance 2026 | AB9: =VLOOKUP(O9,'records (2)'!$A:$Z,8,FALSE) -> 30 | AC9: FALSE | AF9: =VLOOKUP($D9,records!$A:$V,13,FALSE) -> GROUPE SAB - FINANCIERE D'AZOLETTE sa | AH9: =VLOOKUP($D9,records!$A:$V,19,FALSE) -> 1077 Route des 4 vents | AI9: =VLOOKUP($D9,records!$A:$V,14,FALSE) -> BELMONT DE LA LOIRE | AJ9: =VLOOKUP($O9,'records (2)'!$A:$Z,14,FALSE) -> 003IV000010tTsfYAE | AK9: =VLOOKUP($O9,'records (2)'!$A:$Z,15,FALSE) -> Christine GROSSELIN | AL9: =VLOOKUP($O9,'records (2)'!$A:$Z,10,FALSE) -> 003IV000010tTsfYAE | AM9: =VLOOKUP($O9,'records (2)'!$A:$Z,11,FALSE) -> Christine GROSSELIN | AN9: 1 | AO9: 1000 | AP9: 1000 | AQ9: 0 | AR9: 0
A10: HB76-01741 | B10: HABITAT 76 | C10: HABITAT 76 | D10: 001IV000015SAI5YAO | E10: 01tIV00000GyVCbYAN | F10: Redevance d'utilisation - Tranche 25 ETP - Cas 2 | H10: Annual | I10: In advance | J10: 46023 | K10: 46387 | L10: Pixid France | M10: Pack C&S | N10: 46023 | O10: =VLOOKUP(D10,records!$A:$U,10,FALSE) -> 001SZ000002Sv8iYAC | P10: =VLOOKUP(D10,records!$A:$V,20,FALSE) -> FR36781107446 | Q10: =VLOOKUP(D10,records!$A:$V,12,FALSE) -> 78 110 744 600 069 | R10: Paper | T10: Transfer | U10: Renewal | V10: =VLOOKUP($D10,records!$A:$V,3,FALSE) -> OFFICE PUBLIC DE L'HABITAT DU DEPARTEMENT DE SEINE-MARITIME | W10: =IFERROR(VLOOKUP($D10,records!$A:$V,6,FALSE),) -> HABITAT 76 - Service RHEC | X10: =VLOOKUP($D10,records!$A:$V,9,FALSE) -> 112 Boulevard d'Orléans | Y10: =VLOOKUP($D10,records!$A:$V,4,FALSE) -> ROUEN | Z10: =VLOOKUP($D10,records!$A:$V,7,FALSE) -> 76100 | AA10: Redevance 2026 | AB10: =VLOOKUP(O10,'records (2)'!$A:$Z,8,FALSE) -> 30 | AC10: =VLOOKUP(O10,'records (4)'!$A:$C,3,FALSE) -> TRUE | AD10: YES | AE10: 46023 | AF10: =VLOOKUP($D10,records!$A:$V,13,FALSE) -> OFFICE PUBLIC DE L'HABITAT DU DEPARTEMENT DE SEINE-MARITIME | AG10: =VLOOKUP($D10,records!$A:$V,16,FALSE) -> HABITAT 76 - Service RHEC | AH10: =VLOOKUP($D10,records!$A:$V,19,FALSE) -> 112 Boulevard d'Orléans | AI10: =VLOOKUP($D10,records!$A:$V,14,FALSE) -> ROUEN | AJ10: =VLOOKUP($O10,'records (2)'!$A:$Z,14,FALSE) -> 003IV000010rLj2YAE | AK10: =VLOOKUP($O10,'records (2)'!$A:$Z,15,FALSE) -> Mélissa AMGHAR | AL10: =VLOOKUP($O10,'records (2)'!$A:$Z,10,FALSE) -> 003IV000010rLj2YAE | AM10: =VLOOKUP($O10,'records (2)'!$A:$Z,11,FALSE) -> Mélissa AMGHAR | AN10: 1 | AO10: 3000 | AP10: 3000 | AQ10: 0 | AR10: 0
A11: TTPK-01534 | B11: TETRAPAK | C11: TETRAPAK | D11: 001IV000015S2eCYAS | E11: 01tIV00000GOfP1YAL | F11: Redevance d'utilisation - Tranche 25 ETP - Cas 1 | H11: Annual | I11: In advance | J11: 46023 | K11: 46387 | L11: Pixid France | M11: Pack C&S | N11: 46023 | O11: =VLOOKUP(D11,records!$A:$U,10,FALSE) -> 0012p00004OKNMCAA5 | P11: =VLOOKUP(D11,records!$A:$V,20,FALSE) -> FR30017150285 | Q11: =VLOOKUP(D11,records!$A:$V,12,FALSE) -> 1 715 028 500 066 | R11: Email | S11: =VLOOKUP(D11,records!$A:$U,19,FALSE) -> 144.accountspayable@ap.tetrapak.com | T11: Transfer | U11: Renewal | V11: =VLOOKUP($D11,records!$A:$V,3,FALSE) -> PAPETERIES DE DIJON snc | X11: =VLOOKUP($D11,records!$A:$V,9,FALSE) -> 3 rue Romelet | Y11: =VLOOKUP($D11,records!$A:$V,4,FALSE) -> LONGVIC | Z11: =VLOOKUP($D11,records!$A:$V,7,FALSE) -> 21600 | AA11: Redevance 2026 | AB11: =VLOOKUP(O11,'records (2)'!$A:$Z,8,FALSE) -> 30 | AC11: FALSE | AF11: =VLOOKUP($D11,records!$A:$V,13,FALSE) -> PAPETERIES DE DIJON snc | AG11: Facture originale électronique à | AH11: =VLOOKUP($D11,records!$A:$V,19,FALSE) -> 144.accountspayable@ap.tetrapak.com | AI11: =VLOOKUP($D11,records!$A:$V,14,FALSE) -> . | AJ11: =VLOOKUP($O11,'records (2)'!$A:$Z,14,FALSE) -> 003IV000010tRVxYAM | AK11: =VLOOKUP($O11,'records (2)'!$A:$Z,15,FALSE) -> Monika HORVATH (Accounting) | AL11: =VLOOKUP($O11,'records (2)'!$A:$Z,10,FALSE) -> 003IV000010tRVxYAM | AM11: =VLOOKUP($O11,'records (2)'!$A:$Z,11,FALSE) -> Monika HORVATH (Accounting) | AN11: 1 | AO11: 500 | AP11: 500 | AQ11: 0 | AR11: 0
A12: SNDM-01975 | B12: SNCF DOMAINE MATERIEL | C12: SNCF DOMAINE MATERIEL | D12: 001IV000015S541YAC | E12: 01tIV00000GOfP1YAL | F12: Redevance d'utilisation - Tranche 25 ETP - Cas 1 | H12: Annual | I12: In advance | J12: 46023 | K12: 46387 | L12: Pixid France | M12: Pack C&S | N12: 46023 | O12: =VLOOKUP(D12,records!$A:$U,10,FALSE) -> 001SZ00000DoG8ZYAV | P12: =VLOOKUP(D12,records!$A:$V,20,FALSE) -> FR55518697685 | Q12: =VLOOKUP(D12,records!$A:$V,12,FALSE) -> 51 869 768 502 383 | R12: Paper | T12: Transfer | U12: Renewal | V12: =VLOOKUP($D12,records!$A:$V,3,FALSE) -> SNCF DOMAINE MATERIEL | X12: =VLOOKUP($D12,records!$A:$V,9,FALSE) -> 16 rue Simone Veil | Y12: =VLOOKUP($D12,records!$A:$V,4,FALSE) -> SAINT-OUEN-SUR-SEINE | Z12: =VLOOKUP($D12,records!$A:$V,7,FALSE) -> 93400 | AA12: Redevance 2026 | AB12: =VLOOKUP(O12,'records (2)'!$A:$Z,8,FALSE) -> 30 | AC12: FALSE | AF12: =VLOOKUP($D12,records!$A:$V,13,FALSE) -> SNCF DOMAINE MATERIEL | AH12: =VLOOKUP($D12,records!$A:$V,19,FALSE) -> 16 rue Simone Veil | AI12: =VLOOKUP($D12,records!$A:$V,14,FALSE) -> SAINT-OUEN-SUR-SEINE | AJ12: =VLOOKUP($O12,'records (2)'!$A:$Z,14,FALSE) -> 003IV000010tNmEYAU | AK12: =VLOOKUP($O12,'records (2)'!$A:$Z,15,FALSE) -> Marine BOSCH | AL12: =VLOOKUP($O12,'records (2)'!$A:$Z,10,FALSE) -> 003IV000010tSjCYAU | AM12: =VLOOKUP($O12,'records (2)'!$A:$Z,11,FALSE) -> Lolita DE VITI | AN12: 1 | AO12: 1000 | AP12: 1000 | AQ12: 0 | AR12: 0
A13: ANTS-01879 | B13: AGCE NAT DES TITRES SECURISES | C13: ANTS | D13: 001IV000015S8izYAC | E13: 01tIV00000GOfP1YAL | F13: Redevance d'utilisation - Tranche 25 ETP - Cas 1 | H13: Annual | I13: In advance | J13: 46023 | K13: 46387 | L13: Pixid France | M13: Pack C&S | N13: 46023 | O13: =VLOOKUP(D13,records!$A:$U,10,FALSE) -> 001SZ000001s7vFYAQ | P13: =VLOOKUP(D13,records!$A:$V,20,FALSE) -> FR55130003262 | Q13: =VLOOKUP(D13,records!$A:$V,12,FALSE) -> 13 000 326 200 024 | R13: Paper | T13: Transfer | U13: Renewal | V13: =VLOOKUP($D13,records!$A:$V,3,FALSE) -> AGENCE NATIONALE DES TITRES SECURISES | X13: =VLOOKUP($D13,records!$A:$V,9,FALSE) -> 18 Rue Irénee Carré | Y13: =VLOOKUP($D13,records!$A:$V,4,FALSE) -> CHARLEVILLE-MEZIERES | Z13: =VLOOKUP($D13,records!$A:$V,7,FALSE) -> 8800 | AA13: Redevance 2026 | AB13: =VLOOKUP(O13,'records (2)'!$A:$Z,8,FALSE) -> 30 | AC13: =VLOOKUP(O13,'records (4)'!$A:$C,3,FALSE) -> TRUE | AD13: YES | AE13: 46023 | AF13: =VLOOKUP($D13,records!$A:$V,13,FALSE) -> AGENCE NATIONALE DES TITRES SECURISES | AH13: =VLOOKUP($D13,records!$A:$V,19,FALSE) -> 18 Rue Irénee Carré | AI13: =VLOOKUP($D13,records!$A:$V,14,FALSE) -> CHARLEVILLE-MEZIERES | AJ13: =VLOOKUP($O13,'records (2)'!$A:$Z,14,FALSE) -> 003IV000010tSnVYAU | AK13: =VLOOKUP($O13,'records (2)'!$A:$Z,15,FALSE) -> Service facturation | AL13: =VLOOKUP($O13,'records (2)'!$A:$Z,10,FALSE) -> 003IV000010tSnVYAU | AM13: =VLOOKUP($O13,'records (2)'!$A:$Z,11,FALSE) -> Service facturation | AN13: 1 | AO13: 500 | AP13: 500 | AQ13: 0 | AR13: 0
A14: MTBL-01521 | B14: MONT BLANC | C14: MONT BLANC | D14: 001IV000015S2eOYAS | E14: 01tIV00000GyVCbYAN | F14: Redevance d'utilisation - Tranche 25 ETP - Cas 2 | H14: Annual | I14: In advance | J14: 46023 | K14: 46387 | L14: Pixid France | M14: Pack C&S | N14: 46023 | O14: =VLOOKUP(D14,records!$A:$U,10,FALSE) -> 0012p00004MTowVAAT | P14: =VLOOKUP(D14,records!$A:$V,20,FALSE) -> FR56448954362 | Q14: =VLOOKUP(D14,records!$A:$V,12,FALSE) -> 44 895 436 200 043 | R14: Paper | T14: Transfer | U14: Renewal | V14: =VLOOKUP($D14,records!$A:$V,3,FALSE) -> MONT BLANC sas | W14: =IFERROR(VLOOKUP($D14,records!$A:$V,6,FALSE),) -> RH | X14: =VLOOKUP($D14,records!$A:$V,9,FALSE) -> 2 rue du Capitaine Rex Combs | Y14: =VLOOKUP($D14,records!$A:$V,4,FALSE) -> CHEF DU PONT | Z14: =VLOOKUP($D14,records!$A:$V,7,FALSE) -> 50480 | AA14: Redevance 2026 | AB14: =VLOOKUP(O14,'records (2)'!$A:$Z,8,FALSE) -> 30 | AC14: FALSE | AF14: =VLOOKUP($D14,records!$A:$V,13,FALSE) -> MONT BLANC sas | AH14: =VLOOKUP($D14,records!$A:$V,19,FALSE) -> 2 rue du Capitaine Rex Combs | AI14: =VLOOKUP($D14,records!$A:$V,14,FALSE) -> CHEF DU PONT | AJ14: =VLOOKUP($O14,'records (2)'!$A:$Z,14,FALSE) -> 003IV000010t1w0YAA | AK14: =VLOOKUP($O14,'records (2)'!$A:$Z,15,FALSE) -> Lise BAJIC | AL14: =VLOOKUP($O14,'records (2)'!$A:$Z,10,FALSE) -> 003IV000010t1w0YAA | AM14: =VLOOKUP($O14,'records (2)'!$A:$Z,11,FALSE) -> Lise BAJIC | AN14: 1 | AO14: 2000 | AP14: 2000 | AQ14: 0 | AR14: 0
A15: FRFM-01755 | B15: Groupe SFPI | C15: Groupe SFPI | D15: 001IV000015S868YAC | E15: 01tIV00000GOfP1YAL | F15: Redevance d'utilisation - Tranche 25 ETP - Cas 1 | H15: Annual | I15: In advance | J15: 46023 | K15: 46387 | L15: Pixid France | M15: Pack C&S | N15: 46023 | O15: =VLOOKUP(D15,records!$A:$U,10,FALSE) -> 001SZ000003jyZNYAY | P15: =VLOOKUP(D15,records!$A:$V,20,FALSE) -> FR26393588595 | Q15: =VLOOKUP(D15,records!$A:$V,12,FALSE) -> 39 358 859 500 065 | R15: Paper | T15: Transfer | U15: Renewal | V15: =VLOOKUP($D15,records!$A:$V,3,FALSE) -> GROUPE SFPI sa | X15: =VLOOKUP($D15,records!$A:$V,9,FALSE) -> 20 Rue de L'Arc de Triomphe | Y15: =VLOOKUP($D15,records!$A:$V,4,FALSE) -> PARIS | Z15: =VLOOKUP($D15,records!$A:$V,7,FALSE) -> 75017 | AA15: Redevance 2026 | AB15: =VLOOKUP(O15,'records (2)'!$A:$Z,8,FALSE) -> 30 | AC15: FALSE | AF15: =VLOOKUP($D15,records!$A:$V,13,FALSE) -> GROUPE SFPI sa | AH15: =VLOOKUP($D15,records!$A:$V,19,FALSE) -> 20 Rue de L'Arc de Triomphe | AI15: =VLOOKUP($D15,records!$A:$V,14,FALSE) -> PARIS | AJ15: =VLOOKUP($O15,'records (2)'!$A:$Z,14,FALSE) -> 003IV000010tIdSYAU | AK15: =VLOOKUP($O15,'records (2)'!$A:$Z,15,FALSE) -> Laura DI BARTOLOMEO | AL15: =VLOOKUP($O15,'records (2)'!$A:$Z,10,FALSE) -> 003IV000010tIdSYAU | AM15: =VLOOKUP($O15,'records (2)'!$A:$Z,11,FALSE) -> Laura DI BARTOLOMEO | AN15: 1 | AO15: 2500 | AP15: 2500 | AQ15: 0 | AR15: 0
A16: BCRT-01784 | B16: BACCARAT | C16: BACCARAT | D16: 001IV000015SAI6YAO | E16: 01tIV00000GOfP1YAL | F16: Redevance d'utilisation - Tranche 25 ETP - Cas 1 | H16: Annual | I16: In advance | J16: 46023 | K16: 46387 | L16: Pixid France | M16: Pack C&S | N16: 46023 | O16: =VLOOKUP(D16,records!$A:$U,10,FALSE) -> 001SZ000004kQ5GYAU | P16: =VLOOKUP(D16,records!$A:$V,20,FALSE) -> FR86760800060 | Q16: =VLOOKUP(D16,records!$A:$V,12,FALSE) -> 76 080 006 000 013 | R16: Paper | T16: Transfer | U16: Renewal | V16: =VLOOKUP($D16,records!$A:$V,3,FALSE) -> BACCARAT sa | X16: =VLOOKUP($D16,records!$A:$V,9,FALSE) -> 20 Rue des Cristalleries | Y16: =VLOOKUP($D16,records!$A:$V,4,FALSE) -> BACCARAT | Z16: =VLOOKUP($D16,records!$A:$V,7,FALSE) -> 54120 | AA16: Redevance 2026 | AB16: =VLOOKUP(O16,'records (2)'!$A:$Z,8,FALSE) -> 30 | AC16: FALSE | AF16: =VLOOKUP($D16,records!$A:$V,13,FALSE) -> BACCARAT sa | AH16: =VLOOKUP($D16,records!$A:$V,19,FALSE) -> 20 Rue des Cristalleries | AI16: =VLOOKUP($D16,records!$A:$V,14,FALSE) -> BACCARAT | AJ16: =VLOOKUP($O16,'records (2)'!$A:$Z,14,FALSE) -> 003IV000010su8iYAA | AK16: =VLOOKUP($O16,'records (2)'!$A:$Z,15,FALSE) -> Compta Fournisseurs BACCARAT | AL16: =VLOOKUP($O16,'records (2)'!$A:$Z,10,FALSE) -> 003IV000010su8iYAA | AM16: =VLOOKUP($O16,'records (2)'!$A:$Z,11,FALSE) -> Compta Fournisseurs BACCARAT | AN16: 1 | AO16: 500 | AP16: 500 | AQ16: 0 | AR16: 0
A17: MCBD-01903 | B17: MCBRIDE S.A.S | C17: MC BRIDE SAS | D17: 001IV000015RyE0YAK | E17: 01tIV00000GyVCbYAN | F17: Redevance d'utilisation - Tranche 25 ETP - Cas 2 | H17: Annual | I17: In advance | J17: 46023 | K17: 46387 | L17: Pixid France | M17: Pack C&S | N17: 46023 | O17: =VLOOKUP(D17,records!$A:$U,10,FALSE) -> 001SZ000008J7IzYAK | P17: =VLOOKUP(D17,records!$A:$V,20,FALSE) -> FR10391159548 | Q17: =VLOOKUP(D17,records!$A:$V,12,FALSE) -> 39 115 954 800 034 | R17: Paper | T17: Transfer | U17: Renewal | V17: =VLOOKUP($D17,records!$A:$V,3,FALSE) -> McBRIDE S.A.S | X17: =VLOOKUP($D17,records!$A:$V,9,FALSE) -> 20 Rue Gustave Flaubert | Y17: =VLOOKUP($D17,records!$A:$V,4,FALSE) -> MOYAUX | Z17: =VLOOKUP($D17,records!$A:$V,7,FALSE) -> 14590 | AA17: Redevance 2026 | AB17: =VLOOKUP(O17,'records (2)'!$A:$Z,8,FALSE) -> 45 | AC17: =VLOOKUP(O17,'records (4)'!$A:$C,3,FALSE) -> TRUE | AD17: YES | AE17: 46023 | AF17: =VLOOKUP($D17,records!$A:$V,13,FALSE) -> McBRIDE S.A.S | AH17: =VLOOKUP($D17,records!$A:$V,19,FALSE) -> 20 Rue Gustave Flaubert | AI17: =VLOOKUP($D17,records!$A:$V,14,FALSE) -> MOYAUX | AJ17: =VLOOKUP($O17,'records (2)'!$A:$Z,14,FALSE) -> 003IV000010tJZpYAM | AK17: =VLOOKUP($O17,'records (2)'!$A:$Z,15,FALSE) -> Aurélie PETIT | AL17: =VLOOKUP($O17,'records (2)'!$A:$Z,10,FALSE) -> 003IV000010tJZpYAM | AM17: =VLOOKUP($O17,'records (2)'!$A:$Z,11,FALSE) -> Aurélie PETIT | AN17: 1 | AO17: 3000 | AP17: 3000 | AQ17: 0 | AR17: 0
A18: PSTC-01541 | B18: PASTACORP | C18: PASTACORP (PACK C&S) | D18: 001IV000015SAFeYAO | E18: 01tIV00000GOfP1YAL | F18: Redevance d'utilisation - Tranche 25 ETP - Cas 1 | H18: Annual | I18: In advance | J18: 46023 | K18: 46387 | L18: Pixid France | M18: Pack C&S | N18: 46023 | O18: =VLOOKUP(D18,records!$A:$U,10,FALSE) -> 0012p00004Nh7mSAAR | P18: =VLOOKUP(D18,records!$A:$V,20,FALSE) -> FR88829809482 | Q18: =VLOOKUP(D18,records!$A:$V,12,FALSE) -> 82 980 948 200 039 | R18: Paper | T18: Transfer | U18: Renewal | V18: =VLOOKUP($D18,records!$A:$V,3,FALSE) -> PASTACORP TRAITEUR sas | W18: =IFERROR(VLOOKUP($D18,records!$A:$V,6,FALSE),) -> Ressources Humaines | X18: =VLOOKUP($D18,records!$A:$V,9,FALSE) -> 21 Rue de Borolan | Y18: =VLOOKUP($D18,records!$A:$V,4,FALSE) -> CHAMBERY | Z18: =VLOOKUP($D18,records!$A:$V,7,FALSE) -> 73000 | AA18: Redevance 2026 | AB18: =VLOOKUP(O18,'records (2)'!$A:$Z,8,FALSE) -> 30 | AC18: FALSE | AF18: =VLOOKUP($D18,records!$A:$V,13,FALSE) -> PASTACORP TRAITEUR sas | AH18: =VLOOKUP($D18,records!$A:$V,19,FALSE) -> 21 Rue de Borolan | AI18: =VLOOKUP($D18,records!$A:$V,14,FALSE) -> CHAMBERY | AJ18: =VLOOKUP($O18,'records (2)'!$A:$Z,14,FALSE) -> 003IV000010rvHPYAY | AK18: =VLOOKUP($O18,'records (2)'!$A:$Z,15,FALSE) -> Lory LAGACHE (Facturation) | AL18: =VLOOKUP($O18,'records (2)'!$A:$Z,10,FALSE) -> 003IV000010rvHFYAY | AM18: =VLOOKUP($O18,'records (2)'!$A:$Z,11,FALSE) -> Lory LAGACHE | AN18: 1 | AO18: 1000 | AP18: 1000 | AQ18: 0 | AR18: 0
A19: AUTJ-01690 | B19: AUTAJON FRANCE | C19: AUTAJON GROUPE | D19: 001IV000015RhU6YAK | E19: 01tIV00000GyVCbYAN | F19: Redevance d'utilisation - Tranche 25 ETP - Cas 2 | H19: Annual | I19: In advance | J19: 46023 | K19: 46387 | L19: Pixid France | M19: Pack C&S | N19: 46023 | O19: =VLOOKUP(D19,records!$A:$U,10,FALSE) -> 0012p00004MzQWLAA3 | P19: =VLOOKUP(D19,records!$A:$V,20,FALSE) -> FR59538487885 | Q19: =VLOOKUP(D19,records!$A:$V,12,FALSE) -> 34 787 539 500 013 | R19: Paper | T19: Transfer | U19: Renewal | V19: =VLOOKUP($D19,records!$A:$V,3,FALSE) -> AUTAJON SERVICES sasu | X19: =VLOOKUP($D19,records!$A:$V,9,FALSE) -> 36 route d'Espeluche- CS 40149 | Y19: =VLOOKUP($D19,records!$A:$V,4,FALSE) -> MONTELIMAR CEDEX | Z19: =VLOOKUP($D19,records!$A:$V,7,FALSE) -> 26216 | AA19: Redevance 2026 | AB19: =VLOOKUP(O19,'records (2)'!$A:$Z,8,FALSE) -> 30 | AC19: FALSE | AF19: =VLOOKUP($D19,records!$A:$V,13,FALSE) -> AUTAJON SERVICES sasu | AH19: =VLOOKUP($D19,records!$A:$V,19,FALSE) -> 36 route d'Espeluche- CS 40149 | AI19: =VLOOKUP($D19,records!$A:$V,14,FALSE) -> MONTELIMAR CEDEX | AJ19: =VLOOKUP($O19,'records (2)'!$A:$Z,14,FALSE) -> 003IV000010rv3eYAA | AK19: =VLOOKUP($O19,'records (2)'!$A:$Z,15,FALSE) -> Evelyne VICHARD | AL19: =VLOOKUP($O19,'records (2)'!$A:$Z,10,FALSE) -> 003IV000010t2ZTYAY | AM19: =VLOOKUP($O19,'records (2)'!$A:$Z,11,FALSE) -> Michele MOLINA | AN19: 1 | AO19: 9000 | AP19: 9000 | AQ19: 0 | AR19: 0
A20: PIDF-01796 | B20: POINT P IDF | C20: POINT P IDF | D20: 001IV000015RyDxYAK | E20: 01tIV00000GOfP1YAL | F20: Redevance d'utilisation - Tranche 25 ETP - Cas 1 | H20: Annual | I20: In advance | J20: 46023 | K20: 46387 | L20: Pixid France | M20: Pack C&S | N20: 46023 | O20: =VLOOKUP(D20,records!$A:$U,10,FALSE) -> 001SZ000004rtaLYAQ | P20: =VLOOKUP(D20,records!$A:$V,20,FALSE) -> FR73695680108 | Q20: =VLOOKUP(D20,records!$A:$V,12,FALSE) -> 69 568 010 802 753 | R20: Paper | T20: Transfer | U20: Renewal | V20: =VLOOKUP($D20,records!$A:$V,3,FALSE) -> POINT. P S.A.S. | W20: =IFERROR(VLOOKUP($D20,records!$A:$V,6,FALSE),) -> IDF - BCR | X20: =VLOOKUP($D20,records!$A:$V,9,FALSE) -> 9 rue Chappe Gessalin | Y20: =VLOOKUP($D20,records!$A:$V,4,FALSE) -> BRIE COMTE ROBERT | Z20: =VLOOKUP($D20,records!$A:$V,7,FALSE) -> 77170 | AA20: Redevance 2026 | AB20: =VLOOKUP(O20,'records (2)'!$A:$Z,8,FALSE) -> 30 | AC20: FALSE | AF20: =VLOOKUP($D20,records!$A:$V,13,FALSE) -> POINT P IDF | AH20: =VLOOKUP($D20,records!$A:$V,19,FALSE) -> 4 Boulevard Jean Moulin - CS10429 | AI20: =VLOOKUP($D20,records!$A:$V,14,FALSE) -> NANTES | AJ20: =VLOOKUP($O20,'records (2)'!$A:$Z,14,FALSE) -> 003IV000010rlbQYAQ | AK20: =VLOOKUP($O20,'records (2)'!$A:$Z,15,FALSE) -> Clara ARCHER | AL20: =VLOOKUP($O20,'records (2)'!$A:$Z,10,FALSE) -> 003IV000010rlbQYAQ | AM20: =VLOOKUP($O20,'records (2)'!$A:$Z,11,FALSE) -> Clara ARCHER | AN20: 1 | AO20: 1500 | AP20: 1500 | AQ20: 0 | AR20: 0
A21: LSIF-01703 | B21: LIS FRANCE | C21: LIS FRANCE | D21: 001IV000015S8iTYAS | E21: 01tIV00000GOfP1YAL | F21: Redevance d'utilisation - Tranche 25 ETP - Cas 1 | H21: Annual | I21: In advance | J21: 46023 | K21: 46387 | L21: Pixid France | M21: Pack C&S | N21: 46023 | O21: =VLOOKUP(D21,records!$A:$U,10,FALSE) -> 0012p00004UJFBRAA5 | P21: =VLOOKUP(D21,records!$A:$V,20,FALSE) -> FR12692015266 | Q21: =VLOOKUP(D21,records!$A:$V,12,FALSE) -> 69 201 526 600 020 | R21: Paper | T21: Transfer | U21: Renewal | V21: =VLOOKUP($D21,records!$A:$V,3,FALSE) -> LIS France sa | W21: =IFERROR(VLOOKUP($D21,records!$A:$V,6,FALSE),) -> Service RH | X21: =VLOOKUP($D21,records!$A:$V,9,FALSE) -> 67 rue de la Gare | Y21: =VLOOKUP($D21,records!$A:$V,4,FALSE) -> CERENCES | Z21: =VLOOKUP($D21,records!$A:$V,7,FALSE) -> 50510 | AA21: Redevance 2026 | AB21: =VLOOKUP(O21,'records (2)'!$A:$Z,8,FALSE) -> 30 | AC21: FALSE | AF21: =VLOOKUP($D21,records!$A:$V,13,FALSE) -> LIS France sa | AH21: =VLOOKUP($D21,records!$A:$V,19,FALSE) -> 67 rue de la Gare | AI21: =VLOOKUP($D21,records!$A:$V,14,FALSE) -> CERENCES | AJ21: =VLOOKUP($O21,'records (2)'!$A:$Z,14,FALSE) -> 003IV000010sxFvYAI | AK21: =VLOOKUP($O21,'records (2)'!$A:$Z,15,FALSE) -> Franck MORIN | AL21: =VLOOKUP($O21,'records (2)'!$A:$Z,10,FALSE) -> 003IV000010tRVeYAM | AM21: =VLOOKUP($O21,'records (2)'!$A:$Z,11,FALSE) -> Viviane PAWLAK - (compta) | AN21: 1 | AO21: 1000 | AP21: 1000 | AQ21: 0 | AR21: 0
A22: ALMG-01848 | B22: ALMA GROUPE | C22: ALMA GROUPE | D22: 001IV000015RyDjYAK | E22: 01tIV00000GyVCbYAN | F22: Redevance d'utilisation - Tranche 25 ETP - Cas 2 | H22: Annual | I22: In advance | J22: 46023 | K22: 46387 | L22: Pixid France | M22: Pack C&S | N22: 46023 | O22: =VLOOKUP(D22,records!$A:$U,10,FALSE) -> 0012p00004UHPDrAAP | P22: =VLOOKUP(D22,records!$A:$V,20,FALSE) -> FR31304488794 | Q22: =VLOOKUP(D22,records!$A:$V,12,FALSE) -> 30 448 879 400 146 | R22: Paper | T22: Transfer | U22: Renewal | V22: =VLOOKUP($D22,records!$A:$V,3,FALSE) -> ALMA SA | X22: =VLOOKUP($D22,records!$A:$V,9,FALSE) -> 70 Avenue des Sources | Y22: =VLOOKUP($D22,records!$A:$V,4,FALSE) -> SAINT- YORRE | Z22: =VLOOKUP($D22,records!$A:$V,7,FALSE) -> 3270 | AA22: Redevance 2026 | AB22: =VLOOKUP(O22,'records (2)'!$A:$Z,8,FALSE) -> 30 | AC22: FALSE | AF22: =VLOOKUP($D22,records!$A:$V,13,FALSE) -> ALMA SA | AH22: =VLOOKUP($D22,records!$A:$V,19,FALSE) -> 70 Avenue des Sources | AI22: =VLOOKUP($D22,records!$A:$V,14,FALSE) -> SAINT- YORRE | AJ22: =VLOOKUP($O22,'records (2)'!$A:$Z,14,FALSE) -> 003IV000010tJXDYA2 | AK22: =VLOOKUP($O22,'records (2)'!$A:$Z,15,FALSE) -> Olivier GIRAUD | AL22: =VLOOKUP($O22,'records (2)'!$A:$Z,10,FALSE) -> 003IV000010tJXDYA2 | AM22: =VLOOKUP($O22,'records (2)'!$A:$Z,11,FALSE) -> Olivier GIRAUD | AN22: 1 | AO22: 9000 | AP22: 9000 | AQ22: 0 | AR22: 0
A23: SAES-01653 | B23: SENIOR AEROSPACE ERMETO S.A.S | C23: SENIOR | D23: 001IV000015S50LYAS | E23: 01tIV00000GOfP1YAL | F23: Redevance d'utilisation - Tranche 25 ETP - Cas 1 | H23: Annual | I23: In advance | J23: 46023 | K23: 46387 | L23: Pixid France | M23: Pack C&S | N23: 46023 | O23: =VLOOKUP(D23,records!$A:$U,10,FALSE) -> 0012p00004RIoWPAA1 | P23: =VLOOKUP(D23,records!$A:$V,20,FALSE) -> FR37440285401 | Q23: =VLOOKUP(D23,records!$A:$V,12,FALSE) -> 44 028 540 100 053 | R23: Paper | T23: Transfer | U23: Renewal | V23: =VLOOKUP($D23,records!$A:$V,3,FALSE) -> SENIOR AEROSPACE ERMETO SAS | X23: =VLOOKUP($D23,records!$A:$V,9,FALSE) -> 8 rue du Clos Thomas - BP 30 | Y23: =VLOOKUP($D23,records!$A:$V,4,FALSE) -> FOSSÉ | Z23: =VLOOKUP($D23,records!$A:$V,7,FALSE) -> 41330 | AA23: Redevance 2026 | AB23: =VLOOKUP(O23,'records (2)'!$A:$Z,8,FALSE) -> 30 | AC23: FALSE | AF23: =VLOOKUP($D23,records!$A:$V,13,FALSE) -> SENIOR AEROSPACE ERMETO SAS | AH23: =VLOOKUP($D23,records!$A:$V,19,FALSE) -> 8 rue du Clos Thomas - BP 30 | AI23: =VLOOKUP($D23,records!$A:$V,14,FALSE) -> FOSSÉ | AJ23: =VLOOKUP($O23,'records (2)'!$A:$Z,14,FALSE) -> 003IV000010tQI5YAM | AK23: =VLOOKUP($O23,'records (2)'!$A:$Z,15,FALSE) -> Prescillia MORIS | AL23: =VLOOKUP($O23,'records (2)'!$A:$Z,10,FALSE) -> 003IV000010tQI6YAM | AM23: =VLOOKUP($O23,'records (2)'!$A:$Z,11,FALSE) -> Fabienne POTAGE LEGOFF | AN23: 1 | AO23: 1000 | AP23: 1000 | AQ23: 0 | AR23: 0
A24: ELDN-01899 | B24: ELYDAN SAS | C24: ELYDAN sas | D24: 001IV000015SAI9YAO | E24: 01tIV00000GyVCbYAN | F24: Redevance d'utilisation - Tranche 25 ETP - Cas 2 | H24: Annual | I24: In advance | J24: 46023 | K24: 46387 | L24: Pixid France | M24: Pack C&S | N24: 46023 | O24: =VLOOKUP(D24,records!$A:$U,10,FALSE) -> 001SZ000007iWoDYAU | P24: =VLOOKUP(D24,records!$A:$V,20,FALSE) -> FR26388062796 | Q24: =VLOOKUP(D24,records!$A:$V,12,FALSE) -> 38 806 279 600 080 | R24: Email | S24: =VLOOKUP(D24,records!$A:$W,19,FALSE) -> acano@elydan.eu | T24: Transfer | U24: Renewal | V24: =VLOOKUP($D24,records!$A:$V,3,FALSE) -> ELYDAN sas | W24: =IFERROR(VLOOKUP($D24,records!$A:$V,6,FALSE),) -> Ressources Humaines | X24: =VLOOKUP($D24,records!$A:$V,9,FALSE) -> 127 Avenue Louis Bleriot | Y24: =VLOOKUP($D24,records!$A:$V,4,FALSE) -> SAINT ETIENNE DE SAINT GEOIRS | Z24: =VLOOKUP($D24,records!$A:$V,7,FALSE) -> 38590 | AA24: Redevance 2026 | AB24: =VLOOKUP(O24,'records (2)'!$A:$Z,8,FALSE) -> 30 | AC24: FALSE | AF24: =VLOOKUP($D24,records!$A:$V,13,FALSE) -> ELYDAN sas | AG24: Facture originale électronique à | AH24: =VLOOKUP($D24,records!$A:$V,19,FALSE) -> acano@elydan.eu | AI24: =VLOOKUP($D24,records!$A:$V,14,FALSE) -> . | AJ24: =VLOOKUP($O24,'records (2)'!$A:$Z,14,FALSE) -> 003IV000010sqLJYAY | AK24: =VLOOKUP($O24,'records (2)'!$A:$Z,15,FALSE) -> Facture Elydan | AL24: =VLOOKUP($O24,'records (2)'!$A:$Z,10,FALSE) -> 003IV000010sqLKYAY | AM24: =VLOOKUP($O24,'records (2)'!$A:$Z,11,FALSE) -> Relance Factures Elydan | AN24: 1 | AO24: 3000 | AP24: 3000 | AQ24: 0 | AR24: 0
A25: RVMA-01671 | B25: REVIMA | C25: REVIMA | D25: 001IV000015RyL0YAK | E25: 01tIV00000GOfP6YAL | F25: Redevance d'utilisation - ETP EU | H25: Annual | I25: In advance | J25: 46023 | K25: 46387 | L25: Pixid France | M25: Pack C&S | N25: 46023 | O25: =VLOOKUP(D25,records!$A:$U,10,FALSE) -> 0012p00004THFNVAA5 | P25: =VLOOKUP(D25,records!$A:$V,20,FALSE) -> FR75542071329 | Q25: =VLOOKUP(D25,records!$A:$V,12,FALSE) -> 54 207 132 900 024 | R25: Email | S25: =VLOOKUP(D25,records!$A:$W,19,FALSE) -> account.payable@revima.fr | T25: Transfer | U25: Renewal | V25: =VLOOKUP($D25,records!$A:$V,3,FALSE) -> REVIMA sasu | X25: =VLOOKUP($D25,records!$A:$V,9,FALSE) -> 1 Avenue du Latham 47 | Y25: =VLOOKUP($D25,records!$A:$V,4,FALSE) -> RIVES-EN-SEINE | Z25: =VLOOKUP($D25,records!$A:$V,7,FALSE) -> 76490 | AA25: Redevance 2026 | AB25: =VLOOKUP(O25,'records (2)'!$A:$Z,8,FALSE) -> 30 | AC25: FALSE | AF25: =VLOOKUP($D25,records!$A:$V,13,FALSE) -> REVIMA sasu | AG25: Facture originale électronique à | AH25: =VLOOKUP($D25,records!$A:$V,19,FALSE) -> account.payable@revima.fr | AI25: =VLOOKUP($D25,records!$A:$V,14,FALSE) -> . | AJ25: =VLOOKUP($O25,'records (2)'!$A:$Z,14,FALSE) -> 003IV000010tIiXYAU | AK25: =VLOOKUP($O25,'records (2)'!$A:$Z,15,FALSE) -> Facturation REVIMA | AL25: =VLOOKUP($O25,'records (2)'!$A:$Z,10,FALSE) -> 003IV000010tIiXYAU | AM25: =VLOOKUP($O25,'records (2)'!$A:$Z,11,FALSE) -> Facturation REVIMA | AN25: 1 | AO25: 2000 | AP25: 2000 | AQ25: 0 | AR25: 0
A26: MMGS-01617 | B26: MILLET MOUNTAIN GROUP | C26: MILLET MOUNTAIN GROUP SAS | D26: 001IV000015S50KYAS | E26: 01tIV00000GOfP1YAL | F26: Redevance d'utilisation - Tranche 25 ETP - Cas 1 | H26: Annual | I26: In advance | J26: 46023 | K26: 46387 | L26: Pixid France | M26: Pack C&S | N26: 46023 | O26: =VLOOKUP(D26,records!$A:$U,10,FALSE) -> 0012p00004RDYqlAAH | P26: =VLOOKUP(D26,records!$A:$V,20,FALSE) -> FR38400313318 | Q26: =VLOOKUP(D26,records!$A:$V,12,FALSE) -> 40 031 331 800 026 | R26: Email | S26: =VLOOKUP(D26,records!$A:$U,19,FALSE) -> accounting.millet@milletmountaingroup.com | T26: Transfer | U26: Renewal | V26: =VLOOKUP($D26,records!$A:$V,3,FALSE) -> MILLET MOUNTAIN GROUP SAS | X26: =VLOOKUP($D26,records!$A:$V,9,FALSE) -> 21 rue du Pré Faucon | Y26: =VLOOKUP($D26,records!$A:$V,4,FALSE) -> ANNECY LE VIEUX CEDEX | Z26: =VLOOKUP($D26,records!$A:$V,7,FALSE) -> 74943 | AA26: Redevance 2026 | AB26: =VLOOKUP(O26,'records (2)'!$A:$Z,8,FALSE) -> 30 | AC26: FALSE | AF26: =VLOOKUP($D26,records!$A:$V,13,FALSE) -> MILLET MOUNTAIN GROUP SAS | AG26: Facture originale électronique à | AH26: =VLOOKUP($D26,records!$A:$V,19,FALSE) -> accounting.millet@milletmountaingroup.com | AI26: =VLOOKUP($D26,records!$A:$V,14,FALSE) -> . | AJ26: =VLOOKUP($O26,'records (2)'!$A:$Z,14,FALSE) -> 003IV000010tQIMYA2 | AK26: =VLOOKUP($O26,'records (2)'!$A:$Z,15,FALSE) -> Olivier LENESTOUR (accounting) | AL26: =VLOOKUP($O26,'records (2)'!$A:$Z,10,FALSE) -> 003IV000010tQIMYA2 | AM26: =VLOOKUP($O26,'records (2)'!$A:$Z,11,FALSE) -> Olivier LENESTOUR (accounting) | AN26: 1 | AO26: 500 | AP26: 500 | AQ26: 0 | AR26: 0
A27: AFCB-01660 | B27: AMPHENOL FCI BESANCON | C27: AMPHENOL FCI | D27: 001IV000015SAHqYAO | E27: 01tIV00000GOfP1YAL | F27: Redevance d'utilisation - Tranche 25 ETP - Cas 1 | H27: Annual | I27: In advance | J27: 46023 | K27: 46387 | L27: Pixid France | M27: Pack C&S | N27: 46023 | O27: =VLOOKUP(D27,records!$A:$U,10,FALSE) -> 0012p00004ReLR9AAN | P27: =VLOOKUP(D27,records!$A:$V,20,FALSE) -> FR91388636896 | Q27: =VLOOKUP(D27,records!$A:$V,12,FALSE) -> 38 863 689 600 010 | R27: Email | S27: =VLOOKUP(D27,records!$A:$U,19,FALSE) -> accounts-payable.besancon@fci.com | T27: Transfer | U27: Renewal | V27: =VLOOKUP($D27,records!$A:$V,3,FALSE) -> AMPHENOL FCI BESANCON sas | X27: =VLOOKUP($D27,records!$A:$V,9,FALSE) -> 2 Rue Lafayette | Y27: =VLOOKUP($D27,records!$A:$V,4,FALSE) -> BESANCON | Z27: =VLOOKUP($D27,records!$A:$V,7,FALSE) -> 25000 | AA27: Redevance 2026 | AB27: =VLOOKUP(O27,'records (2)'!$A:$Z,8,FALSE) -> 30 | AC27: FALSE | AF27: =VLOOKUP($D27,records!$A:$V,13,FALSE) -> AMPHENOL FCI BESANCON sas | AG27: Facture originale électronique à | AH27: =VLOOKUP($D27,records!$A:$V,19,FALSE) -> accounts-payable.besancon@fci.com | AI27: =VLOOKUP($D27,records!$A:$V,14,FALSE) -> . | AJ27: =VLOOKUP($O27,'records (2)'!$A:$Z,14,FALSE) -> 003IV000010t1XAYAY | AK27: =VLOOKUP($O27,'records (2)'!$A:$Z,15,FALSE) -> Jemil ISHAK-BOUSHAKI | AL27: =VLOOKUP($O27,'records (2)'!$A:$Z,10,FALSE) -> 003IV000010t1XAYAY | AM27: =VLOOKUP($O27,'records (2)'!$A:$Z,11,FALSE) -> Jemil ISHAK-BOUSHAKI | AN27: 1 | AO27: 1000 | AP27: 1000 | AQ27: 0 | AR27: 0
A28: TAFS-01646 | B28: TENNECO AUTOMOTIVE | C28: TENNECO AUTOMOTIVE FRANCE SAS | D28: 001IV000015RyDiYAK | E28: 01tIV00000GOfP1YAL | F28: Redevance d'utilisation - Tranche 25 ETP - Cas 1 | H28: Annual | I28: In advance | J28: 46023 | K28: 46387 | L28: Pixid France | M28: Pack C&S | N28: 46023 | O28: =VLOOKUP(D28,records!$A:$U,10,FALSE) -> 0012p00004TGrjrAAD | P28: =VLOOKUP(D28,records!$A:$V,20,FALSE) -> FR29555450071 | Q28: =VLOOKUP(D28,records!$A:$V,12,FALSE) -> 55 545 007 100 041 | R28: Email | S28: =VLOOKUP(D28,records!$A:$U,19,FALSE) -> AccountsPayableFrance@Tenneco.com | T28: Transfer | U28: Renewal | V28: =VLOOKUP($D28,records!$A:$V,3,FALSE) -> TENNECO AUTOMOTIVE FRANCE SAS | X28: =VLOOKUP($D28,records!$A:$V,9,FALSE) -> ZA des Giraumeries | Y28: =VLOOKUP($D28,records!$A:$V,4,FALSE) -> SAINT BERTHEVIN | Z28: =VLOOKUP($D28,records!$A:$V,7,FALSE) -> 53940 | AA28: Redevance 2026 | AB28: =VLOOKUP(O28,'records (2)'!$A:$Z,8,FALSE) -> 30 | AC28: FALSE | AF28: =VLOOKUP($D28,records!$A:$V,13,FALSE) -> TENNECO AUTOMOTIVE FRANCE SAS | AG28: Facture originale électronique à | AH28: =VLOOKUP($D28,records!$A:$V,19,FALSE) -> AccountsPayableFrance@Tenneco.com | AI28: =VLOOKUP($D28,records!$A:$V,14,FALSE) -> . | AJ28: =VLOOKUP($O28,'records (2)'!$A:$Z,14,FALSE) -> 003IV000010tJXCYA2 | AK28: =VLOOKUP($O28,'records (2)'!$A:$Z,15,FALSE) -> Sandrine LEVECQUE | AL28: =VLOOKUP($O28,'records (2)'!$A:$Z,10,FALSE) -> 003IV000010tJXCYA2 | AM28: =VLOOKUP($O28,'records (2)'!$A:$Z,11,FALSE) -> Sandrine LEVECQUE | AN28: 1 | AO28: 500 | AP28: 500 | AQ28: 0 | AR28: 0
A29: EXCV-01801 | B29: EXCELVISION | C29: EXCELVISION | D29: 001IV000015S2SQYA0 | E29: 01tIV00000GOfP1YAL | F29: Redevance d'utilisation - Tranche 25 ETP - Cas 1 | H29: Annual | I29: In advance | J29: 46023 | K29: 46387 | L29: Pixid France | M29: Pack C&S | N29: 46023 | O29: =VLOOKUP(D29,records!$A:$U,10,FALSE) -> 0012p00004UJG6aAAH | P29: =VLOOKUP(D29,records!$A:$V,20,FALSE) -> FR82335820684 | Q29: =VLOOKUP(D29,records!$A:$V,12,FALSE) -> 33 582 068 400 033 | R29: Email | S29: =VLOOKUP(D29,records!$A:$U,19,FALSE) -> accueilfactures.excelvision@fareva.com | T29: Transfer | U29: Renewal | V29: =VLOOKUP($D29,records!$A:$V,3,FALSE) -> EXCELVISION sas | X29: =VLOOKUP($D29,records!$A:$V,9,FALSE) -> 27 Rue de la Lombardière | Y29: =VLOOKUP($D29,records!$A:$V,4,FALSE) -> ANNONAY | Z29: =VLOOKUP($D29,records!$A:$V,7,FALSE) -> 7100 | AA29: Redevance 2026 | AB29: =VLOOKUP(O29,'records (2)'!$A:$Z,8,FALSE) -> 60 | AC29: FALSE | AF29: =VLOOKUP($D29,records!$A:$V,13,FALSE) -> EXCELVISION sas | AG29: Facture originale électronique à | AH29: =VLOOKUP($D29,records!$A:$V,19,FALSE) -> accueilfactures.excelvision@fareva.com | AI29: =VLOOKUP($D29,records!$A:$V,14,FALSE) -> . | AJ29: =VLOOKUP($O29,'records (2)'!$A:$Z,14,FALSE) -> 003IV000010t687YAA | AK29: =VLOOKUP($O29,'records (2)'!$A:$Z,15,FALSE) -> Service Comptabilité | AL29: =VLOOKUP($O29,'records (2)'!$A:$Z,10,FALSE) -> 003IV000010t688YAA | AM29: =VLOOKUP($O29,'records (2)'!$A:$Z,11,FALSE) -> Frédéric DE ROMELIN | AN29: 1 | AO29: 500 | AP29: 500 | AQ29: 0 | AR29: 0
A30: LLMD-01802 | B30: SOCIETE LALLEMAND | C30: CALIDA GROUP (LALLEMAND) | D30: 001IV000015RyDzYAK | E30: 01tIV00000GOfP1YAL | F30: Redevance d'utilisation - Tranche 25 ETP - Cas 1 | H30: Annual | I30: In advance | J30: 46023 | K30: 46387 | L30: Pixid France | M30: Pack C&S | N30: 46023 | O30: =VLOOKUP(D30,records!$A:$U,10,FALSE) -> 001SZ000005Od72YAC | P30: =VLOOKUP(D30,records!$A:$V,20,FALSE) -> FR44773201108 | Q30: =VLOOKUP(D30,records!$A:$V,12,FALSE) -> 77 320 110 800 018 | R30: Email | S30: =VLOOKUP(D30,records!$A:$U,19,FALSE) -> adminlallemand@lafuma-mobilier.fr | T30: Transfer | U30: Renewal | V30: =VLOOKUP($D30,records!$A:$V,3,FALSE) -> LALLEMAND SAS | X30: =VLOOKUP($D30,records!$A:$V,9,FALSE) -> Le Balmay | Y30: =VLOOKUP($D30,records!$A:$V,4,FALSE) -> VIEU D'IZENAVE | Z30: =VLOOKUP($D30,records!$A:$V,7,FALSE) -> 1430 | AA30: Redevance 2026 | AB30: =VLOOKUP(O30,'records (2)'!$A:$Z,8,FALSE) -> 30 | AC30: FALSE | AF30: =VLOOKUP($D30,records!$A:$V,13,FALSE) -> LALLEMAND SAS | AG30: Facture originale électronique à | AH30: =VLOOKUP($D30,records!$A:$V,19,FALSE) -> adminlallemand@lafuma-mobilier.fr | AI30: =VLOOKUP($D30,records!$A:$V,14,FALSE) -> . | AJ30: =VLOOKUP($O30,'records (2)'!$A:$Z,14,FALSE) -> 003IV000010su8mYAA | AK30: =VLOOKUP($O30,'records (2)'!$A:$Z,15,FALSE) -> Fabrice CORMORECHE | AL30: =VLOOKUP($O30,'records (2)'!$A:$Z,10,FALSE) -> 003IV000010su8mYAA | AM30: =VLOOKUP($O30,'records (2)'!$A:$Z,11,FALSE) -> Fabrice CORMORECHE | AN30: 1 | AO30: 500 | AP30: 500
A31: KSBS-01588 | B31: KSB | C31: KSB CHATEAUROUX | D31: 001IV000015S85hYAC | E31: 01tIV00000GOfP1YAL | F31: Redevance d'utilisation - Tranche 25 ETP - Cas 1 | H31: Annual | I31: In advance | J31: 46023 | K31: 46387 | L31: Pixid France | M31: Pack C&S | N31: 46023 | O31: =VLOOKUP(D31,records!$A:$U,10,FALSE) -> 0012p00004RmixTAAR | P31: =VLOOKUP(D31,records!$A:$V,20,FALSE) -> FR20569801897 | Q31: =VLOOKUP(D31,records!$A:$V,12,FALSE) -> 56 980 189 700 103 | R31: Email | S31: =VLOOKUP(D31,records!$A:$U,19,FALSE) -> alexandra.rongy@ksb.com | T31: Transfer | U31: Renewal | V31: =VLOOKUP($D31,records!$A:$V,3,FALSE) -> KSB SAS | X31: =VLOOKUP($D31,records!$A:$V,9,FALSE) -> Allée de Sagan | Y31: =VLOOKUP($D31,records!$A:$V,4,FALSE) -> CHATEAUROUX | Z31: =VLOOKUP($D31,records!$A:$V,7,FALSE) -> 36000 | AA31: Redevance 2026 | AB31: =VLOOKUP(O31,'records (2)'!$A:$Z,8,FALSE) -> 30 | AC31: FALSE | AF31: =VLOOKUP($D31,records!$A:$V,13,FALSE) -> KSB SAS | AG31: Facture originale électronique à | AH31: =VLOOKUP($D31,records!$A:$V,19,FALSE) -> alexandra.rongy@ksb.com | AI31: =VLOOKUP($D31,records!$A:$V,14,FALSE) -> . | AJ31: =VLOOKUP($O31,'records (2)'!$A:$Z,14,FALSE) -> 003IV000010tIdmYAE | AK31: =VLOOKUP($O31,'records (2)'!$A:$Z,15,FALSE) -> Thomas BRUNEAU | AL31: =VLOOKUP($O31,'records (2)'!$A:$Z,10,FALSE) -> 003IV000010sxGoYAI | AM31: =VLOOKUP($O31,'records (2)'!$A:$Z,11,FALSE) -> Fabienne BOISBOURDIN | AN31: 1 | AO31: 500 | AP31: 500 | AQ31: 0 | AR31: 0
A32: PRMS-01766 | B32: BERRY BEAUTE MAROLLES | C32: BERRY GLOBAL - PROMENS - (EX PGI) | D32: 001IV000015S867YAC | E32: 01tIV00000GOfP1YAL | F32: Redevance d'utilisation - Tranche 25 ETP - Cas 1 | G32: BERRY BEAUTE MAROLLES | H32: Annual | I32: In advance | J32: 46023 | K32: 46387 | L32: Pixid France | M32: Pack C&S | N32: 46023 | O32: =VLOOKUP(D32,records!$A:$U,10,FALSE) -> 001SZ000003ZJXVYA4 | P32: =VLOOKUP(D32,records!$A:$V,20,FALSE) -> FR52759200454 | Q32: =VLOOKUP(D32,records!$A:$V,12,FALSE) -> 75 920 045 400 156 | R32: Email | S32: alexandragrossat@berryglobal.com | T32: Transfer | U32: Renewal | V32: =VLOOKUP($D32,records!$A:$V,3,FALSE) -> PROMENS SA | X32: =VLOOKUP($D32,records!$A:$V,9,FALSE) -> 5 Rue Castellion | Y32: =VLOOKUP($D32,records!$A:$V,4,FALSE) -> BELLIGNAT | Z32: 01100 | AA32: Redevance 2026 | AB32: =VLOOKUP(O32,'records (2)'!$A:$Z,8,FALSE) -> 30 | AC32: =VLOOKUP(O32,'records (4)'!$A:$C,3,FALSE) -> TRUE | AD32: YES | AE32: 46023 | AF32: =VLOOKUP($D32,records!$A:$V,13,FALSE) -> PROMENS SA | AG32: Facture originale électronique à | AH32: alexandragrossat@berryglobal.com | AI32: =VLOOKUP($D32,records!$A:$V,14,FALSE) -> . | AJ32: =VLOOKUP($O32,'records (2)'!$A:$Z,14,FALSE) -> 003IV000010su8aYAA | AK32: =VLOOKUP($O32,'records (2)'!$A:$Z,15,FALSE) -> Alexandra GROSSAT | AL32: =VLOOKUP($O32,'records (2)'!$A:$Z,10,FALSE) -> 003IV000010su8aYAA | AM32: =VLOOKUP($O32,'records (2)'!$A:$Z,11,FALSE) -> Alexandra GROSSAT | AN32: 1 | AO32: 1500 | AP32: 1500 | AQ32: 0 | AR32: 0
A33: Pas de code facture | B33: BERRY BRAMLAGE | C33: BERRY BRAMLAGE | D33: 001IV000015S867YAC | E33: 01tIV00000GOfP1YAL | F33: Redevance d'utilisation - Tranche 25 ETP - Cas 1 | G33: BERRY BRAMLAGE | H33: Annual | I33: In advance | J33: 46023 | K33: 46387 | L33: Pixid France | M33: Pack C&S | N33: 46023 | O33: =VLOOKUP(D33,records!$A:$U,10,FALSE) -> 001SZ000003ZJXVYA4 | P33: FR52759200454 | Q33: 75920045400156 | R33: Email | S33: alexandragrossat@berryglobal.com | T33: Transfer | U33: Renewal | V33: PROMENS SA | X33: 5 Rue Castellion | Y33: BELLIGNAT | Z33: 01100 | AA33: Redevance 2026 | AB33: =VLOOKUP(O33,'records (2)'!$A:$Z,8,FALSE) -> 30 | AC33: =VLOOKUP(O33,'records (4)'!$A:$C,3,FALSE) -> TRUE | AD33: YES | AE33: 46023 | AF33: PROMENS SA | AG33: Facture originale électronique à | AH33: alexandragrossat@berryglobal.com | AI33: . | AJ33: 003IV000010su8aYAA | AK33: Alexandra GROSSAT | AL33: 003IV000010su8aYAA | AM33: Alexandra GROSSAT | AN33: 1 | AO33: 1000 | AP33: 1000 | AQ33: 0 | AR33: Redevance pas facturé en 2025
A34: DFOS-01629 | B34: DANFOSS | C34: DANFOSS | D34: 001IV000015S50OYAS | E34: 01tIV00000GOfP1YAL | F34: Redevance d'utilisation - Tranche 25 ETP - Cas 1 | H34: Annual | I34: In advance | J34: 46023 | K34: 46387 | L34: Pixid France | M34: Pack C&S | N34: 46023 | O34: =VLOOKUP(D34,records!$A:$U,10,FALSE) -> 0012p00004SxGjuAAF | P34: =VLOOKUP(D34,records!$A:$V,20,FALSE) -> FR80713780278 | Q34: =VLOOKUP(D34,records!$A:$V,12,FALSE) -> 71 378 027 800 030 | R34: Email | S34: =VLOOKUP(D34,records!$A:$U,19,FALSE) -> amelie.chesneau@danfoss.com | T34: Transfer | U34: Renewal | V34: =VLOOKUP($D34,records!$A:$V,3,FALSE) -> DANFOSS COMMERCIAL COMPRESSORS sa | W34: =IFERROR(VLOOKUP($D34,records!$A:$V,6,FALSE),) -> Comptabilité | X34: =VLOOKUP($D34,records!$A:$V,9,FALSE) -> ZI de Reyrieux - BP331 | Y34: =VLOOKUP($D34,records!$A:$V,4,FALSE) -> TREVOUX | Z34: =VLOOKUP($D34,records!$A:$V,7,FALSE) -> 1600 | AA34: Redevance 2026 | AB34: =VLOOKUP(O34,'records (2)'!$A:$Z,8,FALSE) -> 45 | AC34: =VLOOKUP(O34,'records (4)'!$A:$C,3,FALSE) -> TRUE | AD34: YES | AE34: 46023 | AF34: =VLOOKUP($D34,records!$A:$V,13,FALSE) -> DANFOSS COMMERCIAL COMPRESSORS sa | AG34: Facture originale électronique à | AH34: =VLOOKUP($D34,records!$A:$V,19,FALSE) -> amelie.chesneau@danfoss.com | AI34: . | AJ34: =VLOOKUP($O34,'records (2)'!$A:$Z,14,FALSE) -> 003IV000010t7J0YAI | AK34: =VLOOKUP($O34,'records (2)'!$A:$Z,15,FALSE) -> Sylvie BERTOIN | AL34: =VLOOKUP($O34,'records (2)'!$A:$Z,10,FALSE) -> 003IV000010tIiJYAU | AM34: =VLOOKUP($O34,'records (2)'!$A:$Z,11,FALSE) -> Corinne ROCHA | AN34: 1 | AO34: 2000 | AP34: 2000 | AQ34: 0 | AR34: 0
A35: FRCS-01805 | B35: SISLEY INDUSTRIE | C35: FRANCOS - (SISLEY) | D35: 001IV000015RyDwYAK | E35: 01tIV00000GyVCbYAN | F35: Redevance d'utilisation - Tranche 25 ETP - Cas 2 | H35: Annual | I35: In advance | J35: 46023 | K35: 46387 | L35: Pixid France | M35: Pack C&S | N35: 46023 | O35: =VLOOKUP(D35,records!$A:$U,10,FALSE) -> 001SZ000004b5HnYAI | P35: =VLOOKUP(D35,records!$A:$V,20,FALSE) -> FR62450982343 | Q35: =VLOOKUP(D35,records!$A:$V,12,FALSE) -> 45 098 234 300 011 | R35: Email | S35: =VLOOKUP(D35,records!$A:$U,19,FALSE) -> amelie.rousselot@francos.fr | T35: Transfer | U35: Renewal | V35: =VLOOKUP($D35,records!$A:$V,3,FALSE) -> FRANCOS sasu | X35: =VLOOKUP($D35,records!$A:$V,9,FALSE) -> 1 Rue des Mardeaux | Y35: =VLOOKUP($D35,records!$A:$V,4,FALSE) -> BLOIS | Z35: =VLOOKUP($D35,records!$A:$V,7,FALSE) -> 41000 | AA35: Redevance 2026 | AB35: =VLOOKUP(O35,'records (2)'!$A:$Z,8,FALSE) -> 30 | AC35: FALSE | AF35: =VLOOKUP($D35,records!$A:$V,13,FALSE) -> FRANCOS sasu | AG35: Facture originale électronique à | AH35: =VLOOKUP($D35,records!$A:$V,19,FALSE) -> amelie.rousselot@francos.fr | AI35: . | AJ35: =VLOOKUP($O35,'records (2)'!$A:$Z,14,FALSE) -> 003IV000010t2BcYAI | AK35: =VLOOKUP($O35,'records (2)'!$A:$Z,15,FALSE) -> Amelie ROUSSELOT | AL35: =VLOOKUP($O35,'records (2)'!$A:$Z,10,FALSE) -> 003IV000010t2BcYAI | AM35: =VLOOKUP($O35,'records (2)'!$A:$Z,11,FALSE) -> Amelie ROUSSELOT | AN35: 1 | AO35: 1000 | AP35: 1000 | AQ35: 0 | AR35: 0
A36: VSTP-01868 | B36: VOESTALPINE | C36: VOESTALPINE | D36: 001IV000015S2eKYAS | E36: 01tIV00000GOfP1YAL | F36: Redevance d'utilisation - Tranche 25 ETP - Cas 1 | H36: Annual | I36: In advance | J36: 46023 | K36: 46387 | L36: Pixid France | M36: Pack C&S | N36: 46023 | O36: =VLOOKUP(D36,records!$A:$U,10,FALSE) -> 001SZ000001pKNXYA2 | P36: =VLOOKUP(D36,records!$A:$V,20,FALSE) -> FR12535520316 | Q36: =VLOOKUP(D36,records!$A:$V,12,FALSE) -> 53 552 031 600 014 | R36: Email | S36: =VLOOKUP(D36,records!$A:$U,19,FALSE) -> andrea.cametti@voestalpine.com | T36: Transfer | U36: Renewal | V36: =VLOOKUP($D36,records!$A:$V,3,FALSE) -> VOESTALPINE AUTOMOTIVE COMPONENTS FONTAINE sa | X36: =VLOOKUP($D36,records!$A:$V,9,FALSE) -> Zac de l'Aéroparc | Y36: =VLOOKUP($D36,records!$A:$V,4,FALSE) -> FONTAINE | Z36: =VLOOKUP($D36,records!$A:$V,7,FALSE) -> 90150 | AA36: Redevance 2026 | AB36: =VLOOKUP(O36,'records (2)'!$A:$Z,8,FALSE) -> 30 | AC36: FALSE | AF36: =VLOOKUP($D36,records!$A:$V,13,FALSE) -> VOESTALPINE AUTOMOTIVE COMPONENTS FONTAINE sa | AG36: Facture originale électronique à | AH36: =VLOOKUP($D36,records!$A:$V,19,FALSE) -> andrea.cametti@voestalpine.com | AI36: . | AJ36: =VLOOKUP($O36,'records (2)'!$A:$Z,14,FALSE) -> 003IV000010su9YYAQ | AK36: =VLOOKUP($O36,'records (2)'!$A:$Z,15,FALSE) -> Christine BONTEMPS | AL36: =VLOOKUP($O36,'records (2)'!$A:$Z,10,FALSE) -> 003IV000010su9YYAQ | AM36: =VLOOKUP($O36,'records (2)'!$A:$Z,11,FALSE) -> Christine BONTEMPS | AN36: 1 | AO36: 500 | AP36: 500 | AQ36: 0 | AR36: 0
A37: LBSP-01837 | B37: BIO SPRINGER | C37: LESAFFRE - BIO SPRINGER | D37: 001IV000015S8j3YAC | E37: 01tIV00000GyVCbYAN | F37: Redevance d'utilisation - Tranche 25 ETP - Cas 2 | H37: Annual | I37: In advance | J37: 46023 | K37: 46387 | L37: Pixid France | M37: Pack C&S | N37: 46023 | O37: =VLOOKUP(D37,records!$A:$U,10,FALSE) -> 001SZ000003YcdpYAC | P37: =VLOOKUP(D37,records!$A:$V,20,FALSE) -> FR93542091996 | Q37: =VLOOKUP(D37,records!$A:$V,12,FALSE) -> 54 209 199 600 026 | R37: Email | S37: =VLOOKUP(D37,records!$A:$U,19,FALSE) -> ap.biospringer@lesaffre.com | T37: Transfer | U37: Renewal | V37: =VLOOKUP($D37,records!$A:$V,3,FALSE) -> BIO SPRINGER sa | W37: =IFERROR(VLOOKUP($D37,records!$A:$V,6,FALSE),) -> Ressources Humaines | X37: =VLOOKUP($D37,records!$A:$V,9,FALSE) -> 103 Rue Jean Jaurès | Y37: =VLOOKUP($D37,records!$A:$V,4,FALSE) -> MAISONS-ALFORT | Z37: =VLOOKUP($D37,records!$A:$V,7,FALSE) -> 94700 | AA37: Redevance 2026 | AB37: =VLOOKUP(O37,'records (2)'!$A:$Z,8,FALSE) -> 60 | AC37: =VLOOKUP(O37,'records (4)'!$A:$C,3,FALSE) -> TRUE | AD37: YES | AE37: 46023 | AF37: =VLOOKUP($D37,records!$A:$V,13,FALSE) -> BIO SPRINGER sa | AG37: Facture originale électronique à | AH37: =VLOOKUP($D37,records!$A:$V,19,FALSE) -> ap.biospringer@lesaffre.com | AI37: . | AJ37: =VLOOKUP($O37,'records (2)'!$A:$Z,14,FALSE) -> 003IV000010tSnLYAU | AK37: =VLOOKUP($O37,'records (2)'!$A:$Z,15,FALSE) -> Morgane PEREZ | AL37: =VLOOKUP($O37,'records (2)'!$A:$Z,10,FALSE) -> 003IV000010sqM3YAI | AM37: =VLOOKUP($O37,'records (2)'!$A:$Z,11,FALSE) -> Contact Recouvrement LESAFFRE - BIO SPRINGER | AN37: 1 | AO37: 2000 | AP37: 2000 | AQ37: 0 | AR37: 0
A38: NMRV-01867 | B38: NEMERA SERVICES | C38: NEMERA | D38: 001IV000015S8jFYAS | E38: 01tIV00000GOfP1YAL | F38: Redevance d'utilisation - Tranche 25 ETP - Cas 1 | H38: Annual | I38: In advance | J38: 46023 | K38: 46387 | L38: Pixid France | M38: Pack C&S | N38: 46023 | O38: =VLOOKUP(D38,records!$A:$U,10,FALSE) -> 001SZ00000BFAySYAX | P38: =VLOOKUP(D38,records!$A:$V,20,FALSE) -> FR81388056962 | Q38: =VLOOKUP(D38,records!$A:$V,12,FALSE) -> 38 805 696 200 029 | R38: Email | S38: =VLOOKUP(D38,records!$A:$U,19,FALSE) -> ap.invoicesnemeralaverpilliere@nemera.net | T38: Transfer | U38: Renewal | V38: =VLOOKUP($D38,records!$A:$V,3,FALSE) -> NEMERA LA VERPILIERE sas | X38: =VLOOKUP($D38,records!$A:$V,9,FALSE) -> 20 Avenue de la Gare | Y38: =VLOOKUP($D38,records!$A:$V,4,FALSE) -> LA VERPILLIERE | Z38: =VLOOKUP($D38,records!$A:$V,7,FALSE) -> 38290 | AA38: Redevance 2026 | AB38: =VLOOKUP(O38,'records (2)'!$A:$Z,8,FALSE) -> 30 | AC38: =VLOOKUP(O38,'records (4)'!$A:$C,3,FALSE) -> TRUE | AD38: YES | AE38: 46023 | AF38: =VLOOKUP($D38,records!$A:$V,13,FALSE) -> NEMERA LA VERPILIERE sas | AG38: Facture originale électronique à | AH38: =VLOOKUP($D38,records!$A:$V,19,FALSE) -> ap.invoicesnemeralaverpilliere@nemera.net | AI38: . | AJ38: =VLOOKUP($O38,'records (2)'!$A:$Z,14,FALSE) -> 003IV000010su9XYAQ | AK38: =VLOOKUP($O38,'records (2)'!$A:$Z,15,FALSE) -> Laurence DALLEMAGNE | AL38: =VLOOKUP($O38,'records (2)'!$A:$Z,10,FALSE) -> 003IV000010su9XYAQ | AM38: =VLOOKUP($O38,'records (2)'!$A:$Z,11,FALSE) -> Laurence DALLEMAGNE | AN38: 1 | AO38: 2000 | AP38: 2000 | AQ38: 0 | AR38: 0
A39: KSBR-01791 | B39: KSB LA ROCHE CHALAIS | C39: KSB LA ROCHE CHALAIS | D39: 001IV000015S862YAC | E39: 01tIV00000GOfP1YAL | F39: Redevance d'utilisation - Tranche 25 ETP - Cas 1 | H39: Annual | I39: In advance | J39: 46023 | K39: 46387 | L39: Pixid France | M39: Pack C&S | N39: 46023 | O39: =VLOOKUP(D39,records!$A:$U,10,FALSE) -> 0012p00004UIt7LAAT | P39: =VLOOKUP(D39,records!$A:$V,20,FALSE) -> FR20569801897 | Q39: =VLOOKUP(D39,records!$A:$V,12,FALSE) -> 56 980 189 700 632 | R39: Email | S39: =VLOOKUP(D39,records!$A:$U,19,FALSE) -> ap_invoices_fr@ksb.com | T39: Transfer | U39: Renewal | V39: =VLOOKUP($D39,records!$A:$V,3,FALSE) -> KSB SAS | W39: =IFERROR(VLOOKUP($D39,records!$A:$V,6,FALSE),) -> Comptabilité fournisseurs | X39: =VLOOKUP($D39,records!$A:$V,9,FALSE) -> 4 Allée des Barbanniers | Y39: =VLOOKUP($D39,records!$A:$V,4,FALSE) -> GENNEVILLIERS | Z39: =VLOOKUP($D39,records!$A:$V,7,FALSE) -> 92230 | AA39: Redevance 2026 | AB39: =VLOOKUP(O39,'records (2)'!$A:$Z,8,FALSE) -> 30 | AC39: FALSE | AF39: =VLOOKUP($D39,records!$A:$V,13,FALSE) -> KSB SAS | AG39: Facture originale électronique à | AH39: =VLOOKUP($D39,records!$A:$V,19,FALSE) -> ap_invoices_fr@ksb.com | AI39: . | AJ39: =VLOOKUP($O39,'records (2)'!$A:$Z,14,FALSE) -> 003IV000010su8fYAA | AK39: =VLOOKUP($O39,'records (2)'!$A:$Z,15,FALSE) -> Hervé DECROOS | AL39: =VLOOKUP($O39,'records (2)'!$A:$Z,10,FALSE) -> 003IV000010su8gYAA | AM39: =VLOOKUP($O39,'records (2)'!$A:$Z,11,FALSE) -> Valérie RAYNAUD | AN39: 1 | AO39: 500 | AP39: 500 | AQ39: 0 | AR39: 0
A40: IVCF-01793 | B40: INVACARE France | C40: INVACARE FRANCE OPERATIONS | D40: 001IV000015S2SUYA0 | E40: 01tIV00000GyVCbYAN | F40: Redevance d'utilisation - Tranche 25 ETP - Cas 2 | H40: Annual | I40: In advance | J40: 46023 | K40: 46387 | L40: Pixid France | M40: Pack C&S | N40: 46023 | O40: =VLOOKUP(D40,records!$A:$U,10,FALSE) -> 001SZ0000059VWTYA2 | P40: =VLOOKUP(D40,records!$A:$V,20,FALSE) -> FR19348418732 | Q40: =VLOOKUP(D40,records!$A:$V,12,FALSE) -> 34 841 873 200 049 | R40: Email | S40: =VLOOKUP(D40,records!$A:$U,19,FALSE) -> ap3110ivcfranceoperations@invacare.com | T40: Transfer | U40: Renewal | V40: =VLOOKUP($D40,records!$A:$V,3,FALSE) -> INVACARE FRANCE OPERATIONS SAS | X40: =VLOOKUP($D40,records!$A:$V,9,FALSE) -> Route de Saint- Roch | Y40: =VLOOKUP($D40,records!$A:$V,4,FALSE) -> FONDETTES | Z40: =VLOOKUP($D40,records!$A:$V,7,FALSE) -> 37230 | AA40: Redevance 2026 | AB40: =VLOOKUP(O40,'records (2)'!$A:$Z,8,FALSE) -> 30 | AC40: FALSE | AF40: =VLOOKUP($D40,records!$A:$V,13,FALSE) -> INVACARE FRANCE OPERATIONS SAS | AG40: Facture originale électronique à | AH40: =VLOOKUP($D40,records!$A:$V,19,FALSE) -> ap3110ivcfranceoperations@invacare.com | AI40: . | AJ40: =VLOOKUP($O40,'records (2)'!$A:$Z,14,FALSE) -> 003IV000010su8kYAA | AK40: =VLOOKUP($O40,'records (2)'!$A:$Z,15,FALSE) -> Stéphane CHEBROUX (ap3110ivcfr) | AL40: =VLOOKUP($O40,'records (2)'!$A:$Z,10,FALSE) -> 003IV000010su8kYAA | AM40: =VLOOKUP($O40,'records (2)'!$A:$Z,11,FALSE) -> Stéphane CHEBROUX (ap3110ivcfr) | AN40: 1 | AO40: 3000 | AP40: 3000 | AQ40: 0 | AR40: 0
A41: CHVP-01985 | B41: CHEMVIRON PARENTIS | C41: CHEMVIRON PARENTIS SAS | D41: 001IV000015RyECYA0 | E41: 01tIV00000GyVCbYAN | F41: Redevance d'utilisation - Tranche 25 ETP - Cas 2 | H41: Annual | I41: In advance | J41: 46023 | K41: 46387 | L41: Pixid France | M41: Pack C&S | N41: 46023 | O41: =VLOOKUP(D41,records!$A:$U,10,FALSE) -> 001SZ00000YI0h9YAD | P41: =VLOOKUP(D41,records!$A:$V,20,FALSE) -> FR27930267059 | Q41: =VLOOKUP(D41,records!$A:$V,12,FALSE) -> 93 026 705 900 028 | R41: Email | S41: =VLOOKUP(D41,records!$A:$U,19,FALSE) -> apchemvironparentis.ccc@kuraray.com | T41: Transfer | U41: Renewal | V41: =VLOOKUP($D41,records!$A:$V,3,FALSE) -> CHEMVRION PARENTIS SAS | X41: =VLOOKUP($D41,records!$A:$V,9,FALSE) -> 58 Avenue de Wagram | Y41: =VLOOKUP($D41,records!$A:$V,4,FALSE) -> PARIS | Z41: =VLOOKUP($D41,records!$A:$V,7,FALSE) -> 75017 | AA41: Redevance 2026 | AB41: =VLOOKUP(O41,'records (2)'!$A:$Z,8,FALSE) -> 30 | AC41: =VLOOKUP(O41,'records (4)'!$A:$C,3,FALSE) -> TRUE | AD41: YES | AE41: 46023 | AF41: =VLOOKUP($D41,records!$A:$V,13,FALSE) -> CHEMVRION PARENTIS SAS | AG41: Facture originale électronique à | AH41: =VLOOKUP($D41,records!$A:$V,19,FALSE) -> apchemvironparentis.ccc@kuraray.com | AI41: . | AJ41: =VLOOKUP($O41,'records (2)'!$A:$Z,14,FALSE) -> 003IV000010t9wwYAA | AK41: =VLOOKUP($O41,'records (2)'!$A:$Z,15,FALSE) -> Catherine BOGEMANS | AL41: =VLOOKUP($O41,'records (2)'!$A:$Z,10,FALSE) -> 003IV000010t9wwYAA | AM41: =VLOOKUP($O41,'records (2)'!$A:$Z,11,FALSE) -> Catherine BOGEMANS | AN41: 1 | AO41: 1000 | AP41: 1000
A42: ASTZ-01930 | B42: ASTRAZENECA | C42: ASTRAZENECA | D42: 001IV000015RzTQYA0 | E42: 01tIV00000GyVCbYAN | F42: Redevance d'utilisation - Tranche 25 ETP - Cas 2 | H42: Annual | I42: In advance | J42: 46023 | K42: 46387 | L42: Pixid France | M42: Pack C&S | N42: 46023 | O42: =VLOOKUP(D42,records!$A:$U,10,FALSE) -> 001SZ00000Lspr7YAB | P42: =VLOOKUP(D42,records!$A:$V,20,FALSE) -> FR78448139634 | Q42: =VLOOKUP(D42,records!$A:$V,12,FALSE) -> 44 813 963 400 019 | R42: Email | S42: =VLOOKUP(D42,records!$A:$U,19,FALSE) -> apinvoicesdunkerque@astrazeneca.com | T42: Transfer | U42: Renewal | V42: =VLOOKUP($D42,records!$A:$V,3,FALSE) -> ASTRA ZENECA DUNKERQUE PRODUCTION scs | X42: =VLOOKUP($D42,records!$A:$V,9,FALSE) -> 224 Avenue de la Dordogne | Y42: =VLOOKUP($D42,records!$A:$V,4,FALSE) -> DUNKERQUE | Z42: =VLOOKUP($D42,records!$A:$V,7,FALSE) -> 59640 | AA42: Redevance 2026 | AB42: =VLOOKUP(O42,'records (2)'!$A:$Z,8,FALSE) -> 60 | AC42: =VLOOKUP(O42,'records (4)'!$A:$C,3,FALSE) -> TRUE | AD42: YES | AE42: 46023 | AF42: =VLOOKUP($D42,records!$A:$V,13,FALSE) -> ASTRA ZENECA DUNKERQUE PRODUCTION scs | AG42: Facture originale électronique à | AH42: =VLOOKUP($D42,records!$A:$V,19,FALSE) -> apinvoicesdunkerque@astrazeneca.com | AI42: . | AJ42: =VLOOKUP($O42,'records (2)'!$A:$Z,14,FALSE) -> 003IV000010tJa7YAE | AK42: =VLOOKUP($O42,'records (2)'!$A:$Z,15,FALSE) -> Compta-Facturation ASTRAZENECA | AL42: =VLOOKUP($O42,'records (2)'!$A:$Z,10,FALSE) -> 003IV000010tJa7YAE | AM42: =VLOOKUP($O42,'records (2)'!$A:$Z,11,FALSE) -> Compta-Facturation ASTRAZENECA | AN42: 1 | AO42: 7000 | AP42: 7000 | AQ42: 0 | AR42: 0
A43: BPEF-01789 | B43: BALL PACKAGING EUROPE | C43: BALL PACKAGING GROUPE | D43: 001IV000015RhU5YAK | E43: 01tIV00000GOfP6YAL | F43: Redevance d'utilisation - ETP EU | H43: Annual | I43: In advance | J43: 46023 | K43: 46387 | L43: Pixid France | M43: Pack C&S | N43: 46023 | O43: =VLOOKUP(D43,records!$A:$U,10,FALSE) -> 0012p00004MygGUAAZ | P43: =VLOOKUP(D43,records!$A:$V,20,FALSE) -> FR46349516005 | Q43: =VLOOKUP(D43,records!$A:$V,12,FALSE) -> 34 951 600 500 015 | R43: Email | S43: =VLOOKUP(D43,records!$A:$U,19,FALSE) -> apinvoicesfr@ball.com | T43: Transfer | U43: Renewal | V43: =VLOOKUP($D43,records!$A:$V,3,FALSE) -> BALL PACKAGING EUROPE FRANCE sasu | X43: =VLOOKUP($D43,records!$A:$V,9,FALSE) -> Zone d'Entreprises de Bergues | Y43: =VLOOKUP($D43,records!$A:$V,4,FALSE) -> BIERNE | Z43: =VLOOKUP($D43,records!$A:$V,7,FALSE) -> 59380 | AA43: Redevance 2026 | AB43: =VLOOKUP(O43,'records (2)'!$A:$Z,8,FALSE) -> 30 | AC43: FALSE | AF43: =VLOOKUP($D43,records!$A:$V,13,FALSE) -> BALL PACKAGING EUROPE FRANCE sasu | AG43: Facture originale électronique à | AH43: =VLOOKUP($D43,records!$A:$V,19,FALSE) -> apinvoicesfr@ball.com | AI43: . | AJ43: =VLOOKUP($O43,'records (2)'!$A:$Z,14,FALSE) -> 003IV000010t2FaYAI | AK43: =VLOOKUP($O43,'records (2)'!$A:$Z,15,FALSE) -> Erwan MORVAN | AL43: =VLOOKUP($O43,'records (2)'!$A:$Z,10,FALSE) -> 003IV000010t2FaYAI | AM43: =VLOOKUP($O43,'records (2)'!$A:$Z,11,FALSE) -> Erwan MORVAN | AN43: 1 | AO43: 1080 | AP43: 1080 | AQ43: 0 | AR43: 0
A44: CHRV-01811 | B44: CHARLES RIVER LABORATOIRE France | C44: CHARLES RIVER LABORATOIRE FRANCE CRLF sasu | D44: 001IV000015RzTcYAK | E44: 01tIV00000GyVCbYAN | F44: Redevance d'utilisation - Tranche 25 ETP - Cas 2 | H44: Annual | I44: In advance | J44: 46023 | K44: 46387 | L44: Pixid France | M44: Pack C&S | N44: 46023 | O44: =VLOOKUP(D44,records!$A:$U,10,FALSE) -> 0012p00004UHMmUAAX | P44: =VLOOKUP(D44,records!$A:$V,20,FALSE) -> FR29086650041 | Q44: =VLOOKUP(D44,records!$A:$V,12,FALSE) -> 8 665 004 100 022 | R44: Email | S44: =VLOOKUP(D44,records!$A:$U,19,FALSE) -> ARBCOMPTACRF@crl.com | T44: Transfer | U44: Renewal | V44: =VLOOKUP($D44,records!$A:$V,3,FALSE) -> CHARLES RIVER LABORATORIES FRANCE - C.R.L.F. sasu | W44: =IFERROR(VLOOKUP($D44,records!$A:$V,6,FALSE),) -> COMPTABILITE | X44: =VLOOKUP($D44,records!$A:$V,9,FALSE) -> 327 Impasse du Domaine Rozier | Y44: =VLOOKUP($D44,records!$A:$V,4,FALSE) -> SAINT GERMAIN NUELLES | Z44: =VLOOKUP($D44,records!$A:$V,7,FALSE) -> 69210 | AA44: Redevance 2026 | AB44: =VLOOKUP(O44,'records (2)'!$A:$Z,8,FALSE) -> 30 | AC44: FALSE | AF44: =VLOOKUP($D44,records!$A:$V,13,FALSE) -> CHARLES RIVER LABORATORIES FRANCE - C.R.L.F. sasu | AG44: Facture originale électronique à | AH44: =VLOOKUP($D44,records!$A:$V,19,FALSE) -> ARBCOMPTACRF@crl.com | AI44: . | AJ44: =VLOOKUP($O44,'records (2)'!$A:$Z,14,FALSE) -> 003IV000010su8wYAA | AK44: =VLOOKUP($O44,'records (2)'!$A:$Z,15,FALSE) -> Diego PINZON (arbcomptacrf) | AL44: =VLOOKUP($O44,'records (2)'!$A:$Z,10,FALSE) -> 003IV000010su8wYAA | AM44: =VLOOKUP($O44,'records (2)'!$A:$Z,11,FALSE) -> Diego PINZON (arbcomptacrf) | AN44: 1 | AO44: 2000 | AP44: 2000 | AQ44: 0 | AR44: 0
A45: RTNS-01679 | B45: RESTONIS | C45: RESTONIS | D45: 001IV000015S2SIYA0 | E45: 01tIV00000GOfP6YAL | F45: Redevance d'utilisation - ETP EU | H45: Annual | I45: In advance | J45: 46023 | K45: 46387 | L45: Pixid France | M45: Pack C&S | N45: 46023 | O45: =VLOOKUP(D45,records!$A:$U,10,FALSE) -> 0012p00004MRAVrAAP | P45: =VLOOKUP(D45,records!$A:$V,20,FALSE) -> FR58531170819 | Q45: =VLOOKUP(D45,records!$A:$V,12,FALSE) -> 53 117 081 900 019 | R45: Email | S45: =VLOOKUP(D45,records!$A:$U,19,FALSE) -> ass.gestion@restonis.fr | T45: Transfer | U45: Renewal | V45: =VLOOKUP($D45,records!$A:$V,3,FALSE) -> RESTONIS sasu | X45: =VLOOKUP($D45,records!$A:$V,9,FALSE) -> 12 rue Jean Marie Poulmarch | Y45: =VLOOKUP($D45,records!$A:$V,4,FALSE) -> IVRY SUR SEINE | Z45: =VLOOKUP($D45,records!$A:$V,7,FALSE) -> 94200 | AA45: Redevance 2026 | AB45: =VLOOKUP(O45,'records (2)'!$A:$Z,8,FALSE) -> 30 | AC45: FALSE | AF45: =VLOOKUP($D45,records!$A:$V,13,FALSE) -> RESTONIS sasu | AG45: Facture originale électronique à | AH45: =VLOOKUP($D45,records!$A:$V,19,FALSE) -> ass.gestion@restonis.fr | AI45: . | AJ45: =VLOOKUP($O45,'records (2)'!$A:$Z,10,FALSE) -> 003IV000010t7NpYAI | AK45: =VLOOKUP($O45,'records (2)'!$A:$Z,11,FALSE) -> Amélie GRILLET | AL45: =VLOOKUP($O45,'records (2)'!$A:$Z,10,FALSE) -> 003IV000010t7NpYAI | AM45: =VLOOKUP($O45,'records (2)'!$A:$Z,11,FALSE) -> Amélie GRILLET | AN45: 1 | AO45: 1200 | AP45: 1200 | AQ45: 0 | AR45: 0
A46: NSTF-01804 | B46: NYRSTAR | C46: NYRSTAR FRANCE | D46: 001IV000015S8j2YAC | E46: 01tIV00000GyVCbYAN | F46: Redevance d'utilisation - Tranche 25 ETP - Cas 2 | H46: Annual | I46: In advance | J46: 46023 | K46: 46387 | L46: Pixid France | M46: Pack C&S | N46: 46023 | O46: =VLOOKUP(D46,records!$A:$U,10,FALSE) -> 001SZ000002xEQqYAM | P46: =VLOOKUP(D46,records!$A:$V,20,FALSE) -> FR63490837283 | Q46: =VLOOKUP(D46,records!$A:$V,12,FALSE) -> 49 083 728 300 020 | R46: Email | S46: =VLOOKUP(D46,records!$A:$U,19,FALSE) -> auby.comptafactures@nyrstar.com | T46: Transfer | U46: Renewal | V46: =VLOOKUP($D46,records!$A:$V,3,FALSE) -> NYRSTAR FRANCE sasu | X46: =VLOOKUP($D46,records!$A:$V,9,FALSE) -> Rue Jean Jacques Rousseau | Y46: =VLOOKUP($D46,records!$A:$V,4,FALSE) -> AUBY | Z46: =VLOOKUP($D46,records!$A:$V,7,FALSE) -> 59950 | AA46: Redevance 2026 | AB46: =VLOOKUP(O46,'records (2)'!$A:$Z,8,FALSE) -> 30 | AC46: FALSE | AF46: =VLOOKUP($D46,records!$A:$V,13,FALSE) -> NYRSTAR FRANCE sasu | AG46: Facture originale électronique à | AH46: =VLOOKUP($D46,records!$A:$V,19,FALSE) -> auby.comptafactures@nyrstar.com | AI46: . | AJ46: =VLOOKUP($O46,'records (2)'!$A:$Z,14,FALSE) -> 003IV000010sqLNYAY | AK46: =VLOOKUP($O46,'records (2)'!$A:$Z,15,FALSE) -> Alexis DOHEIN | AL46: =VLOOKUP($O46,'records (2)'!$A:$Z,10,FALSE) -> 003IV000010sqLMYAY | AM46: =VLOOKUP($O46,'records (2)'!$A:$Z,11,FALSE) -> Relances Factures NYRSTAR FRANCE | AN46: 1 | AO46: 2000 | AP46: 2000 | AQ46: 0 | AR46: 0
A47: INEA-01968 | B47: INEOS AUTOMOTIVE | C47: INEOS AUTOMOTIVE S.A.S | D47: 001IV000015S8jKYAS | E47: 01tIV00000GOfP1YAL | F47: Redevance d'utilisation - Tranche 25 ETP - Cas 1 | H47: Annual | I47: In advance | J47: 46023 | K47: 46387 | L47: Pixid France | M47: Pack C&S | N47: 46023 | O47: =VLOOKUP(D47,records!$A:$U,10,FALSE) -> 001SZ00000PZ6aTYAT | P47: =VLOOKUP(D47,records!$A:$V,20,FALSE) -> FR38403119431 | Q47: =VLOOKUP(D47,records!$A:$V,12,FALSE) -> 40 311 943 100 027 | R47: Email | S47: automotive.compta@ineos.com | T47: Transfer | U47: Renewal | V47: =VLOOKUP($D47,records!$A:$V,3,FALSE) -> INEOS AUTOMOTIVE SAS | W47: =IFERROR(VLOOKUP($D47,records!$A:$V,6,FALSE),) -> Service comptabilité | X47: =VLOOKUP($D47,records!$A:$V,9,FALSE) -> Europôle de Sarreguemines | Y47: =VLOOKUP($D47,records!$A:$V,4,FALSE) -> HAMBACH | Z47: =VLOOKUP($D47,records!$A:$V,7,FALSE) -> 57913 | AA47: Redevance 2026 | AB47: =VLOOKUP(O47,'records (2)'!$A:$Z,8,FALSE) -> 60 | AC47: =VLOOKUP(O47,'records (4)'!$A:$C,3,FALSE) -> TRUE | AD47: YES | AE47: 46023 | AF47: =VLOOKUP($D47,records!$A:$V,13,FALSE) -> INEOS AUTOMOTIVE SAS | AG47: Facture originale électronique à | AH47: automotive.compta@ineos.com | AI47: . | AJ47: =VLOOKUP($O47,'records (2)'!$A:$Z,14,FALSE) -> 003IV000010tSrXYAU | AK47: =VLOOKUP($O47,'records (2)'!$A:$Z,15,FALSE) -> Service Comptabilité | AL47: =VLOOKUP($O47,'records (2)'!$A:$Z,10,FALSE) -> 003IV000010tSrXYAU | AM47: =VLOOKUP($O47,'records (2)'!$A:$Z,11,FALSE) -> Service Comptabilité | AN47: 1 | AO47: 2000 | AP47: 2000 | AQ47: 0 | AR47: 0
A48: CARG-01700 | B48: CAREA GROUPE | C48: CAREA GROUPE | D48: 001IV000015RewNYAS | E48: 01tIV00000GOfP1YAL | F48: Redevance d'utilisation - Tranche 25 ETP - Cas 1 | H48: Annual | I48: In advance | J48: 46023 | K48: 46387 | L48: Pixid France | M48: Pack C&S | N48: 46023 | O48: =VLOOKUP(D48,records!$A:$U,10,FALSE) -> 0012p00004UHRUgAAP | P48: =VLOOKUP(D48,records!$A:$V,20,FALSE) -> FR84334089752 | Q48: =VLOOKUP(D48,records!$A:$V,12,FALSE) -> 33 408 975 200 102 | R48: Email | S48: =VLOOKUP(D48,records!$A:$U,19,FALSE) -> bcouet@carea.fr | T48: Transfer | U48: Renewal | V48: =VLOOKUP($D48,records!$A:$V,3,FALSE) -> CAREA FACADE sasu | X48: =VLOOKUP($D48,records!$A:$V,9,FALSE) -> ZA DE BEL AIR Bel-Air-de-Combrée - COMBREE | Y48: =VLOOKUP($D48,records!$A:$V,4,FALSE) -> OMBREE D'ANJOU | Z48: =VLOOKUP($D48,records!$A:$V,7,FALSE) -> 49520 | AA48: Redevance 2026 | AB48: =VLOOKUP(O48,'records (2)'!$A:$Z,8,FALSE) -> 30 | AC48: FALSE | AF48: =VLOOKUP($D48,records!$A:$V,13,FALSE) -> CAREA FACADE sasu | AG48: Facture originale électronique à | AH48: =VLOOKUP($D48,records!$A:$V,19,FALSE) -> bcouet@carea.fr | AI48: . | AJ48: =VLOOKUP($O48,'records (2)'!$A:$Z,14,FALSE) -> 003IV000010taO5YAI | AK48: =VLOOKUP($O48,'records (2)'!$A:$Z,15,FALSE) -> Bérangère COUET | AL48: =VLOOKUP($O48,'records (2)'!$A:$Z,10,FALSE) -> 003IV000010taO5YAI | AM48: =VLOOKUP($O48,'records (2)'!$A:$Z,11,FALSE) -> Bérangère COUET | AN48: 1 | AO48: 500 | AP48: 500 | AQ48: 0 | AR48: 0
A49: OTRF-01794 | B49: O TERRA FRANCE COSSE | C49: OTERRA FRANCE | D49: 001IV000015S8j9YAC | E49: 01tIV00000GyVCbYAN | F49: Redevance d'utilisation - Tranche 25 ETP - Cas 2 | H49: Annual | I49: In advance | J49: 46023 | K49: 46387 | L49: Pixid France | M49: Pack C&S | N49: 46023 | O49: =VLOOKUP(D49,records!$A:$U,10,FALSE) -> 001SZ000005HETVYA4 | P49: =VLOOKUP(D49,records!$A:$V,20,FALSE) -> FR50890708365 | Q49: =VLOOKUP(D49,records!$A:$V,12,FALSE) -> 89 070 836 500 030 | R49: Email | S49: =VLOOKUP(D49,records!$A:$U,19,FALSE) -> beatrice.chretien@oterra.com | T49: Transfer | U49: Renewal | V49: =VLOOKUP($D49,records!$A:$V,3,FALSE) -> OTERRA FRANCE SAS | X49: =VLOOKUP($D49,records!$A:$V,9,FALSE) -> Rue Ambroise Paré | Y49: =VLOOKUP($D49,records!$A:$V,4,FALSE) -> COSSE-LE-VIVIEN | Z49: =VLOOKUP($D49,records!$A:$V,7,FALSE) -> 53230 | AA49: Redevance 2026 | AB49: =VLOOKUP(O49,'records (2)'!$A:$Z,8,FALSE) -> 30 | AC49: =VLOOKUP(O49,'records (4)'!$A:$C,3,FALSE) -> TRUE | AD49: YES | AE49: 46023 | AF49: =VLOOKUP($D49,records!$A:$V,13,FALSE) -> OTERRA FRANCE SAS | AG49: Facture originale électronique à | AH49: =VLOOKUP($D49,records!$A:$V,19,FALSE) -> beatrice.chretien@oterra.com | AI49: . | AJ49: =VLOOKUP($O49,'records (2)'!$A:$Z,14,FALSE) -> 003IV000010tSkkYAE | AK49: =VLOOKUP($O49,'records (2)'!$A:$Z,15,FALSE) -> Béatrice CHRETIEN | AL49: =VLOOKUP($O49,'records (2)'!$A:$Z,10,FALSE) -> 003IV000010tSkkYAE | AM49: =VLOOKUP($O49,'records (2)'!$A:$Z,11,FALSE) -> Béatrice CHRETIEN | AN49: 1 | AO49: 1000 | AP49: 1000
A50: GRLD-01542 | B50: LUCAY MAROQUINERIE | C50: GROUPE RIOLAND | D50: 001IV000015S6a7YAC | E50: 01tIV00000GyVCbYAN | F50: Redevance d'utilisation - Tranche 25 ETP - Cas 2 | H50: Annual | I50: In advance | J50: 46023 | K50: 46387 | L50: Pixid France | M50: Pack C&S | N50: 46023 | O50: =VLOOKUP(D50,records!$A:$U,10,FALSE) -> 0012p00004OML8JAAX | P50: =VLOOKUP(D50,records!$A:$V,20,FALSE) -> FR53337544720 | Q50: =VLOOKUP(D50,records!$A:$V,12,FALSE) -> 3 375 447 200 051 | R50: Email | S50: =VLOOKUP(D50,records!$A:$U,19,FALSE) -> benoit.pinon@grouperioland.fr | T50: Transfer | U50: Renewal | V50: =VLOOKUP($D50,records!$A:$V,3,FALSE) -> GROUPE RIOLAND sas | X50: =VLOOKUP($D50,records!$A:$V,9,FALSE) -> 24 La Barre | Y50: =VLOOKUP($D50,records!$A:$V,4,FALSE) -> BAUDRES | Z50: =VLOOKUP($D50,records!$A:$V,7,FALSE) -> 36110 | AA50: Redevance 2026 | AB50: =VLOOKUP(O50,'records (2)'!$A:$Z,8,FALSE) -> 30 | AC50: FALSE | AF50: =VLOOKUP($D50,records!$A:$V,13,FALSE) -> GROUPE RIOLAND sas | AG50: Facture originale électronique à | AH50: =VLOOKUP($D50,records!$A:$V,19,FALSE) -> benoit.pinon@grouperioland.fr | AI50: . | AJ50: =VLOOKUP($O50,'records (2)'!$A:$Z,14,FALSE) -> 003IV000010sxFqYAI | AK50: =VLOOKUP($O50,'records (2)'!$A:$Z,15,FALSE) -> Benoît PINON | AL50: =VLOOKUP($O50,'records (2)'!$A:$Z,10,FALSE) -> 003IV000010sxFqYAI | AM50: =VLOOKUP($O50,'records (2)'!$A:$Z,11,FALSE) -> Benoît PINON | AN50: 1 | AO50: 2000 | AP50: 2000 | AQ50: 0 | AR50: 0
A51: DPSB-01896 | B51: DPS BEAUNE | C51: DPS BEAUNE (Groupe Dalloz) | D51: 001IV000015RyE5YAK | E51: 01tIV00000GOfP1YAL | F51: Redevance d'utilisation - Tranche 25 ETP - Cas 1 | H51: Annual | I51: In advance | J51: 46023 | K51: 46387 | L51: Pixid France | M51: Pack C&S | N51: 46023 | O51: =VLOOKUP(D51,records!$A:$U,10,FALSE) -> 001SZ00000CP6rMYAT | P51: =VLOOKUP(D51,records!$A:$V,20,FALSE) -> FR96839694593 | Q51: =VLOOKUP(D51,records!$A:$V,12,FALSE) -> 83 969 459 300 014 | R51: Email | S51: =VLOOKUP(D51,records!$A:$U,19,FALSE) -> besma.ammari@dps-beaune.com | T51: Transfer | U51: Renewal | V51: =VLOOKUP($D51,records!$A:$V,3,FALSE) -> DPS BEAUNE sas | X51: =VLOOKUP($D51,records!$A:$V,9,FALSE) -> 156 Route de Dijon | Y51: =VLOOKUP($D51,records!$A:$V,4,FALSE) -> BEAUNE | Z51: =VLOOKUP($D51,records!$A:$V,7,FALSE) -> 21200 | AA51: Redevance 2026 | AB51: =VLOOKUP(O51,'records (2)'!$A:$Z,8,FALSE) -> 30 | AC51: FALSE | AF51: =VLOOKUP($D51,records!$A:$V,13,FALSE) -> DPS BEAUNE sas | AG51: Facture originale électronique à | AH51: =VLOOKUP($D51,records!$A:$V,19,FALSE) -> besma.ammari@dps-beaune.com | AI51: . | AJ51: =VLOOKUP($O51,'records (2)'!$A:$Z,14,FALSE) -> 003IV000010tJWHYA2 | AK51: =VLOOKUP($O51,'records (2)'!$A:$Z,15,FALSE) -> Léa MONACI | AL51: =VLOOKUP($O51,'records (2)'!$A:$Z,10,FALSE) -> 003IV000010tJWHYA2 | AM51: =VLOOKUP($O51,'records (2)'!$A:$Z,11,FALSE) -> Léa MONACI | AN51: 1 | AO51: 500 | AP51: 500 | AQ51: 0 | AR51: 0
A52: SHRP-01576 | B52: CALIDA GROUP | C52: SHERPA LOGISTIQUE (CALIDA GROUP) | D52: 001IV000015S8ilYAC | E52: 01tIV00000GOfP1YAL | F52: Redevance d'utilisation - Tranche 25 ETP - Cas 1 | H52: Annual | I52: In advance | J52: 46023 | K52: 46387 | L52: Pixid France | M52: Pack C&S | N52: 46023 | O52: =VLOOKUP(D52,records!$A:$U,10,FALSE) -> 0012p00004QckxBAAR | P52: =VLOOKUP(D52,records!$A:$V,20,FALSE) -> FR53439531005 | Q52: =VLOOKUP(D52,records!$A:$V,12,FALSE) -> 43 953 100 500 015 | R52: Email | S52: =VLOOKUP(D52,records!$A:$U,19,FALSE) -> bjumelart@sherpa-logistique.fr | T52: Direct debit | U52: Renewal | V52: =VLOOKUP($D52,records!$A:$V,3,FALSE) -> SHERPA LOGISTIQUE sas | X52: =VLOOKUP($D52,records!$A:$V,9,FALSE) -> ZI du Cappa | Y52: =VLOOKUP($D52,records!$A:$V,4,FALSE) -> ST RAMBERT D'ALBON | Z52: =VLOOKUP($D52,records!$A:$V,7,FALSE) -> 26140 | AA52: Redevance 2026 | AB52: =VLOOKUP(O52,'records (2)'!$A:$Z,8,FALSE) -> 30 | AC52: FALSE | AF52: =VLOOKUP($D52,records!$A:$V,13,FALSE) -> SHERPA LOGISTIQUE sas | AG52: Facture originale électronique à | AH52: =VLOOKUP($D52,records!$A:$V,19,FALSE) -> bjumelart@sherpa-logistique.fr | AI52: . | AJ52: =VLOOKUP($O52,'records (2)'!$A:$Z,14,FALSE) -> 003IV000010tSkOYAU | AK52: =VLOOKUP($O52,'records (2)'!$A:$Z,15,FALSE) -> Béatrice JUMELART | AL52: =VLOOKUP($O52,'records (2)'!$A:$Z,10,FALSE) -> 003IV000010tSkOYAU | AM52: =VLOOKUP($O52,'records (2)'!$A:$Z,11,FALSE) -> Béatrice JUMELART | AN52: 1 | AO52: 500 | AP52: 500
A53: SMTR-01650 | B53: SOCIETE DE MECANIQUE DES TILLES | C53: SMT ROTAREX - (SOCIETE DE MECANIQUE DES TILLES) | D53: 001IV000015S85zYAC | E53: 01tIV00000GOfP1YAL | F53: Redevance d'utilisation - Tranche 25 ETP - Cas 1 | H53: Annual | I53: In advance | J53: 46023 | K53: 46387 | L53: Pixid France | M53: Pack C&S | N53: 46023 | O53: =VLOOKUP(D53,records!$A:$U,10,FALSE) -> 0012p00004TnExuAAF | P53: =VLOOKUP(D53,records!$A:$V,20,FALSE) -> FR20712047547 | Q53: =VLOOKUP(D53,records!$A:$V,12,FALSE) -> 71 204 754 700 021 | R53: Email | S53: =VLOOKUP(D53,records!$A:$U,19,FALSE) -> bon.nathalie@rotarex.com | T53: Transfer | U53: Renewal | V53: =VLOOKUP($D53,records!$A:$V,3,FALSE) -> SOCIETE DE MECANIQUE DES TILLES sas | X53: =VLOOKUP($D53,records!$A:$V,9,FALSE) -> 5 Rue de Labergement | Y53: =VLOOKUP($D53,records!$A:$V,4,FALSE) -> GENLIS | Z53: =VLOOKUP($D53,records!$A:$V,7,FALSE) -> 21110 | AA53: Redevance 2026 | AB53: =VLOOKUP(O53,'records (2)'!$A:$Z,8,FALSE) -> 30 | AC53: FALSE | AF53: =VLOOKUP($D53,records!$A:$V,13,FALSE) -> SOCIETE DE MECANIQUE DES TILLES sas | AG53: Facture originale électronique à | AH53: =VLOOKUP($D53,records!$A:$V,19,FALSE) -> bon.nathalie@rotarex.com | AI53: . | AJ53: =VLOOKUP($O53,'records (2)'!$A:$Z,14,FALSE) -> 003IV000010tIecYAE | AK53: =VLOOKUP($O53,'records (2)'!$A:$Z,15,FALSE) -> Nathalie BON | AL53: =VLOOKUP($O53,'records (2)'!$A:$Z,10,FALSE) -> 003IV000010tIedYAE | AM53: =VLOOKUP($O53,'records (2)'!$A:$Z,11,FALSE) -> Anne DEBIERRE | AN53: 1 | AO53: 500 | AP53: 500
A54: BNFY-01575 | B54: BONNEFOY SAS | C54: BONNEFOY SAS | D54: 001IV000015S8imYAC | E54: 01tIV00000GyVCbYAN | F54: Redevance d'utilisation - Tranche 25 ETP - Cas 2 | H54: Annual | I54: In advance | J54: 46023 | K54: 46387 | L54: Pixid France | M54: Pack C&S | N54: 46023 | O54: =VLOOKUP(D54,records!$A:$U,10,FALSE) -> 0012p00004QdCmrAAF | P54: =VLOOKUP(D54,records!$A:$V,20,FALSE) -> FR25301422622 | Q54: =VLOOKUP(D54,records!$A:$V,12,FALSE) -> 30 142 262 200 029 | R54: Email | S54: =VLOOKUP(D54,records!$A:$U,19,FALSE) -> bonnefoy.achats@groupe-bonnefoy.fr | T54: Transfer | U54: Renewal | V54: =VLOOKUP($D54,records!$A:$V,3,FALSE) -> J.C. BONNEFOY sas | X54: =VLOOKUP($D54,records!$A:$V,9,FALSE) -> ZI- 14 Rue de l'Industrie - BP28 | Y54: =VLOOKUP($D54,records!$A:$V,4,FALSE) -> SAONE | Z54: =VLOOKUP($D54,records!$A:$V,7,FALSE) -> 25660 | AA54: Redevance 2026 | AB54: =VLOOKUP(O54,'records (2)'!$A:$Z,8,FALSE) -> 30 | AC54: FALSE | AF54: =VLOOKUP($D54,records!$A:$V,13,FALSE) -> J.C. BONNEFOY sas | AG54: Facture originale électronique à | AH54: =VLOOKUP($D54,records!$A:$V,19,FALSE) -> bonnefoy.achats@groupe-bonnefoy.fr | AI54: . | AJ54: =VLOOKUP($O54,'records (2)'!$A:$Z,14,FALSE) -> 003IV000010t2kBYAQ | AK54: =VLOOKUP($O54,'records (2)'!$A:$Z,15,FALSE) -> Chantal GOSSE | AL54: =VLOOKUP($O54,'records (2)'!$A:$Z,10,FALSE) -> 003IV000010t2kBYAQ | AM54: =VLOOKUP($O54,'records (2)'!$A:$Z,11,FALSE) -> Chantal GOSSE | AN54: 1 | AO54: 2000 | AP54: 2000 | AQ54: 0 | AR54: 0
A55: VMDC-01524 | B55: VIANT MEDICAL | C55: VIANT MEDICAL - (CHAUMONT) | D55: 001IV000015S508YAC | E55: 01tIV00000GyVCbYAN | F55: Redevance d'utilisation - Tranche 25 ETP - Cas 2 | H55: Annual | I55: In advance | J55: 46023 | K55: 46387 | L55: Pixid France | M55: Pack C&S | N55: 46023 | O55: =VLOOKUP(D55,records!$A:$U,10,FALSE) -> 0012p00004NgQ3uAAF | P55: =VLOOKUP(D55,records!$A:$V,20,FALSE) -> FR40499235018 | Q55: =VLOOKUP(D55,records!$A:$V,12,FALSE) -> 49 923 501 800 011 | R55: Email | S55: =VLOOKUP(D55,records!$A:$U,19,FALSE) -> bruno.gratas@viantmedical.com | T55: Transfer | U55: Renewal | V55: =VLOOKUP($D55,records!$A:$V,3,FALSE) -> VIANT CHAUMONT SAS | W55: =IFERROR(VLOOKUP($D55,records!$A:$V,6,FALSE),) -> Finance | X55: =VLOOKUP($D55,records!$A:$V,9,FALSE) -> 4 rue Renée et Louis Landanger | Y55: =VLOOKUP($D55,records!$A:$V,4,FALSE) -> CHAUMONT | Z55: =VLOOKUP($D55,records!$A:$V,7,FALSE) -> 52000 | AA55: Redevance 2026 | AB55: =VLOOKUP(O55,'records (2)'!$A:$Z,8,FALSE) -> 30 | AC55: FALSE | AF55: =VLOOKUP($D55,records!$A:$V,13,FALSE) -> VIANT CHAUMONT SAS | AG55: Facture originale électronique à | AH55: =VLOOKUP($D55,records!$A:$V,19,FALSE) -> bruno.gratas@viantmedical.com | AI55: . | AJ55: =VLOOKUP($O55,'records (2)'!$A:$Z,14,FALSE) -> 003IV000010tQHtYAM | AK55: =VLOOKUP($O55,'records (2)'!$A:$Z,15,FALSE) -> Bruno GRATAS | AL55: =VLOOKUP($O55,'records (2)'!$A:$Z,10,FALSE) -> 003IV000010tQHtYAM | AM55: =VLOOKUP($O55,'records (2)'!$A:$Z,11,FALSE) -> Bruno GRATAS | AN55: 1 | AO55: 2000 | AP55: 2000 | AQ55: 0 | AR55: 0
A56: ANGD-01672 | B56: ANGDM | C56: ANGDM | D56: 001IV000015S50QYAS | E56: 01tIV00000GyVCbYAN | F56: Redevance d'utilisation - Tranche 25 ETP - Cas 2 | H56: Annual | I56: In advance | J56: 46023 | K56: 46387 | L56: Pixid France | M56: Pack C&S | N56: 46023 | O56: =VLOOKUP(D56,records!$A:$U,10,FALSE) -> 0012p00004TzX0NAAV | P56: =VLOOKUP(D56,records!$A:$V,20,FALSE) -> FR42180092538 | Q56: =VLOOKUP(D56,records!$A:$V,12,FALSE) -> 18 009 253 800 024 | R56: Email | S56: =VLOOKUP(D56,records!$A:$U,19,FALSE) -> bureau.formation@angdm.fr | T56: Transfer | U56: Renewal | V56: =VLOOKUP($D56,records!$A:$V,3,FALSE) -> AGENCE NATIONALE POUR LA GARANTIE DES DROITS DES MINEURS - ANGDM | W56: =IFERROR(VLOOKUP($D56,records!$A:$V,6,FALSE),) -> CENTRE DE GESTION | X56: =VLOOKUP($D56,records!$A:$V,9,FALSE) -> 110 Avenue de la fosse 23 | Y56: =VLOOKUP($D56,records!$A:$V,4,FALSE) -> NOYELLES SOUS LENS | Z56: =VLOOKUP($D56,records!$A:$V,7,FALSE) -> 62221 | AA56: Redevance 2026 | AB56: =VLOOKUP(O56,'records (2)'!$A:$Z,8,FALSE) -> 30 | AC56: FALSE | AF56: =VLOOKUP($D56,records!$A:$V,13,FALSE) -> AGENCE NATIONALE POUR LA GARANTIE DES DROITS DES MINEURS - ANGDM | AG56: Facture originale électronique à | AH56: =VLOOKUP($D56,records!$A:$V,19,FALSE) -> bureau.formation@angdm.fr | AI56: . | AJ56: =VLOOKUP($O56,'records (2)'!$A:$Z,14,FALSE) -> 003IV000010tQITYA2 | AK56: =VLOOKUP($O56,'records (2)'!$A:$Z,15,FALSE) -> Stéphanie LEMARCHAND | AL56: =VLOOKUP($O56,'records (2)'!$A:$Z,10,FALSE) -> 003IV000010tQITYA2 | AM56: =VLOOKUP($O56,'records (2)'!$A:$Z,11,FALSE) -> Stéphanie LEMARCHAND | AN56: 1 | AO56: 1000 | AP56: 1000
A57: SCML-01713 | B57: SOCAMEL | C57: SOCAMEL | D57: 001IV000015S8j0YAC | E57: 01tIV00000GOfP1YAL | F57: Redevance d'utilisation - Tranche 25 ETP - Cas 1 | H57: Annual | I57: In advance | J57: 46023 | K57: 46387 | L57: Pixid France | M57: Pack C&S | N57: 46023 | O57: =VLOOKUP(D57,records!$A:$U,10,FALSE) -> 001SZ0000021G4qYAE | P57: =VLOOKUP(D57,records!$A:$V,20,FALSE) -> FR75070503016 | Q57: =VLOOKUP(D57,records!$A:$V,12,FALSE) -> 7 050 301 600 035 | R57: Email | S57: =VLOOKUP(D57,records!$A:$U,19,FALSE) -> c.latil@socamel.com | T57: Transfer | U57: Renewal | V57: =VLOOKUP($D57,records!$A:$V,3,FALSE) -> SOCAMEL TECHNOLOGIES sas | X57: =VLOOKUP($D57,records!$A:$V,9,FALSE) -> Descente Allivet | Y57: =VLOOKUP($D57,records!$A:$V,4,FALSE) -> RENAGE | Z57: =VLOOKUP($D57,records!$A:$V,7,FALSE) -> 38140 | AA57: Redevance 2026 | AB57: =VLOOKUP(O57,'records (2)'!$A:$Z,8,FALSE) -> 30 | AC57: FALSE | AF57: =VLOOKUP($D57,records!$A:$V,13,FALSE) -> SOCAMEL TECHNOLOGIES sas | AG57: Facture originale électronique à | AH57: =VLOOKUP($D57,records!$A:$V,19,FALSE) -> c.latil@socamel.com | AI57: . | AJ57: =VLOOKUP($O57,'records (2)'!$A:$Z,14,FALSE) -> 003IV000010tSkaYAE | AK57: =VLOOKUP($O57,'records (2)'!$A:$Z,15,FALSE) -> Carine LATIL | AL57: =VLOOKUP($O57,'records (2)'!$A:$Z,10,FALSE) -> 003IV000010tSkaYAE | AM57: =VLOOKUP($O57,'records (2)'!$A:$Z,11,FALSE) -> Carine LATIL | AN57: 1 | AO57: 500 | AP57: 500 | AQ57: 0 | AR57: 0
A58: HJHZ-01770 | B58: HEINZ SAS | C58: HEINZ | D58: 001IV000015RzTjYAK | E58: 01tIV00000GyVCbYAN | F58: Redevance d'utilisation - Tranche 25 ETP - Cas 2 | H58: Annual | I58: In advance | J58: 46023 | K58: 46387 | L58: Pixid France | M58: Pack C&S | N58: 46023 | O58: =VLOOKUP(D58,records!$A:$U,10,FALSE) -> 001SZ000003WtXqYAK | P58: =VLOOKUP(D58,records!$A:$V,20,FALSE) -> FR23483005328 | Q58: =VLOOKUP(D58,records!$A:$V,12,FALSE) -> 48 300 532 800 040 | R58: Email | S58: =VLOOKUP(D58,records!$A:$U,19,FALSE) -> camille.meurin@kraftheinz.com | T58: Transfer | U58: Renewal | V58: =VLOOKUP($D58,records!$A:$V,3,FALSE) -> H.J. HEINZ FRANCE sasu | X58: =VLOOKUP($D58,records!$A:$V,9,FALSE) -> 18 Rue Marx Dormoy | Y58: =VLOOKUP($D58,records!$A:$V,4,FALSE) -> SECLIN | Z58: =VLOOKUP($D58,records!$A:$V,7,FALSE) -> 59113 | AA58: Redevance 2026 | AB58: =VLOOKUP(O58,'records (2)'!$A:$Z,8,FALSE) -> 30 | AC58: =VLOOKUP(O58,'records (4)'!$A:$C,3,FALSE) -> TRUE | AD58: YES | AE58: 46023 | AF58: =VLOOKUP($D58,records!$A:$V,13,FALSE) -> H.J. HEINZ FRANCE sasu | AG58: Facture originale électronique à | AH58: =VLOOKUP($D58,records!$A:$V,19,FALSE) -> camille.meurin@kraftheinz.com | AI58: . | AJ58: =VLOOKUP($O58,'records (2)'!$A:$Z,14,FALSE) -> 003IV000010t7tcYAA | AK58: =VLOOKUP($O58,'records (2)'!$A:$Z,15,FALSE) -> Camille MEURIN | AL58: =VLOOKUP($O58,'records (2)'!$A:$Z,10,FALSE) -> 003IV000010t7tcYAA | AM58: =VLOOKUP($O58,'records (2)'!$A:$Z,11,FALSE) -> Camille MEURIN | AN58: 1 | AO58: 1000 | AP58: 1000 | AQ58: 0 | AR58: 0
A59: GDVS-01883 | B59: GRANDVISION FRANCE | C59: GRANDVISION | D59: 001IV000015S86BYAS | E59: 01tIV00000GOfP1YAL | F59: Redevance d'utilisation - Tranche 25 ETP - Cas 1 | H59: Annual | I59: In advance | J59: 46023 | K59: 46387 | L59: Pixid France | M59: Pack C&S | N59: 46023 | O59: =VLOOKUP(D59,records!$A:$U,10,FALSE) -> 001SZ000007aM4TYAU | P59: =VLOOKUP(D59,records!$A:$V,20,FALSE) -> FR75492787957 | Q59: =VLOOKUP(D59,records!$A:$V,12,FALSE) -> 49 278 795 700 041 | R59: Email | S59: =VLOOKUP(D59,records!$A:$U,19,FALSE) -> camille.niquet@grandvision.fr | T59: Transfer | U59: Renewal | V59: =VLOOKUP($D59,records!$A:$V,3,FALSE) -> GRANDVISION FRANCE sasu | X59: =VLOOKUP($D59,records!$A:$V,9,FALSE) -> Rue du Four à Chaux - ZA DES LOUAITIERES | Y59: =VLOOKUP($D59,records!$A:$V,4,FALSE) -> NOUAN-LE-FUZELIER | Z59: =VLOOKUP($D59,records!$A:$V,7,FALSE) -> 41600 | AA59: Redevance 2026 | AB59: =VLOOKUP(O59,'records (2)'!$A:$Z,8,FALSE) -> 30 | AC59: FALSE | AF59: =VLOOKUP($D59,records!$A:$V,13,FALSE) -> GRANDVISION FRANCE sasu | AG59: Facture originale électronique à | AH59: =VLOOKUP($D59,records!$A:$V,19,FALSE) -> camille.niquet@grandvision.fr | AI59: . | AJ59: =VLOOKUP($O59,'records (2)'!$A:$Z,14,FALSE) -> 003IV000010t1X4YAI | AK59: =VLOOKUP($O59,'records (2)'!$A:$Z,15,FALSE) -> Camille NIQUET | AL59: =VLOOKUP($O59,'records (2)'!$A:$Z,10,FALSE) -> 003IV000010t1X4YAI | AM59: =VLOOKUP($O59,'records (2)'!$A:$Z,11,FALSE) -> Camille NIQUET | AN59: 1 | AO59: 1500 | AP59: 1500 | AQ59: 0 | AR59: 0
A60: MMPP-01589 | B60: MMP SAS | C60: MMP PACKETIS | D60: 001IV000015S8ioYAC | E60: 01tIV00000GyVCbYAN | F60: Redevance d'utilisation - Tranche 25 ETP - Cas 2 | H60: Annual | I60: In advance | J60: 46023 | K60: 46387 | L60: Pixid France | M60: Pack C&S | N60: 46023 | O60: =VLOOKUP(D60,records!$A:$U,10,FALSE) -> 0012p00004QwpRfAAJ | P60: =VLOOKUP(D60,records!$A:$V,20,FALSE) -> FR45403221930 | Q60: =VLOOKUP(D60,records!$A:$V,12,FALSE) -> 40 322 193 000 023 | R60: Email | S60: =VLOOKUP(D60,records!$A:$U,19,FALSE) -> carole.tardieu@mm.group | T60: Transfer | U60: Renewal | V60: =VLOOKUP($D60,records!$A:$V,3,FALSE) -> MMP PACKETIS SAS | X60: =VLOOKUP($D60,records!$A:$V,9,FALSE) -> Treille | Y60: =VLOOKUP($D60,records!$A:$V,4,FALSE) -> CHAZELLES | Z60: =VLOOKUP($D60,records!$A:$V,7,FALSE) -> 16380 | AA60: Redevance 2026 | AB60: =VLOOKUP(O60,'records (2)'!$A:$Z,8,FALSE) -> 30 | AC60: FALSE | AF60: =VLOOKUP($D60,records!$A:$V,13,FALSE) -> MMP PACKETIS SAS | AG60: Facture originale électronique à | AH60: =VLOOKUP($D60,records!$A:$V,19,FALSE) -> carole.tardieu@mm.group | AI60: . | AJ60: =VLOOKUP($O60,'records (2)'!$A:$Z,14,FALSE) -> 003IV000010s6QzYAI | AK60: =VLOOKUP($O60,'records (2)'!$A:$Z,15,FALSE) -> David JUBIEN | AL60: =VLOOKUP($O60,'records (2)'!$A:$Z,10,FALSE) -> 003IV000010s6QzYAI | AM60: =VLOOKUP($O60,'records (2)'!$A:$Z,11,FALSE) -> David JUBIEN | AN60: 1 | AO60: 4000 | AP60: 4000 | AQ60: 0 | AR60: 0
A61: TIES-01480 | B61: TOYO INK EUROPE SPEC CHEMICALS | C61: TOYO INK EUROPE | D61: 001IV000015S6ZvYAK | E61: 01tIV00000GyVCbYAN | F61: Redevance d'utilisation - Tranche 25 ETP - Cas 2 | H61: Annual | I61: In advance | J61: 46023 | K61: 46387 | L61: Pixid France | M61: Pack C&S | N61: 46023 | O61: =VLOOKUP(D61,records!$A:$U,10,FALSE) -> 0012p00004MXgKGAA1 | P61: =VLOOKUP(D61,records!$A:$V,20,FALSE) -> FR06389316191 | Q61: =VLOOKUP(D61,records!$A:$V,12,FALSE) -> 38 931 619 100 037 | R61: Email | S61: =VLOOKUP(D61,records!$A:$U,19,FALSE) -> cbelmere@toyoink-europe.com | T61: Transfer | U61: Renewal | V61: =VLOOKUP($D61,records!$A:$V,3,FALSE) -> TOYO INK EUROPE SPECIALTY CHEMICALS sasu | X61: =VLOOKUP($D61,records!$A:$V,9,FALSE) -> Boulevard Dambourney | Y61: =VLOOKUP($D61,records!$A:$V,4,FALSE) -> OISSEL | Z61: =VLOOKUP($D61,records!$A:$V,7,FALSE) -> 76350 | AA61: Redevance 2026 | AB61: =VLOOKUP(O61,'records (2)'!$A:$Z,8,FALSE) -> 30 | AC61: FALSE | AF61: =VLOOKUP($D61,records!$A:$V,13,FALSE) -> TOYO INK EUROPE SPECIALTY CHEMICALS sasu | AG61: Facture originale électronique à | AH61: =VLOOKUP($D61,records!$A:$V,19,FALSE) -> cbelmere@toyoink-europe.com | AI61: . | AJ61: =VLOOKUP($O61,'records (2)'!$A:$Z,14,FALSE) -> 003IV000010sxFfYAI | AK61: =VLOOKUP($O61,'records (2)'!$A:$Z,15,FALSE) -> Nadia HAMMOUANI | AL61: =VLOOKUP($O61,'records (2)'!$A:$Z,10,FALSE) -> 003IV000010sxFfYAI | AM61: =VLOOKUP($O61,'records (2)'!$A:$Z,11,FALSE) -> Nadia HAMMOUANI | AN61: 1 | AO61: 1000 | AP61: 1000 | AQ61: 0 | AR61: 0
A62: MOYP-01828 | B62: MOY PARK FRANCE SAS | C62: MOY PARK | D62: 001IV000015S8nKYAS | E62: 01tIV00000GOfP1YAL | F62: Redevance d'utilisation - Tranche 25 ETP - Cas 1 | H62: Annual | I62: In advance | J62: 46023 | K62: 46387 | L62: Pixid France | M62: Pack C&S | N62: 46023 | O62: =VLOOKUP(D62,records!$A:$U,10,FALSE) -> 001SZ000008DnhTYAS | P62: =VLOOKUP(D62,records!$A:$V,20,FALSE) -> FR10444575120 | Q62: =VLOOKUP(D62,records!$A:$V,12,FALSE) -> 44 457 512 000 019 | R62: Email | S62: ceap.invoices@moypark.com | T62: Direct debit | U62: Renewal | V62: =VLOOKUP($D62,records!$A:$V,3,FALSE) -> MOY PARK FRANCE sas | X62: =VLOOKUP($D62,records!$A:$V,9,FALSE) -> 712 Chemin de Noyelles | Y62: =VLOOKUP($D62,records!$A:$V,4,FALSE) -> HENIN-BEAUMONT | Z62: =VLOOKUP($D62,records!$A:$V,7,FALSE) -> 72110 | AA62: Redevance 2026 | AB62: =VLOOKUP(O62,'records (2)'!$A:$Z,8,FALSE) -> 30 | AC62: FALSE | AF62: =VLOOKUP($D62,records!$A:$V,13,FALSE) -> MOY PARK FRANCE sas | AG62: Facture originale électronique à | AH62: ceap.invoices@moypark.com | AI62: . | AJ62: =VLOOKUP($O62,'records (2)'!$A:$Z,14,FALSE) -> 003IV000010su9HYAQ | AK62: =VLOOKUP($O62,'records (2)'!$A:$Z,15,FALSE) -> Carine CAPELLE | AL62: =VLOOKUP($O62,'records (2)'!$A:$Z,10,FALSE) -> 003IV000010su9HYAQ | AM62: =VLOOKUP($O62,'records (2)'!$A:$Z,11,FALSE) -> Carine CAPELLE | AN62: 1 | AO62: 500 | AP62: 500 | AQ62: 0 | AR62: 0
A63: BPMD-01549 | B63: BANQUE POPULAIRE MEDITERRANEE | C63: BANQUE POPULAIRE MEDITERRANEE | D63: 001IV000015SAFiYAO | E63: 01tIV00000GOfP1YAL | F63: Redevance d'utilisation - Tranche 25 ETP - Cas 1 | H63: Annual | I63: In advance | J63: 46023 | K63: 46387 | L63: Pixid France | M63: Pack C&S | N63: 46023 | O63: =VLOOKUP(D63,records!$A:$U,10,FALSE) -> 0012p00004Ovfx1AAB | P63: =VLOOKUP(D63,records!$A:$V,20,FALSE) -> FR61058801481 | Q63: =VLOOKUP(D63,records!$A:$V,12,FALSE) -> 5 880 148 101 264 | R63: Email | S63: =VLOOKUP(D63,records!$A:$U,19,FALSE) -> cecile.geoffroy@bpmed.fr | T63: Transfer | U63: Renewal | V63: =VLOOKUP($D63,records!$A:$V,3,FALSE) -> BANQUE POPULAIRE MEDITERRANEE sa | X63: =VLOOKUP($D63,records!$A:$V,9,FALSE) -> 457 Promenade des Anglais - BP 241 | Y63: =VLOOKUP($D63,records!$A:$V,4,FALSE) -> NICE | Z63: =VLOOKUP($D63,records!$A:$V,7,FALSE) -> 6200 | AA63: Redevance 2026 | AB63: =VLOOKUP(O63,'records (2)'!$A:$Z,8,FALSE) -> 30 | AC63: FALSE | AF63: =VLOOKUP($D63,records!$A:$V,13,FALSE) -> BANQUE POPULAIRE MEDITERRANEE sa | AG63: Facture originale électronique à | AH63: =VLOOKUP($D63,records!$A:$V,19,FALSE) -> cecile.geoffroy@bpmed.fr | AI63: . | AJ63: =VLOOKUP($O63,'records (2)'!$A:$Z,14,FALSE) -> 003IV000010rvHQYAY | AK63: =VLOOKUP($O63,'records (2)'!$A:$Z,15,FALSE) -> Cécile GEOFFROY | AL63: =VLOOKUP($O63,'records (2)'!$A:$Z,10,FALSE) -> 003IV000010t2gOYAQ | AM63: =VLOOKUP($O63,'records (2)'!$A:$Z,11,FALSE) -> Isabelle AUBRY | AN63: 1 | AO63: 500 | AP63: 500
A64: CEBF-01654 | B64: CAISSE D'EPARGNE BOURGOGNE FRANCHE COMTE | C64: CAISSE D'EPARGNE BOURGOGNE FRANCHE COMTE (CEBFC) | D64: 001IV000015S8ipYAC | E64: 01tIV00000GOfP1YAL | F64: Redevance d'utilisation - Tranche 25 ETP - Cas 1 | H64: Annual | I64: In advance | J64: 46023 | K64: 46387 | L64: Pixid France | M64: Pack C&S | N64: 46023 | O64: =VLOOKUP(D64,records!$A:$U,10,FALSE) -> 0012p00004RLlIQAA1 | P64: =VLOOKUP(D64,records!$A:$V,20,FALSE) -> FR73352483341 | Q64: =VLOOKUP(D64,records!$A:$V,12,FALSE) -> 35 248 334 100 017 | R64: Email | S64: =VLOOKUP(D64,records!$A:$U,19,FALSE) -> cecile.pencole-lehaut@cebfc.caisse-epargne.fr | T64: Transfer | U64: Renewal | V64: =VLOOKUP($D64,records!$A:$V,3,FALSE) -> CAISSE D'EPARGNE ET DE PREVOYANCE DE BOURGOGNE FRANCHE-COMTE sa - CEBFC | X64: =VLOOKUP($D64,records!$A:$V,9,FALSE) -> 1 Rond Point de la Nation | Y64: =VLOOKUP($D64,records!$A:$V,4,FALSE) -> DIJON | Z64: =VLOOKUP($D64,records!$A:$V,7,FALSE) -> 21000 | AA64: Redevance 2026 | AB64: =VLOOKUP(O64,'records (2)'!$A:$Z,8,FALSE) -> 30 | AC64: FALSE | AF64: =VLOOKUP($D64,records!$A:$V,13,FALSE) -> CAISSE D'EPARGNE ET DE PREVOYANCE DE BOURGOGNE FRANCHE-COMTE sa - CEBFC | AG64: Facture originale électronique à | AH64: =VLOOKUP($D64,records!$A:$V,19,FALSE) -> cecile.pencole-lehaut@cebfc.caisse-epargne.fr | AI64: . | AJ64: =VLOOKUP($O64,'records (2)'!$A:$Z,14,FALSE) -> 003IV000010s6QxYAI | AK64: =VLOOKUP($O64,'records (2)'!$A:$Z,15,FALSE) -> Céline BALLOT | AL64: =VLOOKUP($O64,'records (2)'!$A:$Z,10,FALSE) -> 003IV000010s6QxYAI | AM64: =VLOOKUP($O64,'records (2)'!$A:$Z,11,FALSE) -> Céline BALLOT | AN64: 1 | AO64: 1000 | AP64: 1000 | AQ64: 0 | AR64: 0
A65: THUA-01777 | B65: THUASNE | C65: THUASNE | D65: 001IV000015SADqYAO | E65: 01tIV00000GOfP1YAL | F65: Redevance d'utilisation - Tranche 25 ETP - Cas 1 | H65: Annual | I65: In advance | J65: 46023 | K65: 46387 | L65: Pixid France | M65: Pack C&S | N65: 46023 | O65: =VLOOKUP(D65,records!$A:$U,10,FALSE) -> 001SZ000003NGlbYAG | P65: =VLOOKUP(D65,records!$A:$V,20,FALSE) -> FR88542091186 | Q65: =VLOOKUP(D65,records!$A:$V,12,FALSE) -> 54 209 118 600 040 | R65: Email | S65: =VLOOKUP(D65,records!$A:$U,19,FALSE) -> celine.champion@thuasne.fr | T65: Transfer | U65: Renewal | V65: =VLOOKUP($D65,records!$A:$V,3,FALSE) -> THUASNE sas | X65: =VLOOKUP($D65,records!$A:$V,9,FALSE) -> 27 Rue de la Jomayere | Y65: =VLOOKUP($D65,records!$A:$V,4,FALSE) -> SAINT-ETIENNE Cedex 2 | Z65: =VLOOKUP($D65,records!$A:$V,7,FALSE) -> 42100 | AA65: Redevance 2026 | AB65: =VLOOKUP(O65,'records (2)'!$A:$Z,8,FALSE) -> 60 | AC65: FALSE | AF65: =VLOOKUP($D65,records!$A:$V,13,FALSE) -> THUASNE sas | AG65: Facture originale électronique à | AH65: =VLOOKUP($D65,records!$A:$V,19,FALSE) -> celine.champion@thuasne.fr | AI65: . | AJ65: =VLOOKUP($O65,'records (2)'!$A:$Z,14,FALSE) -> 003IV000010t4BKYAY | AK65: =VLOOKUP($O65,'records (2)'!$A:$Z,15,FALSE) -> Céline CHAMPION | AL65: =VLOOKUP($O65,'records (2)'!$A:$Z,10,FALSE) -> 003IV000010t4BKYAY | AM65: =VLOOKUP($O65,'records (2)'!$A:$Z,11,FALSE) -> Céline CHAMPION | AN65: 1 | AO65: 1000 | AP65: 1000 | AQ65: 0 | AR65: 0
A66: HUA-01777 | B66: THUASNE | C66: THUASNE | D66: 001IV000015SADqYAO | E66: 01tIV00000GOfP1YAL | F66: Redevance d'utilisation - Tranche 25 ETP - Cas 1 | H66: Annual | I66: In advance | J66: 46023 | K66: 46387 | L66: Pixid France | M66: Pack C&S | N66: 46023 | O66: =VLOOKUP(D66,records!$A:$U,10,FALSE) -> 001SZ000003NGlbYAG | P66: =VLOOKUP(D66,records!$A:$V,20,FALSE) -> FR88542091186 | Q66: =VLOOKUP(D66,records!$A:$V,12,FALSE) -> 54 209 118 600 040 | R66: Email | S66: =VLOOKUP(D66,records!$A:$U,19,FALSE) -> celine.champion@thuasne.fr | T66: Transfer | U66: Renewal | V66: =VLOOKUP($D66,records!$A:$V,3,FALSE) -> THUASNE sas | X66: =VLOOKUP($D66,records!$A:$V,9,FALSE) -> 27 Rue de la Jomayere | Y66: =VLOOKUP($D66,records!$A:$V,4,FALSE) -> SAINT-ETIENNE Cedex 2 | Z66: =VLOOKUP($D66,records!$A:$V,7,FALSE) -> 42100 | AA66: Redevance 2026 | AB66: =VLOOKUP(O66,'records (2)'!$A:$Z,8,FALSE) -> 60 | AC66: FALSE | AF66: =VLOOKUP($D66,records!$A:$V,13,FALSE) -> THUASNE sas | AG66: Facture originale électronique à | AH66: =VLOOKUP($D66,records!$A:$V,19,FALSE) -> celine.champion@thuasne.fr | AI66: . | AJ66: =VLOOKUP($O66,'records (2)'!$A:$Z,14,FALSE) -> 003IV000010t4BKYAY | AK66: =VLOOKUP($O66,'records (2)'!$A:$Z,15,FALSE) -> Céline CHAMPION | AL66: =VLOOKUP($O66,'records (2)'!$A:$Z,10,FALSE) -> 003IV000010t4BKYAY | AM66: =VLOOKUP($O66,'records (2)'!$A:$Z,11,FALSE) -> Céline CHAMPION | AN66: 1 | AO66: 1000 | AP66: 1000 | AQ66: 0 | AR66: 0
A67: FMGC-01539 | B67: FMGC GROUPE | C67: FMGC Groupe | D67: 001IV000015S6a6YAC | E67: 01tIV00000GOfP1YAL | F67: Redevance d'utilisation - Tranche 25 ETP - Cas 1 | H67: Annual | I67: In advance | J67: 46023 | K67: 46387 | L67: Pixid France | M67: Pack C&S | N67: 46023 | O67: =VLOOKUP(D67,records!$A:$U,10,FALSE) -> 0012p00004OLmuHAAT | P67: =VLOOKUP(D67,records!$A:$V,20,FALSE) -> FR94866801210 | Q67: =VLOOKUP(D67,records!$A:$V,12,FALSE) -> 86 680 121 000 026 | R67: Email | S67: =VLOOKUP(D67,records!$A:$U,19,FALSE) -> celine.chevrel@fmgc.net | T67: Transfer | U67: Renewal | V67: =VLOOKUP($D67,records!$A:$V,3,FALSE) -> FONDERIE ET MECANIQUE GENERALE CASTELBRIANTAISE sa - FMGC | X67: =VLOOKUP($D67,records!$A:$V,9,FALSE) -> ZI Hochepie | Y67: =VLOOKUP($D67,records!$A:$V,4,FALSE) -> SOUDAN | Z67: =VLOOKUP($D67,records!$A:$V,7,FALSE) -> 44110 | AA67: Redevance 2026 | AB67: =VLOOKUP(O67,'records (2)'!$A:$Z,8,FALSE) -> 30 | AC67: FALSE | AF67: =VLOOKUP($D67,records!$A:$V,13,FALSE) -> FONDERIE ET MECANIQUE GENERALE CASTELBRIANTAISE sa - FMGC | AG67: Facture originale électronique à | AH67: =VLOOKUP($D67,records!$A:$V,19,FALSE) -> celine.chevrel@fmgc.net | AI67: . | AJ67: =VLOOKUP($O67,'records (2)'!$A:$Z,14,FALSE) -> 003IV000010t2ZCYAY | AK67: =VLOOKUP($O67,'records (2)'!$A:$Z,15,FALSE) -> Nadine CROUILBOIS | AL67: =VLOOKUP($O67,'records (2)'!$A:$Z,10,FALSE) -> 003IV000010t2ZCYAY | AM67: =VLOOKUP($O67,'records (2)'!$A:$Z,11,FALSE) -> Nadine CROUILBOIS | AN67: 1 | AO67: 1000 | AP67: 1000 | AQ67: 0 | AR67: 0
A68: VRNT-01701 | B68: VERNET | C68: VERNET | D68: 001IV000015SAHxYAO | E68: 01tIV00000GyVCbYAN | F68: Redevance d'utilisation - Tranche 25 ETP - Cas 2 | H68: Annual | I68: In advance | J68: 46023 | K68: 46387 | L68: Pixid France | M68: Pack C&S | N68: 46023 | O68: =VLOOKUP(D68,records!$A:$U,10,FALSE) -> 001SZ000001N3caYAC | P68: =VLOOKUP(D68,records!$A:$V,20,FALSE) -> FR77308528827 | Q68: =VLOOKUP(D68,records!$A:$V,12,FALSE) -> 30 852 882 700 022 | R68: Email | S68: =VLOOKUP(D68,records!$A:$U,19,FALSE) -> cerutti@vernet.fr | T68: Transfer | U68: Renewal | V68: =VLOOKUP($D68,records!$A:$V,3,FALSE) -> VERNET sas | X68: =VLOOKUP($D68,records!$A:$V,9,FALSE) -> 21-27 route d'Arpajon | Y68: =VLOOKUP($D68,records!$A:$V,4,FALSE) -> ARPAJON Cedex | Z68: =VLOOKUP($D68,records!$A:$V,7,FALSE) -> 91291 | AA68: Redevance 2026 | AB68: =VLOOKUP(O68,'records (2)'!$A:$Z,8,FALSE) -> 30 | AC68: FALSE | AF68: =VLOOKUP($D68,records!$A:$V,13,FALSE) -> VERNET sas | AG68: Facture originale électronique à | AH68: =VLOOKUP($D68,records!$A:$V,19,FALSE) -> cerutti@vernet.fr | AI68: . | AJ68: =VLOOKUP($O68,'records (2)'!$A:$Z,14,FALSE) -> 003IV000010tPagYAE | AK68: =VLOOKUP($O68,'records (2)'!$A:$Z,15,FALSE) -> Jean Christophe RIBEIRO | AL68: =VLOOKUP($O68,'records (2)'!$A:$Z,10,FALSE) -> 003IV000010tPagYAE | AM68: =VLOOKUP($O68,'records (2)'!$A:$Z,11,FALSE) -> Jean Christophe RIBEIRO | AN68: 1 | AO68: 4000 | AP68: 4000 | AQ68: 0 | AR68: 0
A69: DGRD-01933 | B69: DAGARD | C69: DAGARD | D69: 001IV000015S8jIYAS | E69: 01tIV00000GOfP1YAL | F69: Redevance d'utilisation - Tranche 25 ETP - Cas 1 | H69: Annual | I69: In advance | J69: 46023 | K69: 46387 | L69: Pixid France | M69: Pack C&S | N69: 46023 | O69: =VLOOKUP(D69,records!$A:$U,10,FALSE) -> 001SZ00000Oced1YAB | P69: =VLOOKUP(D69,records!$A:$V,20,FALSE) -> FR76995750288 | Q69: =VLOOKUP(D69,records!$A:$V,12,FALSE) -> 99 575 028 800 012 | R69: Email | S69: =VLOOKUP(D69,records!$A:$U,19,FALSE) -> cfournisseurs@dagard.com | T69: Transfer | U69: Renewal | V69: =VLOOKUP($D69,records!$A:$V,3,FALSE) -> DAGARD sas | X69: =VLOOKUP($D69,records!$A:$V,9,FALSE) -> Route du Stade | Y69: =VLOOKUP($D69,records!$A:$V,4,FALSE) -> BOUSSAC | Z69: =VLOOKUP($D69,records!$A:$V,7,FALSE) -> 23600 | AA69: Redevance 2026 | AB69: =VLOOKUP(O69,'records (2)'!$A:$Z,8,FALSE) -> 30 | AC69: FALSE | AF69: =VLOOKUP($D69,records!$A:$V,13,FALSE) -> DAGARD sas | AG69: Facture originale électronique à | AH69: =VLOOKUP($D69,records!$A:$V,19,FALSE) -> cfournisseurs@dagard.com | AI69: . | AJ69: =VLOOKUP($O69,'records (2)'!$A:$Z,14,FALSE) -> 003IV000010tJaCYAU | AK69: =VLOOKUP($O69,'records (2)'!$A:$Z,15,FALSE) -> Comptabilité Fournisseurs | AL69: =VLOOKUP($O69,'records (2)'!$A:$Z,10,FALSE) -> 003IV000010tJaCYAU | AM69: =VLOOKUP($O69,'records (2)'!$A:$Z,11,FALSE) -> Comptabilité Fournisseurs | AN69: 1 | AO69: 1000 | AP69: 1000 | AQ69: 0 | AR69: 0
A70: RDDJ-01721 | B70: REINE DE DIJON | C70: REINE DE DIJON | D70: 001IV000015S85lYAC | E70: 01tIV00000GOfP1YAL | F70: Redevance d'utilisation - Tranche 25 ETP - Cas 1 | H70: Annual | I70: In advance | J70: 46023 | K70: 46387 | L70: Pixid France | M70: Pack C&S | N70: 46023 | O70: =VLOOKUP(D70,records!$A:$U,10,FALSE) -> 0012p00004S28b2AAB | P70: =VLOOKUP(D70,records!$A:$V,20,FALSE) -> FR16394256275 | Q70: =VLOOKUP(D70,records!$A:$V,12,FALSE) -> 39 425 627 500 022 | R70: Email | S70: =VLOOKUP(D70,records!$A:$U,19,FALSE) -> cguichard@reinededijon.fr | T70: Transfer | U70: Renewal | V70: =VLOOKUP($D70,records!$A:$V,3,FALSE) -> REINE DE DIJON sas | X70: =VLOOKUP($D70,records!$A:$V,9,FALSE) -> 1 Rue des Combets | Y70: =VLOOKUP($D70,records!$A:$V,4,FALSE) -> FLEUREY-SUR-OUCHE | Z70: =VLOOKUP($D70,records!$A:$V,7,FALSE) -> 21410 | AA70: Redevance 2026 | AB70: =VLOOKUP(O70,'records (2)'!$A:$Z,8,FALSE) -> 45 | AC70: FALSE | AF70: =VLOOKUP($D70,records!$A:$V,13,FALSE) -> REINE DE DIJON sas | AG70: Facture originale électronique à | AH70: =VLOOKUP($D70,records!$A:$V,19,FALSE) -> cguichard@reinededijon.fr | AI70: . | AJ70: =VLOOKUP($O70,'records (2)'!$A:$Z,14,FALSE) -> 003IV000010tIe0YAE | AK70: =VLOOKUP($O70,'records (2)'!$A:$Z,15,FALSE) -> Céline GUICHARD | AL70: =VLOOKUP($O70,'records (2)'!$A:$Z,10,FALSE) -> 003IV000010tIe0YAE | AM70: =VLOOKUP($O70,'records (2)'!$A:$Z,11,FALSE) -> Céline GUICHARD | AN70: 1 | AO70: 500 | AP70: 500 | AQ70: 0 | AR70: 0
A71: GPEP-01591 | B71: GROUPE EUREDEN | C71: GROUPE EUREDEN - (ex GROUPE D'AUCY - PEP sas) | D71: 001IV000015S2eEYAS | E71: 01tIV00000GyVCbYAN | F71: Redevance d'utilisation - Tranche 25 ETP - Cas 2 | H71: Annual | I71: In advance | J71: 46023 | K71: 46387 | L71: Pixid France | M71: Pack C&S | N71: 46023 | O71: =VLOOKUP(D71,records!$A:$U,10,FALSE) -> 0012p00004RB7pqAAD | P71: =VLOOKUP(D71,records!$A:$V,20,FALSE) -> FR32420800492 | Q71: =VLOOKUP(D71,records!$A:$V,12,FALSE) -> 42 080 049 200 027 | R71: Email | S71: =VLOOKUP(D71,records!$A:$U,19,FALSE) -> charline.leberrigaud@eureden.com | T71: Transfer | U71: Renewal | V71: =VLOOKUP($D71,records!$A:$V,3,FALSE) -> PEP sasu | X71: =VLOOKUP($D71,records!$A:$V,9,FALSE) -> ZI de Camagnon | Y71: =VLOOKUP($D71,records!$A:$V,4,FALSE) -> PLOERMEL | Z71: =VLOOKUP($D71,records!$A:$V,7,FALSE) -> 56800 | AA71: Redevance 2026 | AB71: =VLOOKUP(O71,'records (2)'!$A:$Z,8,FALSE) -> 30 | AC71: FALSE | AF71: =VLOOKUP($D71,records!$A:$V,13,FALSE) -> PEP sasu | AG71: Facture originale électronique à | AH71: =VLOOKUP($D71,records!$A:$V,19,FALSE) -> charline.leberrigaud@eureden.com | AI71: . | AJ71: =VLOOKUP($O71,'records (2)'!$A:$Z,14,FALSE) -> 003IV000010t2zrYAA | AK71: =VLOOKUP($O71,'records (2)'!$A:$Z,15,FALSE) -> Régine OGER | AL71: =VLOOKUP($O71,'records (2)'!$A:$Z,10,FALSE) -> 003IV000010tRW1YAM | AM71: =VLOOKUP($O71,'records (2)'!$A:$Z,11,FALSE) -> Christian HUET | AN71: 1 | AO71: 4000 | AP71: 4000 | AQ71: 0 | AR71: 0
A72: TXLS-01877 | B72: TEXELIS | C72: TEXELIS | D72: 001IV000015S8jEYAS | E72: 01tIV00000GOfP1YAL | F72: Redevance d'utilisation - Tranche 25 ETP - Cas 1 | H72: Annual | I72: In advance | J72: 46023 | K72: 46387 | L72: Pixid France | M72: Pack C&S | N72: 46023 | O72: =VLOOKUP(D72,records!$A:$U,10,FALSE) -> 001SZ000009VR6pYAG | P72: =VLOOKUP(D72,records!$A:$V,20,FALSE) -> FR07501698419 | Q72: =VLOOKUP(D72,records!$A:$V,12,FALSE) -> 50 169 841 900 022 | R72: Email | S72: =VLOOKUP(D72,records!$A:$U,19,FALSE) -> charlotte.maillard@texelis.com | T72: Transfer | U72: Renewal | V72: =VLOOKUP($D72,records!$A:$V,3,FALSE) -> TEXELIS sasu | X72: =VLOOKUP($D72,records!$A:$V,9,FALSE) -> 72 Route du Palais | Y72: =VLOOKUP($D72,records!$A:$V,4,FALSE) -> LIMOGES CEDEX 1 | Z72: =VLOOKUP($D72,records!$A:$V,7,FALSE) -> 87011 | AA72: Redevance 2026 | AB72: =VLOOKUP(O72,'records (2)'!$A:$Z,8,FALSE) -> 45 | AC72: FALSE | AF72: =VLOOKUP($D72,records!$A:$V,13,FALSE) -> TEXELIS sasu | AG72: Facture originale électronique à | AH72: =VLOOKUP($D72,records!$A:$V,19,FALSE) -> charlotte.maillard@texelis.com | AI72: . | AJ72: =VLOOKUP($O72,'records (2)'!$A:$Z,14,FALSE) -> 003IV000010t3skYAA | AK72: =VLOOKUP($O72,'records (2)'!$A:$Z,15,FALSE) -> Magalie DAUGE | AL72: =VLOOKUP($O72,'records (2)'!$A:$Z,10,FALSE) -> 003IV000010t3skYAA | AM72: =VLOOKUP($O72,'records (2)'!$A:$Z,11,FALSE) -> Magalie DAUGE | AN72: 1 | AO72: 1000 | AP72: 1000 | AQ72: 0 | AR72: 0
A73: CPCH-01648 | B73: CORDEN PHARMA CHENOVE | C73: CORDEN PHARMA CHENOVE | D73: 001IV000015RewKYAS | E73: 01tIV00000GOfP1YAL | F73: Redevance d'utilisation - Tranche 25 ETP - Cas 1 | H73: Annual | I73: In advance | J73: 46023 | K73: 46387 | L73: Pixid France | M73: Pack C&S | N73: 46023 | O73: =VLOOKUP(D73,records!$A:$U,10,FALSE) -> 0012p00004TGasWAAT | P73: =VLOOKUP(D73,records!$A:$V,20,FALSE) -> FR92421181819 | Q73: =VLOOKUP(D73,records!$A:$V,12,FALSE) -> 42 118 181 900 010 | R73: Email | S73: =VLOOKUP(D73,records!$A:$U,19,FALSE) -> chenove.comptabilite@cordenpharma.com | T73: Transfer | U73: Renewal | V73: =VLOOKUP($D73,records!$A:$V,3,FALSE) -> CORDEN PHARMA CHENOVE sasu | X73: =VLOOKUP($D73,records!$A:$V,9,FALSE) -> 47 rue de Longvic | Y73: =VLOOKUP($D73,records!$A:$V,4,FALSE) -> CHENOVE | Z73: =VLOOKUP($D73,records!$A:$V,7,FALSE) -> 21300 | AA73: Redevance 2026 | AB73: =VLOOKUP(O73,'records (2)'!$A:$Z,8,FALSE) -> 30 | AC73: FALSE | AF73: =VLOOKUP($D73,records!$A:$V,13,FALSE) -> CORDEN PHARMA CHENOVE sasu | AG73: Facture originale électronique à | AH73: =VLOOKUP($D73,records!$A:$V,19,FALSE) -> chenove.comptabilite@cordenpharma.com | AI73: . | AJ73: =VLOOKUP($O73,'records (2)'!$A:$Z,14,FALSE) -> 003IV000010tIiQYAU | AK73: =VLOOKUP($O73,'records (2)'!$A:$Z,15,FALSE) -> Nathalie CATTANEO | AL73: =VLOOKUP($O73,'records (2)'!$A:$Z,10,FALSE) -> 003IV000010tIiQYAU | AM73: =VLOOKUP($O73,'records (2)'!$A:$Z,11,FALSE) -> Nathalie CATTANEO | AN73: 1 | AO73: 1000 | AP73: 1000 | AQ73: 0 | AR73: 0
A74: RNRA-01573 | B74: REYNAERS ALUMINIUM SAS | C74: REYNAERS ALUMINIUM | D74: 001IV000015S2e8YAC | E74: 01tIV00000GOfP1YAL | F74: Redevance d'utilisation - Tranche 25 ETP - Cas 1 | H74: Annual | I74: In advance | J74: 46023 | K74: 46387 | L74: Pixid France | M74: Pack C&S | N74: 46023 | O74: =VLOOKUP(D74,records!$A:$U,10,FALSE) -> 0012p00004NeUaTAAV | P74: =VLOOKUP(D74,records!$A:$V,20,FALSE) -> FR06399227263 | Q74: =VLOOKUP(D74,records!$A:$V,12,FALSE) -> 39 922 726 300 072 | R74: Email | S74: =VLOOKUP(D74,records!$A:$U,19,FALSE) -> chm@reynaers.com | T74: Transfer | U74: Renewal | V74: =VLOOKUP($D74,records!$A:$V,3,FALSE) -> REYNAERS ALUMINIUM sasu | X74: =VLOOKUP($D74,records!$A:$V,9,FALSE) -> Route de Brouchy | Y74: =VLOOKUP($D74,records!$A:$V,4,FALSE) -> HAM | Z74: =VLOOKUP($D74,records!$A:$V,7,FALSE) -> 80400 | AA74: Redevance 2026 | AB74: =VLOOKUP(O74,'records (2)'!$A:$Z,8,FALSE) -> 30 | AC74: FALSE | AF74: =VLOOKUP($D74,records!$A:$V,13,FALSE) -> REYNAERS ALUMINIUM sasu | AG74: Facture originale électronique à | AH74: =VLOOKUP($D74,records!$A:$V,19,FALSE) -> chm@reynaers.com | AI74: . | AJ74: =VLOOKUP($O74,'records (2)'!$A:$Z,14,FALSE) -> 003IV000010tRVRYA2 | AK74: =VLOOKUP($O74,'records (2)'!$A:$Z,15,FALSE) -> Christelle MERESSE | AL74: =VLOOKUP($O74,'records (2)'!$A:$Z,10,FALSE) -> 003IV000010t2QNYAY | AM74: =VLOOKUP($O74,'records (2)'!$A:$Z,11,FALSE) -> Stephane VAYSSIERE | AN74: 1 | AO74: 500 | AP74: 500 | AQ74: 0 | AR74: 0
A75: EUFR-01878 | B75: EURIAL ULTRA-FRAIS | C75: EURIAL ULTRA-FRAIS - Château Salins | D75: 001IV000015S2eZYAS | E75: 01tIV00000GyVCbYAN | F75: Redevance d'utilisation - Tranche 25 ETP - Cas 2 | H75: Annual | I75: In advance | J75: 46023 | K75: 46387 | L75: Pixid France | M75: Pack C&S | N75: 46023 | O75: =VLOOKUP(D75,records!$A:$U,10,FALSE) -> 0012p00004Rel0OAAR | P75: =VLOOKUP(D75,records!$A:$V,20,FALSE) -> FR31705580108 | Q75: =VLOOKUP(D75,records!$A:$V,12,FALSE) -> 70 558 010 800 102 | R75: Email | S75: =VLOOKUP(D75,records!$A:$U,19,FALSE) -> christophe.renoncial@eurial.eu | T75: Transfer | U75: Renewal | V75: =VLOOKUP($D75,records!$A:$V,3,FALSE) -> EURIAL ULTRA FRAIS sasu | X75: =VLOOKUP($D75,records!$A:$V,9,FALSE) -> Avenue des Saulniers | Y75: =VLOOKUP($D75,records!$A:$V,4,FALSE) -> CHATEAU SALINS | Z75: =VLOOKUP($D75,records!$A:$V,7,FALSE) -> 57170 | AA75: Redevance 2026 | AB75: =VLOOKUP(O75,'records (2)'!$A:$Z,8,FALSE) -> 30 | AC75: FALSE | AF75: =VLOOKUP($D75,records!$A:$V,13,FALSE) -> EURIAL ULTRA FRAIS sasu | AG75: Facture originale électronique à | AH75: =VLOOKUP($D75,records!$A:$V,19,FALSE) -> christophe.renoncial@eurial.eu | AI75: . | AJ75: =VLOOKUP($O75,'records (2)'!$A:$Z,14,FALSE) -> 003IV000010tJZVYA2 | AK75: =VLOOKUP($O75,'records (2)'!$A:$Z,15,FALSE) -> Christophe RENONCIAL | AL75: =VLOOKUP($O75,'records (2)'!$A:$Z,10,FALSE) -> 003IV000010tJZVYA2 | AM75: =VLOOKUP($O75,'records (2)'!$A:$Z,11,FALSE) -> Christophe RENONCIAL | AN75: 1 | AO75: 3000 | AP75: 3000 | AQ75: 0 | AR75: 0
... A84: WESR-01594 | B84: WESER | C84: WESER | D84: 001IV000015S2eUYAS | E84: 01tIV00000GOfP6YAL | F84: Redevance d'utilisation - ETP EU | H84: Annual | I84: In advance | J84: 46023 | K84: 46387 | L84: Pixid France | M84: Pack C&S | N84: 46023 | O84: =VLOOKUP(D84,records!$A:$U,10,FALSE) -> 0012p00004RJUKLAA5 | P84: =VLOOKUP(D84,records!$A:$V,20,FALSE) -> FR24654801026 | Q84: =VLOOKUP(D84,records!$A:$V,12,FALSE) -> 65 480 102 600 018 | R84: Email | S84: =VLOOKUP(D84,records!$A:$U,19,FALSE) -> compta.fournisseurs@weser.fr | T84: Transfer | U84: Renewal | V84: =VLOOKUP($D84,records!$A:$V,3,FALSE) -> WESER sas | X84: =VLOOKUP($D84,records!$A:$V,9,FALSE) -> 1 Route de Cléré | Y84: =VLOOKUP($D84,records!$A:$V,4,FALSE) -> MAZIERES DE TOURAINE | Z84: =VLOOKUP($D84,records!$A:$V,7,FALSE) -> 37130 | AA84: Redevance 2026 | AB84: =VLOOKUP(O84,'records (2)'!$A:$Z,8,FALSE) -> 30 | AC84: FALSE | AF84: =VLOOKUP($D84,records!$A:$V,13,FALSE) -> WESER sas | AG84: Facture originale électronique à | AH84: =VLOOKUP($D84,records!$A:$V,19,FALSE) -> compta.fournisseurs@weser.fr | AI84: . | AJ84: =VLOOKUP($O84,'records (2)'!$A:$Z,14,FALSE) -> 003IV000010tIe4YAE | AK84: =VLOOKUP($O84,'records (2)'!$A:$Z,15,FALSE) -> Lydie GAUDIN (compta) | AL84: =VLOOKUP($O84,'records (2)'!$A:$Z,10,FALSE) -> 003IV000010tIe4YAE | AM84: =VLOOKUP($O84,'records (2)'!$A:$Z,11,FALSE) -> Lydie GAUDIN (compta) | AN84: 1 | AO84: 3120 | AP84: 3120 | AQ84: 0 | AR84: 0
A85: PLVL-01764 | B85: PLASTIVALOIRE | C85: PLASTIVALOIRE | D85: 001IV000015S8irYAC | E85: 01tIV00000GOfP1YAL | F85: Redevance d'utilisation - Tranche 25 ETP - Cas 1 | H85: Annual | I85: In advance | J85: 46023 | K85: 46387 | L85: Pixid France | M85: Pack C&S | N85: 46023 | O85: =VLOOKUP(D85,records!$A:$U,10,FALSE) -> 0012p00004Sfc9aAAB | P85: =VLOOKUP(D85,records!$A:$V,20,FALSE) -> FR14644800161 | Q85: =VLOOKUP(D85,records!$A:$V,12,FALSE) -> 64 480 016 100 015 | R85: Email | S85: =VLOOKUP(D85,records!$A:$U,19,FALSE) -> compta.groupe@plastivaloire.com | T85: Transfer | U85: Renewal | V85: =VLOOKUP($D85,records!$A:$V,3,FALSE) -> PLASTIQUES DU VAL DE LOIRE sa | W85: =IFERROR(VLOOKUP($D85,records!$A:$V,6,FALSE),) -> Comptabilité & ressources Humaines | X85: =VLOOKUP($D85,records!$A:$V,9,FALSE) -> 1 route de la Retaudière - E.I. Nord - BP 38 | Y85: =VLOOKUP($D85,records!$A:$V,4,FALSE) -> LANGEAIS | Z85: =VLOOKUP($D85,records!$A:$V,7,FALSE) -> 37130 | AA85: Redevance 2026 | AB85: =VLOOKUP(O85,'records (2)'!$A:$Z,8,FALSE) -> 30 | AC85: FALSE | AF85: =VLOOKUP($D85,records!$A:$V,13,FALSE) -> PLASTIQUES DU VAL DE LOIRE sa | AG85: Facture originale électronique à | AH85: =VLOOKUP($D85,records!$A:$V,19,FALSE) -> compta.groupe@plastivaloire.com | AI85: . | AJ85: =VLOOKUP($O85,'records (2)'!$A:$Z,14,FALSE) -> 003IV000010tJXjYAM | AK85: =VLOOKUP($O85,'records (2)'!$A:$Z,15,FALSE) -> Aurélie BOISSONNEAU (compta.groupe) | AL85: =VLOOKUP($O85,'records (2)'!$A:$Z,10,FALSE) -> 003IV000010tJXjYAM | AM85: =VLOOKUP($O85,'records (2)'!$A:$Z,11,FALSE) -> Aurélie BOISSONNEAU (compta.groupe) | AN85: 1 | AO85: 6500 | AP85: 6500 | AQ85: 0 | AR85: 0
A86: SAEM-01806 | B86: SAEM ENERGIES | C86: SAEM ENERGIES | D86: 001IV000015S2eFYAS | E86: 01tIV00000GOfP1YAL | F86: Redevance d'utilisation - Tranche 25 ETP - Cas 1 | H86: Annual | I86: In advance | J86: 46023 | K86: 46387 | L86: Pixid France | M86: Pack C&S | N86: 46023 | O86: =VLOOKUP(D86,records!$A:$U,10,FALSE) -> 0012p00004RBJMwAAP | P86: =VLOOKUP(D86,records!$A:$V,20,FALSE) -> FR72801339524 | Q86: =VLOOKUP(D86,records!$A:$V,12,FALSE) -> 80 133 952 400 010 | R86: Email | S86: =VLOOKUP(D86,records!$A:$U,19,FALSE) -> compta.saem@engie.com | T86: Transfer | U86: Renewal | V86: =VLOOKUP($D86,records!$A:$V,3,FALSE) -> SAEM sas | W86: =IFERROR(VLOOKUP($D86,records!$A:$V,6,FALSE),) -> SAEM ENERGIES | X86: =VLOOKUP($D86,records!$A:$V,9,FALSE) -> 2 Boulevard Jean Lafaure | Y86: =VLOOKUP($D86,records!$A:$V,4,FALSE) -> CUSSET | Z86: =VLOOKUP($D86,records!$A:$V,7,FALSE) -> 3300 | AA86: Redevance 2026 | AB86: =VLOOKUP(O86,'records (2)'!$A:$Z,8,FALSE) -> 30 | AC86: FALSE | AF86: =VLOOKUP($D86,records!$A:$V,13,FALSE) -> SAEM sas | AG86: Facture originale électronique à | AH86: =VLOOKUP($D86,records!$A:$V,19,FALSE) -> compta.saem@engie.com | AI86: . | AJ86: =VLOOKUP($O86,'records (2)'!$A:$Z,14,FALSE) -> 003IV000010tRW6YAM | AK86: =VLOOKUP($O86,'records (2)'!$A:$Z,15,FALSE) -> Rémi LUCENET | AL86: =VLOOKUP($O86,'records (2)'!$A:$Z,10,FALSE) -> 003IV000010tRW6YAM | AM86: =VLOOKUP($O86,'records (2)'!$A:$Z,11,FALSE) -> Rémi LUCENET | AN86: 1 | AO86: 500 | AP86: 500
A87: BGRD-01647 | B87: BONGARD | C87: BONGARD | D87: 001IV000015S2eNYAS | E87: 01tIV00000GyVCbYAN | F87: Redevance d'utilisation - Tranche 25 ETP - Cas 2 | H87: Annual | I87: In advance | J87: 46023 | K87: 46387 | L87: Pixid France | M87: Pack C&S | N87: 46023 | O87: =VLOOKUP(D87,records!$A:$U,10,FALSE) -> 0012p00004MRCLYAA5 | P87: =VLOOKUP(D87,records!$A:$V,20,FALSE) -> FR12582950309 | Q87: =VLOOKUP(D87,records!$A:$V,12,FALSE) -> 58 295 030 900 051 | R87: Email | S87: =VLOOKUP(D87,records!$A:$U,19,FALSE) -> compta@afebakery.fr | T87: Transfer | U87: Renewal | V87: =VLOOKUP($D87,records!$A:$V,3,FALSE) -> BONGARD sas | W87: =IFERROR(VLOOKUP($D87,records!$A:$V,6,FALSE),) -> Comptabilité | X87: =VLOOKUP($D87,records!$A:$V,9,FALSE) -> 32 route de Wolfisheim | Y87: =VLOOKUP($D87,records!$A:$V,4,FALSE) -> HOLTZHEIM | Z87: =VLOOKUP($D87,records!$A:$V,7,FALSE) -> 67810 | AA87: Redevance 2026 | AB87: =VLOOKUP(O87,'records (2)'!$A:$Z,8,FALSE) -> 30 | AC87: FALSE | AF87: =VLOOKUP($D87,records!$A:$V,13,FALSE) -> BONGARD sas | AG87: Facture originale électronique à | AH87: =VLOOKUP($D87,records!$A:$V,19,FALSE) -> compta@afebakery.fr | AI87: . | AJ87: =VLOOKUP($O87,'records (2)'!$A:$Z,14,FALSE) -> 003IV000010tIeYYAU | AK87: =VLOOKUP($O87,'records (2)'!$A:$Z,15,FALSE) -> Sylvie KREMER | AL87: =VLOOKUP($O87,'records (2)'!$A:$Z,10,FALSE) -> 003IV000010tTt4YAE | AM87: =VLOOKUP($O87,'records (2)'!$A:$Z,11,FALSE) -> Aurore MARCHAND | AN87: 1 | AO87: 1000 | AP87: 1000 | AQ87: 0 | AR87: 0
A88: SAMB-01819 | B88: SAMB | C88: SAMB | D88: 001IV000015SAHmYAO | E88: 01tIV00000GOfP1YAL | F88: Redevance d'utilisation - Tranche 25 ETP - Cas 1 | H88: Annual | I88: In advance | J88: 46023 | K88: 46387 | L88: Pixid France | M88: Pack C&S | N88: 46023 | O88: =VLOOKUP(D88,records!$A:$U,10,FALSE) -> 0012p00004SiWGTAA3 | P88: =VLOOKUP(D88,records!$A:$V,20,FALSE) -> FR26505317172 | Q88: =VLOOKUP(D88,records!$A:$V,12,FALSE) -> 31 349 840 400 067 | R88: Email | S88: =VLOOKUP(D88,records!$A:$U,19,FALSE) -> compta@atelier36.fr | T88: Transfer | U88: Renewal | V88: =VLOOKUP($D88,records!$A:$V,3,FALSE) -> SAMB sasu | X88: =VLOOKUP($D88,records!$A:$V,9,FALSE) -> 18 Allée Gaspard Monge - ZI des Daubourgs | Y88: =VLOOKUP($D88,records!$A:$V,4,FALSE) -> LE BLANC | Z88: =VLOOKUP($D88,records!$A:$V,7,FALSE) -> 36300 | AA88: Redevance 2026 | AB88: =VLOOKUP(O88,'records (2)'!$A:$Z,8,FALSE) -> 30 | AC88: FALSE | AF88: =VLOOKUP($D88,records!$A:$V,13,FALSE) -> SAMB sasu | AG88: Facture originale électronique à | AH88: =VLOOKUP($D88,records!$A:$V,19,FALSE) -> compta@atelier36.fr | AI88: . | AJ88: =VLOOKUP($O88,'records (2)'!$A:$Z,14,FALSE) -> 003IV000010su8xYAA | AK88: =VLOOKUP($O88,'records (2)'!$A:$Z,15,FALSE) -> Daphné AUDOUIN | AL88: =VLOOKUP($O88,'records (2)'!$A:$Z,10,FALSE) -> 003IV000010su8xYAA | AM88: =VLOOKUP($O88,'records (2)'!$A:$Z,11,FALSE) -> Daphné AUDOUIN | AN88: 1 | AO88: 1500 | AP88: 1500 | AQ88: 0 | AR88: 0
A89: CHPR-01547 | B89: CHARLES PERROUD | C89: CHARLES PERROUD | D89: 001IV000015S8ifYAC | E89: 01tIV00000GyVCbYAN | F89: Redevance d'utilisation - Tranche 25 ETP - Cas 2 | H89: Annual | I89: In advance | J89: 46023 | K89: 46387 | L89: Pixid France | M89: Pack C&S | N89: 46023 | O89: =VLOOKUP(D89,records!$A:$U,10,FALSE) -> 0012p00004ONPiSAAX | P89: =VLOOKUP(D89,records!$A:$V,20,FALSE) -> FR74301166138 | Q89: =VLOOKUP(D89,records!$A:$V,12,FALSE) -> 30 116 613 800 034 | R89: Email | S89: =VLOOKUP(D89,records!$A:$U,19,FALSE) -> compta@charles-perroud.com | T89: Transfer | U89: Renewal | V89: =VLOOKUP($D89,records!$A:$V,3,FALSE) -> CHARLES PERROUD sas | X89: =VLOOKUP($D89,records!$A:$V,9,FALSE) -> 173 route de Chapernay | Y89: =VLOOKUP($D89,records!$A:$V,4,FALSE) -> LENTILLY | Z89: =VLOOKUP($D89,records!$A:$V,7,FALSE) -> 69210 | AA89: Redevance 2026 | AB89: =VLOOKUP(O89,'records (2)'!$A:$Z,8,FALSE) -> 30 | AC89: FALSE | AF89: =VLOOKUP($D89,records!$A:$V,13,FALSE) -> CHARLES PERROUD sas | AG89: Facture originale électronique à | AH89: =VLOOKUP($D89,records!$A:$V,19,FALSE) -> compta@charles-perroud.com | AI89: . | AJ89: =VLOOKUP($O89,'records (2)'!$A:$Z,14,FALSE) -> 003IV000010t2foYAA | AK89: =VLOOKUP($O89,'records (2)'!$A:$Z,15,FALSE) -> Stéphanie VILLEDIEU | AL89: =VLOOKUP($O89,'records (2)'!$A:$Z,10,FALSE) -> 003IV000010t2foYAA | AM89: =VLOOKUP($O89,'records (2)'!$A:$Z,11,FALSE) -> Stéphanie VILLEDIEU | AN89: 1 | AO89: 1000 | AP89: 1000 | AQ89: 0 | AR89: 0
A90: ELTP-01876 | B90: ELECTROPOLI | C90: ELECTROPOLI | D90: 001IV000015RyE2YAK | E90: 01tIV00000GOfP1YAL | F90: Redevance d'utilisation - Tranche 25 ETP - Cas 1 | H90: Annual | I90: In advance | J90: 46023 | K90: 46387 | L90: Pixid France | M90: Pack C&S | N90: 46023 | O90: =VLOOKUP(D90,records!$A:$U,10,FALSE) -> 001SZ000009hKuUYAU | P90: =VLOOKUP(D90,records!$A:$V,20,FALSE) -> FR48420454175 | Q90: =VLOOKUP(D90,records!$A:$V,12,FALSE) -> 42 045 417 500 035 | R90: Email | S90: =VLOOKUP(D90,records!$A:$U,19,FALSE) -> compta@electropoli.com | T90: Transfer | U90: Renewal | V90: =VLOOKUP($D90,records!$A:$V,3,FALSE) -> ELECTROPOLI FRANCE sarl | W90: =IFERROR(VLOOKUP($D90,records!$A:$V,6,FALSE),) -> Service Comptabilité | X90: =VLOOKUP($D90,records!$A:$V,9,FALSE) -> Le Grand Chemin | Y90: =VLOOKUP($D90,records!$A:$V,4,FALSE) -> ISIGNY LE BUAT | Z90: =VLOOKUP($D90,records!$A:$V,7,FALSE) -> 50540 | AA90: Redevance 2026 | AB90: =VLOOKUP(O90,'records (2)'!$A:$Z,8,FALSE) -> 30 | AC90: FALSE | AF90: =VLOOKUP($D90,records!$A:$V,13,FALSE) -> ELECTROPOLI FRANCE sarl | AG90: Facture originale électronique à | AH90: =VLOOKUP($D90,records!$A:$V,19,FALSE) -> compta@electropoli.com | AI90: . | AJ90: =VLOOKUP($O90,'records (2)'!$A:$Z,14,FALSE) -> 003IV000010tJWDYA2 | AK90: =VLOOKUP($O90,'records (2)'!$A:$Z,15,FALSE) -> Florent MONTAUFRAY | AL90: =VLOOKUP($O90,'records (2)'!$A:$Z,10,FALSE) -> 003IV000010tJWDYA2 | AM90: =VLOOKUP($O90,'records (2)'!$A:$Z,11,FALSE) -> Florent MONTAUFRAY | AN90: 1 | AO90: 500 | AP90: 500 | AQ90: 0 | AR90: 0
A91: URGO-01687 | B91: URGO | C91: URGO | D91: 001IV000015RzTXYA0 | E91: 01tIV00000GOfP1YAL | F91: Redevance d'utilisation - Tranche 25 ETP - Cas 1 | H91: Annual | I91: In advance | J91: 46023 | K91: 46387 | L91: Pixid France | M91: Pack C&S | N91: 46023 | O91: =VLOOKUP(D91,records!$A:$U,10,FALSE) -> 0012p00004Rfp1kAAB | P91: =VLOOKUP(D91,records!$A:$V,20,FALSE) -> FR29433842044 | Q91: =VLOOKUP(D91,records!$A:$V,12,FALSE) -> 43 384 204 400 052 | R91: Email | S91: =VLOOKUP(D91,records!$A:$U,19,FALSE) -> compta@fr.urgo.com | T91: Transfer | U91: Renewal | V91: =VLOOKUP($D91,records!$A:$V,3,FALSE) -> LABORATOIRES URGO sasu | W91: =IFERROR(VLOOKUP($D91,records!$A:$V,6,FALSE),) -> Comptabilité Fournisseurs | X91: =VLOOKUP($D91,records!$A:$V,9,FALSE) -> 42 rue de Longvic | Y91: =VLOOKUP($D91,records!$A:$V,4,FALSE) -> CHENOVE | Z91: =VLOOKUP($D91,records!$A:$V,7,FALSE) -> 21300 | AA91: Redevance 2026 | AB91: =VLOOKUP(O91,'records (2)'!$A:$Z,8,FALSE) -> 30 | AC91: =VLOOKUP(O91,'records (4)'!$A:$C,3,FALSE) -> TRUE | AD91: YES | AE91: 46023 | AF91: =VLOOKUP($D91,records!$A:$V,13,FALSE) -> LABORATOIRES URGO sasu | AG91: Facture originale électronique à | AH91: =VLOOKUP($D91,records!$A:$V,19,FALSE) -> compta@fr.urgo.com | AI91: . | AJ91: =VLOOKUP($O91,'records (2)'!$A:$Z,14,FALSE) -> 003IV000010tJXYYA2 | AK91: =VLOOKUP($O91,'records (2)'!$A:$Z,15,FALSE) -> Morgane CICHY | AL91: =VLOOKUP($O91,'records (2)'!$A:$Z,10,FALSE) -> 003IV000010tJXYYA2 | AM91: =VLOOKUP($O91,'records (2)'!$A:$Z,11,FALSE) -> Morgane CICHY | AN91: 1 | AO91: 2500 | AP91: 2500 | AQ91: 0 | AR91: 0
A92: HBRM-01719 | B92: HERBAROM | C92: HERBAROM | D92: 001IV000015RyDpYAK | E92: 01tIV00000GOfP1YAL | F92: Redevance d'utilisation - Tranche 25 ETP - Cas 1 | H92: Annual | I92: In advance | J92: 46023 | K92: 46387 | L92: Pixid France | M92: Pack C&S | N92: 46023 | O92: =VLOOKUP(D92,records!$A:$U,10,FALSE) -> 001SZ000001IBfbYAG | P92: =VLOOKUP(D92,records!$A:$V,20,FALSE) -> FR18394280267 | Q92: =VLOOKUP(D92,records!$A:$V,12,FALSE) -> 39 428 026 700 037 | R92: Email | S92: =VLOOKUP(D92,records!$A:$U,19,FALSE) -> compta@herbarom-laboratoire.com | T92: Transfer | U92: Renewal | V92: =VLOOKUP($D92,records!$A:$V,3,FALSE) -> HERBAROM LABORATOIRE sas | W92: =IFERROR(VLOOKUP($D92,records!$A:$V,6,FALSE),) -> RH | X92: =VLOOKUP($D92,records!$A:$V,9,FALSE) -> 31 Avenue de Lautagne | Y92: =VLOOKUP($D92,records!$A:$V,4,FALSE) -> VALENCE | Z92: =VLOOKUP($D92,records!$A:$V,7,FALSE) -> 26000 | AA92: Redevance 2026 | AB92: =VLOOKUP(O92,'records (2)'!$A:$Z,8,FALSE) -> 30 | AC92: FALSE | AF92: =VLOOKUP($D92,records!$A:$V,13,FALSE) -> HERBAROM LABORATOIRE sas | AG92: Facture originale électronique à | AH92: =VLOOKUP($D92,records!$A:$V,19,FALSE) -> compta@herbarom-laboratoire.com | AI92: . | AJ92: =VLOOKUP($O92,'records (2)'!$A:$Z,10,FALSE) -> 003IV000010tI5MYAU | AK92: =VLOOKUP($O92,'records (2)'!$A:$Z,11,FALSE) -> Nelly FAVEYROLLES | AL92: =VLOOKUP($O92,'records (2)'!$A:$Z,10,FALSE) -> 003IV000010tI5MYAU | AM92: =VLOOKUP($O92,'records (2)'!$A:$Z,11,FALSE) -> Nelly FAVEYROLLES | AN92: 1 | AO92: 1000 | AP92: 1000 | AQ92: 0 | AR92: 0
A93: JOUS-01678 | B93: JOUSSEAU SAS | C93: JOUSSEAU | D93: 001IV000015S864YAC | E93: 01tIV00000GOfP1YAL | F93: Redevance d'utilisation - Tranche 25 ETP - Cas 1 | H93: Annual | I93: In advance | J93: 46023 | K93: 46387 | L93: Pixid France | M93: Pack C&S | N93: 46023 | O93: =VLOOKUP(D93,records!$A:$U,10,FALSE) -> 001SZ0000012WT4YAM | P93: =VLOOKUP(D93,records!$A:$V,20,FALSE) -> FR07480108935 | Q93: =VLOOKUP(D93,records!$A:$V,12,FALSE) -> 48 010 893 500 010 | R93: Email | S93: =VLOOKUP(D93,records!$A:$U,19,FALSE) -> compta@jousseau.com | T93: Transfer | U93: Renewal | V93: =VLOOKUP($D93,records!$A:$V,3,FALSE) -> SAS JOUSSEAU | X93: =VLOOKUP($D93,records!$A:$V,9,FALSE) -> 32 rue du 19 mars 1962 | Y93: =VLOOKUP($D93,records!$A:$V,4,FALSE) -> VIRE | Z93: =VLOOKUP($D93,records!$A:$V,7,FALSE) -> 71260 | AA93: Redevance 2026 | AB93: =VLOOKUP(O93,'records (2)'!$A:$Z,8,FALSE) -> 30 | AC93: FALSE | AF93: =VLOOKUP($D93,records!$A:$V,13,FALSE) -> SAS JOUSSEAU | AG93: Facture originale électronique à | AH93: =VLOOKUP($D93,records!$A:$V,19,FALSE) -> compta@jousseau.com | AI93: . | AJ93: =VLOOKUP($O93,'records (2)'!$A:$Z,14,FALSE) -> 003IV000010tIepYAE | AK93: =VLOOKUP($O93,'records (2)'!$A:$Z,15,FALSE) -> Corinne JOUSSEAU (compta) | AL93: =VLOOKUP($O93,'records (2)'!$A:$Z,10,FALSE) -> 003IV000010tLcYYAU | AM93: =VLOOKUP($O93,'records (2)'!$A:$Z,11,FALSE) -> Corinne JOUSSEAU | AN93: 1 | AO93: 500 | AP93: 500 | AQ93: 0 | AR93: 0
A94: PDGP-01507 | B94: PDG Plastiques | C94: PDG PLASTIQUES | D94: 001IV000015S6ZyYAK | E94: 01tIV00000GyVCbYAN | F94: Redevance d'utilisation - Tranche 25 ETP - Cas 2 | H94: Annual | I94: In advance | J94: 46023 | K94: 46387 | L94: Pixid France | M94: Pack C&S | N94: 46023 | O94: =VLOOKUP(D94,records!$A:$U,10,FALSE) -> 0012p00004NLHuzAAH | P94: =VLOOKUP(D94,records!$A:$V,20,FALSE) -> FR63331468223 | Q94: =VLOOKUP(D94,records!$A:$V,12,FALSE) -> 33 146 822 300 028 | R94: Email | S94: =VLOOKUP(D94,records!$A:$U,19,FALSE) -> compta@pdg-plastiques.com | T94: Transfer | U94: Renewal | V94: =VLOOKUP($D94,records!$A:$V,3,FALSE) -> PDG PLASTIQUES sas | W94: =IFERROR(VLOOKUP($D94,records!$A:$V,6,FALSE),) -> Baptiste VILLEVALOIS | X94: =VLOOKUP($D94,records!$A:$V,9,FALSE) -> 31 Route de Sermaises - ZI Secteur 2 | Y94: =VLOOKUP($D94,records!$A:$V,4,FALSE) -> MALESHERBES | Z94: =VLOOKUP($D94,records!$A:$V,7,FALSE) -> 45330 | AA94: Redevance 2026 | AB94: =VLOOKUP(O94,'records (2)'!$A:$Z,8,FALSE) -> 30 | AC94: FALSE | AF94: =VLOOKUP($D94,records!$A:$V,13,FALSE) -> PDG PLASTIQUES sas | AG94: Facture originale électronique à | AH94: =VLOOKUP($D94,records!$A:$V,19,FALSE) -> compta@pdg-plastiques.com | AI94: . | AJ94: =VLOOKUP($O94,'records (2)'!$A:$Z,14,FALSE) -> 003IV000010sxFhYAI | AK94: =VLOOKUP($O94,'records (2)'!$A:$Z,15,FALSE) -> Baptiste VILLEVALOIS | AL94: =VLOOKUP($O94,'records (2)'!$A:$Z,10,FALSE) -> 003IV000010t2BIYAY | AM94: =VLOOKUP($O94,'records (2)'!$A:$Z,11,FALSE) -> Corinne COULON (Compta) | AN94: 1 | AO94: 1000 | AP94: 1000 | AQ94: 0 | AR94: 0
A95: RMRE-01538 | B95: ROMAIRE | C95: ROMAIRE | D95: 001IV000015RewCYAS | E95: 01tIV00000GOfP1YAL | F95: Redevance d'utilisation - Tranche 25 ETP - Cas 1 | H95: Annual | I95: In advance | J95: 46023 | K95: 46387 | L95: Pixid France | M95: Pack C&S | N95: 46023 | O95: =VLOOKUP(D95,records!$A:$U,10,FALSE) -> 0012p00004ONxyqAAD | P95: =VLOOKUP(D95,records!$A:$V,20,FALSE) -> FR38300031226 | Q95: =VLOOKUP(D95,records!$A:$V,12,FALSE) -> 30 003 122 600 016 | R95: Email | S95: =VLOOKUP(D95,records!$A:$U,19,FALSE) -> compta@romaire-sa.fr | T95: Transfer | U95: Renewal | V95: =VLOOKUP($D95,records!$A:$V,3,FALSE) -> ETABLISSEMENTS ROMAIRE sasu | X95: =VLOOKUP($D95,records!$A:$V,9,FALSE) -> 1032 Avenue de Joux | Y95: =VLOOKUP($D95,records!$A:$V,4,FALSE) -> ARNAS | Z95: =VLOOKUP($D95,records!$A:$V,7,FALSE) -> 69400 | AA95: Redevance 2026 | AB95: =VLOOKUP(O95,'records (2)'!$A:$Z,8,FALSE) -> 30 | AC95: FALSE | AF95: =VLOOKUP($D95,records!$A:$V,13,FALSE) -> ETABLISSEMENTS ROMAIRE sasu | AG95: Facture originale électronique à | AH95: =VLOOKUP($D95,records!$A:$V,19,FALSE) -> compta@romaire-sa.fr | AI95: . | AJ95: =VLOOKUP($O95,'records (2)'!$A:$Z,14,FALSE) -> 003IV000010tWSNYA2 | AK95: =VLOOKUP($O95,'records (2)'!$A:$Z,15,FALSE) -> Clothilde ANDRE-CHARTIER (Compta) | AL95: =VLOOKUP($O95,'records (2)'!$A:$Z,10,FALSE) -> 003IV000010tWSNYA2 | AM95: =VLOOKUP($O95,'records (2)'!$A:$Z,11,FALSE) -> Clothilde ANDRE-CHARTIER (Compta) | AN95: 1 | AO95: 500 | AP95: 500 | AQ95: 0 | AR95: 0
A96: RVAL-01597 | B96: ROVAL | C96: ROVAL | D96: 001IV000015RhU7YAK | E96: 01tIV00000GyVCbYAN | F96: Redevance d'utilisation - Tranche 25 ETP - Cas 2 | H96: Annual | I96: In advance | J96: 46023 | K96: 46387 | L96: Pixid France | M96: Pack C&S | N96: 46023 | O96: =VLOOKUP(D96,records!$A:$U,10,FALSE) -> 0012p00004SN179AAD | P96: =VLOOKUP(D96,records!$A:$V,20,FALSE) -> FR68311866206 | Q96: =VLOOKUP(D96,records!$A:$V,12,FALSE) -> 31 186 620 600 064 | R96: Email | S96: =VLOOKUP(D96,records!$A:$U,19,FALSE) -> compta@roval.fr | T96: Transfer | U96: Renewal | V96: =VLOOKUP($D96,records!$A:$V,3,FALSE) -> ROVAL sas | X96: =VLOOKUP($D96,records!$A:$V,9,FALSE) -> Rue des Sports | Y96: =VLOOKUP($D96,records!$A:$V,4,FALSE) -> FLERS | Z96: =VLOOKUP($D96,records!$A:$V,7,FALSE) -> 61100 | AA96: Redevance 2026 | AB96: =VLOOKUP(O96,'records (2)'!$A:$Z,8,FALSE) -> 30 | AC96: FALSE | AF96: =VLOOKUP($D96,records!$A:$V,13,FALSE) -> ROVAL sas | AG96: Facture originale électronique à | AH96: =VLOOKUP($D96,records!$A:$V,19,FALSE) -> compta@roval.fr | AI96: . | AJ96: =VLOOKUP($O96,'records (2)'!$A:$Z,14,FALSE) -> 003IV000010tQICYA2 | AK96: =VLOOKUP($O96,'records (2)'!$A:$Z,15,FALSE) -> Corinne DUFRECHOU | AL96: =VLOOKUP($O96,'records (2)'!$A:$Z,10,FALSE) -> 003IV000010tWSzYAM | AM96: =VLOOKUP($O96,'records (2)'!$A:$Z,11,FALSE) -> Christophe DE LAVALETTE | AN96: 1 | AO96: 7000 | AP96: 7000 | AQ96: 0 | AR96: 0
A97: SMBS-01572 | B97: SAMIBOIS | C97: SAMIBOIS SAS | D97: 001IV000015SJKeYAO | E97: 01tIV00000GOfP1YAL | F97: Redevance d'utilisation - Tranche 25 ETP - Cas 1 | H97: Annual | I97: In advance | J97: 46023 | K97: 46387 | L97: Pixid France | M97: Pack C&S | N97: 46023 | O97: =VLOOKUP(D97,records!$A:$U,10,FALSE) -> 0012p00004Ng9V2AAJ | P97: =VLOOKUP(D97,records!$A:$V,20,FALSE) -> FR08921322715 | Q97: =VLOOKUP(D97,records!$A:$V,12,FALSE) -> 92 132 271 500 019 | R97: Email | S97: =VLOOKUP(D97,records!$A:$U,19,FALSE) -> compta@samibois.com | T97: Transfer | U97: Renewal | V97: =VLOOKUP($D97,records!$A:$V,3,FALSE) -> SAMIBOIS sasu | X97: =VLOOKUP($D97,records!$A:$V,9,FALSE) -> Pôle Technique Odyssée - 6 rue Denis Papin | Y97: =VLOOKUP($D97,records!$A:$V,4,FALSE) -> COËX | Z97: =VLOOKUP($D97,records!$A:$V,7,FALSE) -> 85220 | AA97: Redevance 2026 | AB97: =VLOOKUP(O97,'records (2)'!$A:$Z,8,FALSE) -> 30 | AC97: FALSE | AF97: =VLOOKUP($D97,records!$A:$V,13,FALSE) -> SAMIBOIS sasu | AG97: Facture originale électronique à | AH97: =VLOOKUP($D97,records!$A:$V,19,FALSE) -> compta@samibois.com | AI97: . | AJ97: =VLOOKUP($O97,'records (2)'!$A:$Z,14,FALSE) -> 003IV000010t2ZQYAY | AK97: =VLOOKUP($O97,'records (2)'!$A:$Z,15,FALSE) -> Valérie THIBAUDEAU (compta Samibois) | AL97: =VLOOKUP($O97,'records (2)'!$A:$Z,10,FALSE) -> 003IV000010t2ZQYAY | AM97: =VLOOKUP($O97,'records (2)'!$A:$Z,11,FALSE) -> Valérie THIBAUDEAU (compta Samibois) | AN97: 1 | AO97: 500 | AP97: 500 | AQ97: 0 | AR97: 0
A98: SMPL-01571 | B98: SAMIPLAST | C98: SAMIPLAST SAS | D98: 001IV000015S4lJYAS | E98: 01tIV00000GOfP1YAL | F98: Redevance d'utilisation - Tranche 25 ETP - Cas 1 | H98: Annual | I98: In advance | J98: 46023 | K98: 46387 | L98: Pixid France | M98: Pack C&S | N98: 46023 | O98: =VLOOKUP(D98,records!$A:$U,10,FALSE) -> 0012p00004Ng8goAAB | P98: =VLOOKUP(D98,records!$A:$V,20,FALSE) -> FR65834221681 | Q98: =VLOOKUP(D98,records!$A:$V,12,FALSE) -> 83 422 168 100 036 | R98: Email | S98: =VLOOKUP(D98,records!$A:$U,19,FALSE) -> compta@samiplast.fr | T98: Transfer | U98: Renewal | V98: =VLOOKUP($D98,records!$A:$V,3,FALSE) -> SAMIPLAST sasu | W98: =IFERROR(VLOOKUP($D98,records!$A:$V,6,FALSE),) -> Service Comptabilité | X98: =VLOOKUP($D98,records!$A:$V,9,FALSE) -> Route de Saint Julien des Landes | Y98: =VLOOKUP($D98,records!$A:$V,4,FALSE) -> LA CHAIZE GIRAUD | Z98: =VLOOKUP($D98,records!$A:$V,7,FALSE) -> 85220 | AA98: Redevance 2026 | AB98: =VLOOKUP(O98,'records (2)'!$A:$Z,8,FALSE) -> 30 | AC98: FALSE | AF98: =VLOOKUP($D98,records!$A:$V,13,FALSE) -> SAMIPLAST sasu | AG98: Facture originale électronique à | AH98: =VLOOKUP($D98,records!$A:$V,19,FALSE) -> compta@samiplast.fr | AI98: . | AJ98: =VLOOKUP($O98,'records (2)'!$A:$Z,14,FALSE) -> 003IV000010t2ZRYAY | AK98: =VLOOKUP($O98,'records (2)'!$A:$Z,15,FALSE) -> Valérie THIBAUDEAU (compta Samiplast) | AL98: =VLOOKUP($O98,'records (2)'!$A:$Z,10,FALSE) -> 003IV000010t2ZRYAY | AM98: =VLOOKUP($O98,'records (2)'!$A:$Z,11,FALSE) -> Valérie THIBAUDEAU (compta Samiplast) | AN98: 1 | AO98: 500 | AP98: 500 | AQ98: 0 | AR98: 0
A99: SECM-01683 | B99: SECMAIR | C99: SECMAIR | D99: 001IV000015RyDkYAK | E99: 01tIV00000GOfP1YAL | F99: Redevance d'utilisation - Tranche 25 ETP - Cas 1 | H99: Annual | I99: In advance | J99: 46023 | K99: 46387 | L99: Pixid France | M99: Pack C&S | N99: 46023 | O99: =VLOOKUP(D99,records!$A:$U,10,FALSE) -> 0012p00004UHSybAAH | P99: =VLOOKUP(D99,records!$A:$V,20,FALSE) -> FR16380972125 | Q99: =VLOOKUP(D99,records!$A:$V,12,FALSE) -> 38 097 212 500 013 | R99: Email | S99: =VLOOKUP(D99,records!$A:$U,19,FALSE) -> compta@secmair.fayat.com | T99: Transfer | U99: Renewal | V99: =VLOOKUP($D99,records!$A:$V,3,FALSE) -> SECMAIR sas | W99: =IFERROR(VLOOKUP($D99,records!$A:$V,6,FALSE),) -> Service Comptabilité | X99: =VLOOKUP($D99,records!$A:$V,9,FALSE) -> Rue des Frères Lumières | Y99: =VLOOKUP($D99,records!$A:$V,4,FALSE) -> COSSE LE VIVIEN | Z99: =VLOOKUP($D99,records!$A:$V,7,FALSE) -> 53203 | AA99: Redevance 2026 | AB99: =VLOOKUP(O99,'records (2)'!$A:$Z,8,FALSE) -> 30 | AC99: FALSE | AF99: =VLOOKUP($D99,records!$A:$V,13,FALSE) -> SECMAIR sas | AG99: Facture originale électronique à | AH99: =VLOOKUP($D99,records!$A:$V,19,FALSE) -> compta@secmair.fayat.com | AI99: . | AJ99: =VLOOKUP($O99,'records (2)'!$A:$Z,14,FALSE) -> 003IV000010tJXaYAM | AK99: =VLOOKUP($O99,'records (2)'!$A:$Z,15,FALSE) -> Andoline LAURENT | AL99: =VLOOKUP($O99,'records (2)'!$A:$Z,10,FALSE) -> 003IV000010tI5IYAU | AM99: =VLOOKUP($O99,'records (2)'!$A:$Z,11,FALSE) -> Anne GUILLOTIN | AN99: 1 | AO99: 500 | AP99: 500 | AQ99: 0 | AR99: 0
A100: SDLL-01546 | B100: SODEL LISIEUX | C100: SODEL LISIEUX | D100: 001IV000015SAFgYAO | E100: 01tIV00000GyVCbYAN | F100: Redevance d'utilisation - Tranche 25 ETP - Cas 2 | H100: Annual | I100: In advance | J100: 46023 | K100: 46387 | L100: Pixid France | M100: Pack C&S | N100: 46023 | O100: =VLOOKUP(D100,records!$A:$U,10,FALSE) -> 0012p00004Ns98wAAB | P100: =VLOOKUP(D100,records!$A:$V,20,FALSE) -> FR12627150105 | Q100: =VLOOKUP(D100,records!$A:$V,12,FALSE) -> 62 715 010 500 070 | R100: Email | S100: =VLOOKUP(D100,records!$A:$U,19,FALSE) -> compta@sodel-sa.eu | T100: Transfer | U100: Renewal | V100: =VLOOKUP($D100,records!$A:$V,3,FALSE) -> SODEL sas | X100: =VLOOKUP($D100,records!$A:$V,9,FALSE) -> 190 rue René Barthelemy | Y100: =VLOOKUP($D100,records!$A:$V,4,FALSE) -> LISIEUX | Z100: =VLOOKUP($D100,records!$A:$V,7,FALSE) -> 14100 | AA100: Redevance 2026 | AB100: =VLOOKUP(O100,'records (2)'!$A:$Z,8,FALSE) -> 30 | AC100: FALSE | AF100: =VLOOKUP($D100,records!$A:$V,13,FALSE) -> SODEL sas | AG100: Facture originale électronique à | AH100: =VLOOKUP($D100,records!$A:$V,19,FALSE) -> compta@sodel-sa.eu | AI100: . | AJ100: =VLOOKUP($O100,'records (2)'!$A:$Z,14,FALSE) -> 003IV000010rvHLYAY | AK100: =VLOOKUP($O100,'records (2)'!$A:$Z,15,FALSE) -> Marie-Christine KEROUANTON | AL100: =VLOOKUP($O100,'records (2)'!$A:$Z,10,FALSE) -> 003IV000010rvHLYAY | AM100: =VLOOKUP($O100,'records (2)'!$A:$Z,11,FALSE) -> Marie-Christine KEROUANTON | AN100: 1 | AO100: 1000 | AP100: 1000 | AQ100: 0 | AR100: 0
A101: SPRN-01762 | B101: SOPRONEM | C101: SOPRONEM | D101: 001IV000015S2eHYAS | E101: 01tIV00000GOfP1YAL | F101: Redevance d'utilisation - Tranche 25 ETP - Cas 1 | H101: Annual | I101: In advance | J101: 46023 | K101: 46387 | L101: Pixid France | M101: Pack C&S | N101: 46023 | O101: =VLOOKUP(D101,records!$A:$U,10,FALSE) -> 0012p00004RgyEoAAJ | P101: =VLOOKUP(D101,records!$A:$V,20,FALSE) -> FR79814762548 | Q101: =VLOOKUP(D101,records!$A:$V,12,FALSE) -> 81 476 254 800 026 | R101: Email | S101: =VLOOKUP(D101,records!$A:$U,19,FALSE) -> compta@sopronem.com | T101: Transfer | U101: Renewal | V101: =VLOOKUP($D101,records!$A:$V,3,FALSE) -> SOCIETE DE PRODUCTION DE NEMOURS "SOPRONEM" sasu | X101: =VLOOKUP($D101,records!$A:$V,9,FALSE) -> 2 Rue des Etangs | Y101: =VLOOKUP($D101,records!$A:$V,4,FALSE) -> SAINT-PIERRE-LES-NEMOURS | Z101: =VLOOKUP($D101,records!$A:$V,7,FALSE) -> 77140 | AA101: Redevance 2026 | AB101: =VLOOKUP(O101,'records (2)'!$A:$Z,8,FALSE) -> 30 | AC101: FALSE | AF101: =VLOOKUP($D101,records!$A:$V,13,FALSE) -> SOCIETE DE PRODUCTION DE NEMOURS "SOPRONEM" sasu | AG101: Facture originale électronique à | AH101: =VLOOKUP($D101,records!$A:$V,19,FALSE) -> compta@sopronem.com | AI101: . | AJ101: =VLOOKUP($O101,'records (2)'!$A:$Z,14,FALSE) -> 003IV000010tRW7YAM | AK101: =VLOOKUP($O101,'records (2)'!$A:$Z,15,FALSE) -> Isabelle VEKEMAN | AL101: =VLOOKUP($O101,'records (2)'!$A:$Z,10,FALSE) -> 003IV000010tRW7YAM | AM101: =VLOOKUP($O101,'records (2)'!$A:$Z,11,FALSE) -> Isabelle VEKEMAN | AN101: 1 | AO101: 500 | AP101: 500
A102: MSSA-01622 | B102: MSSA SAS | C102: MSSA SAS | D102: 001IV000015S85tYAC | E102: 01tIV00000GOfP1YAL | F102: Redevance d'utilisation - Tranche 25 ETP - Cas 1 | H102: Annual | I102: In advance | J102: 46023 | K102: 46387 | L102: Pixid France | M102: Pack C&S | N102: 46023 | O102: =VLOOKUP(D102,records!$A:$U,10,FALSE) -> 0012p00004Sz9g9AAB | P102: =VLOOKUP(D102,records!$A:$V,20,FALSE) -> FR96410219042 | Q102: =VLOOKUP(D102,records!$A:$V,12,FALSE) -> 41 021 904 200 026 | R102: Email | S102: =VLOOKUP(D102,records!$A:$U,19,FALSE) -> compta_fournisseur@metauxspeciaux.fr | T102: Transfer | U102: Renewal | V102: =VLOOKUP($D102,records!$A:$V,3,FALSE) -> MSSA sasu | X102: =VLOOKUP($D102,records!$A:$V,9,FALSE) -> 111 rue de la Volta Pomblière | Y102: =VLOOKUP($D102,records!$A:$V,4,FALSE) -> SAINT MARCEL | Z102: =VLOOKUP($D102,records!$A:$V,7,FALSE) -> 73600 | AA102: Redevance 2026 | AB102: =VLOOKUP(O102,'records (2)'!$A:$Z,8,FALSE) -> 30 | AC102: FALSE | AF102: =VLOOKUP($D102,records!$A:$V,13,FALSE) -> MSSA sasu | AG102: Facture originale électronique à | AH102: =VLOOKUP($D102,records!$A:$V,19,FALSE) -> compta_fournisseur@metauxspeciaux.fr | AI102: . | AJ102: =VLOOKUP($O102,'records (2)'!$A:$Z,14,FALSE) -> 003IV000010tIeLYAU | AK102: =VLOOKUP($O102,'records (2)'!$A:$Z,15,FALSE) -> Comptabilité FOURNISSEURS - MSSA | AL102: =VLOOKUP($O102,'records (2)'!$A:$Z,10,FALSE) -> 003IV000010tIeLYAU | AM102: =VLOOKUP($O102,'records (2)'!$A:$Z,11,FALSE) -> Comptabilité FOURNISSEURS - MSSA | AN102: 1 | AO102: 1000 | AP102: 1000 | AQ102: 0 | AR102: 0
A103: GCPS-01511 | B103: COFIDIS GROUP | C103: GROUPE COFIDIS PARTICIPATIONS (SYNERGIE GEIE) | D103: 001IV000015SAHRYA4 | E103: 01tIV00000GyVCbYAN | F103: Redevance d'utilisation - Tranche 25 ETP - Cas 2 | H103: Annual | I103: In advance | J103: 46023 | K103: 46387 | L103: Pixid France | M103: Pack C&S | N103: 46023 | O103: =VLOOKUP(D103,records!$A:$U,10,FALSE) -> 0012p00004NeCR0AAN | P103: =VLOOKUP(D103,records!$A:$V,20,FALSE) -> FR19751108994 | Q103: =VLOOKUP(D103,records!$A:$V,12,FALSE) -> 75 110 899 400 011 | R103: Email | S103: =VLOOKUP(D103,records!$A:$U,19,FALSE) -> compta_fraisgeneraux@cofidis-group.com | T103: Transfer | U103: Renewal | V103: =VLOOKUP($D103,records!$A:$V,3,FALSE) -> SYNERGIE Geie | W103: =IFERROR(VLOOKUP($D103,records!$A:$V,6,FALSE),) -> Service comptabilité fournisseurs | X103: =VLOOKUP($D103,records!$A:$V,9,FALSE) -> Parc de la Haute Borne 61 avenue Halley | Y103: =VLOOKUP($D103,records!$A:$V,4,FALSE) -> VILLENEUVE D'ASCQ | Z103: =VLOOKUP($D103,records!$A:$V,7,FALSE) -> 59650 | AA103: Redevance 2026 | AB103: =VLOOKUP(O103,'records (2)'!$A:$Z,8,FALSE) -> 30 | AC103: FALSE | AF103: =VLOOKUP($D103,records!$A:$V,13,FALSE) -> SYNERGIE Geie | AG103: Facture originale électronique à | AH103: =VLOOKUP($D103,records!$A:$V,19,FALSE) -> compta_fraisgeneraux@cofidis-group.com | AI103: . | AJ103: =VLOOKUP($O103,'records (2)'!$A:$Z,14,FALSE) -> 003IV000010rvHBYAY | AK103: =VLOOKUP($O103,'records (2)'!$A:$Z,15,FALSE) -> Sandrine ZABATTA | AL103: =VLOOKUP($O103,'records (2)'!$A:$Z,10,FALSE) -> 003IV000010rvHBYAY | AM103: =VLOOKUP($O103,'records (2)'!$A:$Z,11,FALSE) -> Sandrine ZABATTA | AN103: 1 | AO103: 1000 | AP103: 1000 | AQ103: 0 | AR103: 0
A104: PAPM-01628 | B104: GROUPE PAPIN | C104: PAPIN GROUPE | D104: 001IV000015S85iYAC | E104: 01tIV00000GyVCbYAN | F104: Redevance d'utilisation - Tranche 25 ETP - Cas 2 | H104: Annual | I104: In advance | J104: 46023 | K104: 46387 | L104: Pixid France | M104: Pack C&S | N104: 46023 | O104: =VLOOKUP(D104,records!$A:$U,10,FALSE) -> 0012p00004RmkIaAAJ | P104: =VLOOKUP(D104,records!$A:$V,20,FALSE) -> FR40799363106 | Q104: =VLOOKUP(D104,records!$A:$V,12,FALSE) -> 79 936 310 600 011 | R104: Email | S104: =VLOOKUP(D104,records!$A:$U,19,FALSE) -> compta-achats@groupe-papin.fr | T104: Transfer | U104: Renewal | V104: =VLOOKUP($D104,records!$A:$V,3,FALSE) -> PAPIN MANAGEMENT sas | X104: =VLOOKUP($D104,records!$A:$V,9,FALSE) -> ZI rue du Stade | Y104: =VLOOKUP($D104,records!$A:$V,4,FALSE) -> SAINT-FULGENT | Z104: =VLOOKUP($D104,records!$A:$V,7,FALSE) -> 85250 | AA104: Redevance 2026 | AB104: =VLOOKUP(O104,'records (2)'!$A:$Z,8,FALSE) -> 30 | AC104: FALSE | AF104: =VLOOKUP($D104,records!$A:$V,13,FALSE) -> PAPIN MANAGEMENT sas | AG104: Facture originale électronique à | AH104: =VLOOKUP($D104,records!$A:$V,19,FALSE) -> compta-achats@groupe-papin.fr | AI104: . | AJ104: =VLOOKUP($O104,'records (2)'!$A:$Z,14,FALSE) -> 003IV000010tRWmYAM | AK104: =VLOOKUP($O104,'records (2)'!$A:$Z,15,FALSE) -> Vincent PORTRAIT | AL104: =VLOOKUP($O104,'records (2)'!$A:$Z,10,FALSE) -> 003IV000010tRWmYAM | AM104: =VLOOKUP($O104,'records (2)'!$A:$Z,11,FALSE) -> Vincent PORTRAIT | AN104: 1 | AO104: 4000 | AP104: 4000 | AQ104: 0 | AR104: 0
A105: VRLF-01972 | B105: VERALLIA France | C105: VERALLIA France | D105: 001IV000015S9GIYA0 | E105: 01tIV00000GOfP6YAL | F105: Redevance d'utilisation - ETP EU | H105: Annual | I105: In advance | J105: 46023 | K105: 46387 | L105: Pixid France | M105: Pack C&S | N105: 46023 | O105: =VLOOKUP(D105,records!$A:$U,10,FALSE) -> 001SZ00000VsYE9YAN | P105: =VLOOKUP(D105,records!$A:$V,20,FALSE) -> FR86722034592 | Q105: =VLOOKUP(D105,records!$A:$V,12,FALSE) -> 72 203 459 200 278 | R105: Email | S105: =VLOOKUP(D105,records!$A:$U,19,FALSE) -> comptabilite.fournisseurs.vf@verallia.com | T105: Transfer | U105: Renewal | V105: =VLOOKUP($D105,records!$A:$V,3,FALSE) -> VERALLIA FRANCE sas | X105: =VLOOKUP($D105,records!$A:$V,9,FALSE) -> 31 Place des Corolles | Y105: =VLOOKUP($D105,records!$A:$V,4,FALSE) -> COURBEVOIE | Z105: =VLOOKUP($D105,records!$A:$V,7,FALSE) -> 92400 | AA105: Redevance 2026 | AB105: =VLOOKUP(O105,'records (2)'!$A:$Z,8,FALSE) -> 30 | AC105: FALSE | AF105: =VLOOKUP($D105,records!$A:$V,13,FALSE) -> VERALLIA FRANCE sas | AG105: Facture originale électronique à | AH105: =VLOOKUP($D105,records!$A:$V,19,FALSE) -> comptabilite.fournisseurs.vf@verallia.com | AI105: . | AJ105: =VLOOKUP($O105,'records (2)'!$A:$Z,14,FALSE) -> 003IV000010t9wmYAA | AK105: =VLOOKUP($O105,'records (2)'!$A:$Z,15,FALSE) -> Christophe DUCHESNE | AL105: =VLOOKUP($O105,'records (2)'!$A:$Z,10,FALSE) -> 003IV000010t9wmYAA | AM105: =VLOOKUP($O105,'records (2)'!$A:$Z,11,FALSE) -> Christophe DUCHESNE | AN105: 1 | AO105: 3440 | AP105: 3440 | AQ105: 0 | AR105: 0
A106: ESNK-01707 | B106: EUROPE SNACKS | C106: EUROPE SNACKS - (FRANDEX) | D106: 001IV000015S4lDYAS | E106: 01tIV00000GOfP1YAL | F106: Redevance d'utilisation - Tranche 25 ETP - Cas 1 | H106: Annual | I106: In advance | J106: 46023 | K106: 46387 | L106: Pixid France | M106: Pack C&S | N106: 46023 | O106: =VLOOKUP(D106,records!$A:$U,10,FALSE) -> 001SZ000001KulTYAS | P106: =VLOOKUP(D106,records!$A:$V,20,FALSE) -> FR58411683600 | Q106: =VLOOKUP(D106,records!$A:$V,12,FALSE) -> 41 168 360 000 018 | R106: Email | S106: =VLOOKUP(D106,records!$A:$U,19,FALSE) -> comptabilite.fournisseurs@europesnacks.com | T106: Transfer | U106: Renewal | V106: =VLOOKUP($D106,records!$A:$V,3,FALSE) -> FRANDEX sas | X106: =VLOOKUP($D106,records!$A:$V,9,FALSE) -> ZI Saint Denis les Lucs | Y106: =VLOOKUP($D106,records!$A:$V,4,FALSE) -> SAINT DENIS LA CHEVASSE | Z106: =VLOOKUP($D106,records!$A:$V,7,FALSE) -> 85170 | AA106: Redevance 2026 | AB106: =VLOOKUP(O106,'records (2)'!$A:$Z,8,FALSE) -> 30 | AC106: FALSE | AF106: =VLOOKUP($D106,records!$A:$V,13,FALSE) -> FRANDEX sas | AG106: Facture originale électronique à | AH106: =VLOOKUP($D106,records!$A:$V,19,FALSE) -> comptabilite.fournisseurs@europesnacks.com | AI106: . | AJ106: =VLOOKUP($O106,'records (2)'!$A:$Z,14,FALSE) -> 003IV000010tRzGYAU | AK106: =VLOOKUP($O106,'records (2)'!$A:$Z,15,FALSE) -> Audrey GUESDON (E.Snacks) | AL106: =VLOOKUP($O106,'records (2)'!$A:$Z,10,FALSE) -> 003IV000010su87YAA | AM106: =VLOOKUP($O106,'records (2)'!$A:$Z,11,FALSE) -> Comptabilité EUROPE SNACKS - (FRANDEX) | AN106: 1 | AO106: 2000 | AP106: 2000 | AQ106: 0 | AR106: 0
A107: SGVR-01822 | B107: SIGVARIS | C107: SIGVARIS | D107: 001IV000015S865YAC | E107: 01tIV00000GOfP1YAL | F107: Redevance d'utilisation - Tranche 25 ETP - Cas 1 | H107: Annual | I107: In advance | J107: 46023 | K107: 46387 | L107: Pixid France | M107: Pack C&S | N107: 46023 | O107: =VLOOKUP(D107,records!$A:$U,10,FALSE) -> 001SZ000001A8i6YAC | P107: =VLOOKUP(D107,records!$A:$V,20,FALSE) -> FR39384137857 | Q107: =VLOOKUP(D107,records!$A:$V,12,FALSE) -> 38 413 785 700 031 | R107: Email | S107: =VLOOKUP(D107,records!$A:$U,19,FALSE) -> comptabilite.fournisseurs@sigvaris.com | T107: Transfer | U107: Renewal | V107: =VLOOKUP($D107,records!$A:$V,3,FALSE) -> SIGVARIS sasu | X107: =VLOOKUP($D107,records!$A:$V,9,FALSE) -> ZI Sud d'Andrézieux - Rue Barthélémy Thimonnier | Y107: =VLOOKUP($D107,records!$A:$V,4,FALSE) -> SAINT-JUST-SAINT-RAMBERT | Z107: =VLOOKUP($D107,records!$A:$V,7,FALSE) -> 42170 | AA107: Redevance 2026 | AB107: =VLOOKUP(O107,'records (2)'!$A:$Z,8,FALSE) -> 30 | AC107: =VLOOKUP(O107,'records (4)'!$A:$C,3,FALSE) -> TRUE | AD107: YES | AE107: 46023 | AF107: =VLOOKUP($D107,records!$A:$V,13,FALSE) -> SIGVARIS sasu | AG107: Facture originale électronique à | AH107: =VLOOKUP($D107,records!$A:$V,19,FALSE) -> comptabilite.fournisseurs@sigvaris.com | AI107: . | AJ107: =VLOOKUP($O107,'records (2)'!$A:$Z,14,FALSE) -> 003IV000010su9BYAQ | AK107: =VLOOKUP($O107,'records (2)'!$A:$Z,15,FALSE) -> Service Comptabilité | AL107: =VLOOKUP($O107,'records (2)'!$A:$Z,10,FALSE) -> 003IV000010su9BYAQ | AM107: =VLOOKUP($O107,'records (2)'!$A:$Z,11,FALSE) -> Service Comptabilité | AN107: 1 | AO107: 500 | AP107: 500 | AQ107: 0 | AR107: 0
A108: SMFG-01882 | B108: SOMFY | C108: SOMFY GROUPE | D108: 001IV000015S8jHYAS | E108: 01tIV00000GOfP1YAL | F108: Redevance d'utilisation - Tranche 25 ETP - Cas 1 | H108: Annual | I108: In advance | J108: 46023 | K108: 46387 | L108: Pixid France | M108: Pack C&S | N108: 46023 | O108: =VLOOKUP(D108,records!$A:$U,10,FALSE) -> 001SZ00000EaK55YAF | P108: =VLOOKUP(D108,records!$A:$V,20,FALSE) -> FR25303970230 | Q108: =VLOOKUP(D108,records!$A:$V,12,FALSE) -> 30 397 023 000 122 | R108: Email | S108: =VLOOKUP(D108,records!$A:$U,19,FALSE) -> comptabilite.fournisseurs@somfy.com | T108: Transfer | U108: Renewal | V108: =VLOOKUP($D108,records!$A:$V,3,FALSE) -> SOMFY ACTIVITES SA | X108: =VLOOKUP($D108,records!$A:$V,9,FALSE) -> 50 Avenue du Nouveau Monde | Y108: =VLOOKUP($D108,records!$A:$V,4,FALSE) -> CLUSES | Z108: =VLOOKUP($D108,records!$A:$V,7,FALSE) -> 74300 | AA108: Redevance 2026 | AB108: =VLOOKUP(O108,'records (2)'!$A:$Z,8,FALSE) -> 60 | AC108: =VLOOKUP(O108,'records (4)'!$A:$C,3,FALSE) -> TRUE | AD108: YES | AE108: 46023 | AF108: =VLOOKUP($D108,records!$A:$V,13,FALSE) -> SOMFY ACTIVITES SA | AG108: Facture originale électronique à | AH108: =VLOOKUP($D108,records!$A:$V,19,FALSE) -> comptabilite.fournisseurs@somfy.com | AI108: . | AJ108: =VLOOKUP($O108,'records (2)'!$A:$Z,14,FALSE) -> 003IV000010tJZYYA2 | AK108: =VLOOKUP($O108,'records (2)'!$A:$Z,15,FALSE) -> Comptabilité Fournisseurs SOMFY | AL108: =VLOOKUP($O108,'records (2)'!$A:$Z,10,FALSE) -> 003IV000010tJZYYA2 | AM108: =VLOOKUP($O108,'records (2)'!$A:$Z,11,FALSE) -> Comptabilité Fournisseurs SOMFY | AN108: 1 | AO108: 3500 | AP108: 3500 | AQ108: 0 | AR108: 0
A109: LGLF-01857 | B109: LFB FRANCE | C109: LFB FRANCE (ex LENNOX ex LGL) | D109: 001IV000015S869YAC | E109: 01tIV00000GyVCbYAN | F109: Redevance d'utilisation - Tranche 25 ETP - Cas 2 | H109: Annual | I109: In advance | J109: 46023 | K109: 46387 | L109: Pixid France | M109: Pack C&S | N109: 46023 | O109: =VLOOKUP(D109,records!$A:$U,10,FALSE) -> 001SZ000003vEuKYAU | P109: =VLOOKUP(D109,records!$A:$V,20,FALSE) -> FR59309528115 | Q109: =VLOOKUP(D109,records!$A:$V,12,FALSE) -> 30 952 811 500 061 | R109: Email | S109: =VLOOKUP(D109,records!$A:$U,19,FALSE) -> comptabilite.fr@lennoxemea.com | T109: Transfer | U109: Renewal | V109: =VLOOKUP($D109,records!$A:$V,3,FALSE) -> LFB FRANCE sas | X109: =VLOOKUP($D109,records!$A:$V,9,FALSE) -> Rue des Albatros - ZI Les Meurières | Y109: =VLOOKUP($D109,records!$A:$V,4,FALSE) -> MIONS | Z109: =VLOOKUP($D109,records!$A:$V,7,FALSE) -> 69780 | AA109: Redevance 2026 | AB109: =VLOOKUP(O109,'records (2)'!$A:$Z,8,FALSE) -> 45 | AC109: =VLOOKUP(O109,'records (4)'!$A:$C,3,FALSE) -> TRUE | AD109: YES | AE109: 46023 | AF109: =VLOOKUP($D109,records!$A:$V,13,FALSE) -> LFB FRANCE sas | AG109: Facture originale électronique à | AH109: =VLOOKUP($D109,records!$A:$V,19,FALSE) -> comptabilite.fr@lennoxemea.com | AI109: . | AJ109: =VLOOKUP($O109,'records (2)'!$A:$Z,14,FALSE) -> 003IV000010su8XYAQ | AK109: =VLOOKUP($O109,'records (2)'!$A:$Z,15,FALSE) -> Floriane BONNEL (comptabilite) | AL109: =VLOOKUP($O109,'records (2)'!$A:$Z,10,FALSE) -> 003IV000010su8XYAQ | AM109: =VLOOKUP($O109,'records (2)'!$A:$Z,11,FALSE) -> Floriane BONNEL (comptabilite) | AN109: 1 | AO109: 4000 | AP109: 4000 | AQ109: 0 | AR109: 0
A110: LGLF-01857 | B110: LFB FRANCE (ex LENNOX ex LGL) | C110: LFB FRANCE (ex LENNOX ex LGL) | D110: 001IV000015S869YAC | E110: 01tIV00000GOfPAYA1 | F110: Licence BI - Consultation | H110: Annual | I110: In advance | J110: 46023 | K110: 46387 | L110: Pixid France | M110: Pack C&S | N110: 46023 | O110: =VLOOKUP(D110,records!$A:$U,10,FALSE) -> 001SZ000003vEuKYAU | P110: =VLOOKUP(D110,records!$A:$V,20,FALSE) -> FR59309528115 | Q110: =VLOOKUP(D110,records!$A:$V,12,FALSE) -> 30 952 811 500 061 | R110: Email | S110: =VLOOKUP(D110,records!$A:$U,19,FALSE) -> comptabilite.fr@lennoxemea.com | T110: Transfer | U110: Renewal | V110: =VLOOKUP($D110,records!$A:$V,3,FALSE) -> LFB FRANCE sas | X110: =VLOOKUP($D110,records!$A:$V,9,FALSE) -> Rue des Albatros - ZI Les Meurières | Y110: =VLOOKUP($D110,records!$A:$V,4,FALSE) -> MIONS | Z110: =VLOOKUP($D110,records!$A:$V,7,FALSE) -> 69780 | AA110: Redevance 2026 | AB110: =VLOOKUP(O110,'records (2)'!$A:$Z,8,FALSE) -> 45 | AC110: =VLOOKUP(O110,'records (4)'!$A:$C,3,FALSE) -> TRUE | AD110: YES | AE110: 46023 | AF110: =VLOOKUP($D110,records!$A:$V,13,FALSE) -> LFB FRANCE sas | AG110: Facture originale électronique à | AH110: =VLOOKUP($D110,records!$A:$V,19,FALSE) -> comptabilite.fr@lennoxemea.com | AI110: . | AJ110: =VLOOKUP($O110,'records (2)'!$A:$Z,14,FALSE) -> 003IV000010su8XYAQ | AK110: =VLOOKUP($O110,'records (2)'!$A:$Z,15,FALSE) -> Floriane BONNEL (comptabilite) | AL110: =VLOOKUP($O110,'records (2)'!$A:$Z,10,FALSE) -> 003IV000010su8XYAQ | AM110: =VLOOKUP($O110,'records (2)'!$A:$Z,11,FALSE) -> Floriane BONNEL (comptabilite) | AN110: 1 | AO110: 1200 | AP110: 1200 | AQ110: 0 | AR110: Produit annexe
A111: MWFR-01677 | B111: MAGNETTO WHEELS FRANCE | C111: MW FRANCE | D111: 001IV000015RyDoYAK | E111: 01tIV00000GOfP1YAL | F111: Redevance d'utilisation - Tranche 25 ETP - Cas 1 | H111: Annual | I111: In advance | J111: 46023 | K111: 46387 | L111: Pixid France | M111: Pack C&S | N111: 46023 | O111: =VLOOKUP(D111,records!$A:$U,10,FALSE) -> 001SZ0000015EBSYA2 | P111: =VLOOKUP(D111,records!$A:$V,20,FALSE) -> FR03330263948 | Q111: =VLOOKUP(D111,records!$A:$V,12,FALSE) -> 33 026 394 800 011 | R111: Email | S111: =VLOOKUP(D111,records!$A:$U,19,FALSE) -> comptabilite@fr.mw.gruppocln.com | T111: Transfer | U111: Renewal | V111: =VLOOKUP($D111,records!$A:$V,3,FALSE) -> MW FRANCE sas | W111: =IFERROR(VLOOKUP($D111,records!$A:$V,6,FALSE),) -> Comptabilité | X111: =VLOOKUP($D111,records!$A:$V,9,FALSE) -> 33 Boulevard du 32ème R.I. - ZI les Certels | Y111: =VLOOKUP($D111,records!$A:$V,4,FALSE) -> TERGNIER | Z111: =VLOOKUP($D111,records!$A:$V,7,FALSE) -> 2700 | AA111: Redevance 2026 | AB111: =VLOOKUP(O111,'records (2)'!$A:$Z,8,FALSE) -> 30 | AC111: FALSE | AF111: =VLOOKUP($D111,records!$A:$V,13,FALSE) -> MW FRANCE sas | AG111: Facture originale électronique à | AH111: =VLOOKUP($D111,records!$A:$V,19,FALSE) -> comptabilite@fr.mw.gruppocln.com | AI111: . | AJ111: =VLOOKUP($O111,'records (2)'!$A:$Z,14,FALSE) -> 003IV000010tJXZYA2 | AK111: =VLOOKUP($O111,'records (2)'!$A:$Z,15,FALSE) -> William BRUN | AL111: =VLOOKUP($O111,'records (2)'!$A:$Z,10,FALSE) -> 003IV000010tJXZYA2 | AM111: =VLOOKUP($O111,'records (2)'!$A:$Z,11,FALSE) -> William BRUN | AN111: 1 | AO111: 500 | AP111: 500 | AQ111: 0 | AR111: 0
A112: STJN-01743 | B112: SAINT JEAN SAS | C112: SAINT JEAN SAS | D112: 001IV000015RyDrYAK | E112: 01tIV00000GOfP1YAL | F112: Redevance d'utilisation - Tranche 25 ETP - Cas 1 | H112: Annual | I112: In advance | J112: 46023 | K112: 46387 | L112: Pixid France | M112: Pack C&S | N112: 46023 | O112: =VLOOKUP(D112,records!$A:$U,10,FALSE) -> 001SZ000001rZISYA2 | P112: =VLOOKUP(D112,records!$A:$V,20,FALSE) -> FR84311821268 | Q112: =VLOOKUP(D112,records!$A:$V,12,FALSE) -> 31 182 126 800 027 | R112: Email | S112: =VLOOKUP(D112,records!$A:$U,19,FALSE) -> comptabilite@saint-jean.fr | T112: Transfer | U112: Renewal | V112: =VLOOKUP($D112,records!$A:$V,3,FALSE) -> SAINT JEAN sas | X112: =VLOOKUP($D112,records!$A:$V,9,FALSE) -> 44 Avenue des Allobroges | Y112: =VLOOKUP($D112,records!$A:$V,4,FALSE) -> ROMANS-SUR-ISERE | Z112: =VLOOKUP($D112,records!$A:$V,7,FALSE) -> 26100 | AA112: Redevance 2026 | AB112: =VLOOKUP(O112,'records (2)'!$A:$Z,8,FALSE) -> 30 | AC112: FALSE | AF112: =VLOOKUP($D112,records!$A:$V,13,FALSE) -> SAINT JEAN sas | AG112: Facture originale électronique à | AH112: =VLOOKUP($D112,records!$A:$V,19,FALSE) -> comptabilite@saint-jean.fr | AI112: . | AJ112: =VLOOKUP($O112,'records (2)'!$A:$Z,14,FALSE) -> 003IV000010su8PYAQ | AK112: =VLOOKUP($O112,'records (2)'!$A:$Z,15,FALSE) -> Florence VALLET | AL112: =VLOOKUP($O112,'records (2)'!$A:$Z,10,FALSE) -> 003IV000010su8PYAQ | AM112: =VLOOKUP($O112,'records (2)'!$A:$Z,11,FALSE) -> Florence VALLET | AN112: 1 | AO112: 1000 | AP112: 1000 | AQ112: 0 | AR112: 0
...

Sheet records (4)
A1: Id | B1: Name | C1: Commande_obligatoire__c
A2: 0012p00004NeCnVAAV | B2: NESTLE PURINA CENTRE R&D | C2: TRUE
A3: 0012p00004OLnMyAAL | B3: BASF AGRIPRODUCTION | C3: TRUE
A4: 0012p00004PIzW3AAL | B4: EMG-EARLY MAKERS GROUP | C4: TRUE
A5: 0012p00004RDXHiAAP | B5: C&K COMPONENTS SAS | C5: TRUE
A6: 0012p00004RfoNdAAJ | B6: ARMOR PROTEINES | C6: TRUE
A7: 0012p00004Rfp1kAAB | B7: URGO | C7: TRUE
A8: 0012p00004RmilzAAB | B8: EUROLYSINE (ex METEX NOOVISTAGO) | C8: TRUE
A9: 0012p00004SxGjuAAF | B9: DANFOSS | C9: TRUE
A10: 0012p00004SxcYeAAJ | B10: BOEHRINGER INGELHEIM | C10: TRUE
A11: 0012p00004U0MCtAAN | B11: METSO FRANCE SAS | C11: TRUE
A12: 0012p00004UpS9pAAF | B12: UPSA | C12: TRUE
A13: 001SZ000000lJNPYA2 | B13: KUHN | C13: TRUE
... A51: 001SZ00000YI0h9YAD | B51: CHEMVIRON PARENTIS SAS | C51: TRUE

Sheet records
A1: Id | B1: Name | C1: BillingBusinessName__c | D1: BillingCity | E1: BillingCountry | F1: BillingDepartment__c | G1: BillingPostalCode | H1: BillingState | I1: BillingStreet | J1: LegacyId__c | K1: Num_Compte__c | L1: RegistrationNumber__c | M1: ShippingBusinessName__c | N1: ShippingCity | O1: ShippingCountry | P1: ShippingDepartment__c | Q1: ShippingPostalCode | R1: ShippingState | S1: ShippingStreet | T1: VATNumber__c | U1: X | V1: Send invoice to
A2: 001IV000015S2eCYAS | B2: TETRAPAK | C2: PAPETERIES DE DIJON snc | D2: LONGVIC | E2: France | G2: 21600 | I2: 3 rue Romelet | J2: 0012p00004OKNMCAA5 | K2: TTPK-01534 | L2: 1 715 028 500 066 | M2: PAPETERIES DE DIJON snc | N2: . | P2: Facture originale électronique à | Q2: . | S2: 144.accountspayable@ap.tetrapak.com | T2: FR30017150285 | V2: =VLOOKUP(J2,'records (2)'!$A:$Z,16,FALSE) -> accountinghub.budaors@tetrapak.com
A3: 001IV000015RyL0YAK | B3: REVIMA | C3: REVIMA sasu | D3: RIVES-EN-SEINE | E3: France | G3: 76490 | I3: 1 Avenue du Latham 47 | J3: 0012p00004THFNVAA5 | K3: RVMA-01671 | L3: 54 207 132 900 024 | M3: REVIMA sasu | N3: . | P3: Facture originale électronique à | Q3: . | S3: account.payable@revima.fr | T3: FR75542071329 | V3: =VLOOKUP(J3,'records (2)'!$A:$Z,16,FALSE) -> account.payable@revima.fr
A4: 001IV000015S50KYAS | B4: MILLET MOUNTAIN GROUP SAS | C4: MILLET MOUNTAIN GROUP SAS | D4: ANNECY LE VIEUX CEDEX | E4: France | G4: 74943 | I4: 21 rue du Pré Faucon | J4: 0012p00004RDYqlAAH | K4: MMGS-01617 | L4: 40 031 331 800 026 | M4: MILLET MOUNTAIN GROUP SAS | N4: . | P4: Facture original électronique à | Q4: . | S4: accounting.millet@milletmountaingroup.com | T4: FR38400313318 | V4: =VLOOKUP(J4,'records (2)'!$A:$Z,16,FALSE) -> accounting.millet@milletmoutaingroup.com
A5: 001IV000015SAHqYAO | B5: AMPHENOL FCI | C5: AMPHENOL FCI BESANCON sas | D5: BESANCON | E5: France | G5: 25000 | I5: 2 Rue Lafayette | J5: 0012p00004ReLR9AAN | K5: AFCB-01660 | L5: 38 863 689 600 010 | M5: AMPHENOL FCI BESANCON sas | N5: . | P5: Facture originale électronique à | Q5: . | S5: accounts-payable.besancon@fci.com | T5: FR91388636896 | V5: =VLOOKUP(J5,'records (2)'!$A:$Z,16,FALSE) -> jemil.ishak-boushaki@fci.com
A6: 001IV000015RyDiYAK | B6: TENNECO AUTOMOTIVE FRANCE SAS | C6: TENNECO AUTOMOTIVE FRANCE SAS | D6: SAINT BERTHEVIN | E6: France | G6: 53940 | I6: ZA des Giraumeries | J6: 0012p00004TGrjrAAD | K6: TAFS-01646 | L6: 55 545 007 100 041 | M6: TENNECO AUTOMOTIVE FRANCE SAS | N6: . | P6: Facture originale électronique à | Q6: . | S6: AccountsPayableFrance@Tenneco.com | T6: FR29555450071 | V6: =VLOOKUP(J6,'records (2)'!$A:$Z,16,FALSE) -> sleveque@tenneco.com
A7: 001IV000015S2SQYA0 | B7: EXCELVISION | C7: EXCELVISION sas | D7: ANNONAY | E7: France | G7: 7100 | I7: 27 Rue de la Lombardière | J7: 0012p00004UJG6aAAH | K7: EXCV-01801 | L7: 33 582 068 400 033 | M7: EXCELVISION sas | N7: . | P7: Facture originale électronique à | Q7: . | S7: accueilfactures.excelvision@fareva.com | T7: FR82335820684 | V7: =VLOOKUP(J7,'records (2)'!$A:$Z,16,FALSE) -> accueilfactures.excelvision@fareva.com
A8: 001IV000015RyDzYAK | B8: CALIDA GROUP (LALLEMAND) | C8: LALLEMAND SAS | D8: VIEU D'IZENAVE | E8: France | G8: 1430 | I8: Le Balmay | J8: 001SZ000005Od72YAC | K8: LLMD-01802 | L8: 77 320 110 800 018 | M8: LALLEMAND SAS | N8: . | P8: Facture originale électronique à | Q8: . | S8: adminlallemand@lafuma-mobilier.fr | T8: FR44773201108 | V8: =VLOOKUP(J8,'records (2)'!$A:$Z,16,FALSE) -> fcormoreche@lafuma-mobilier.fr
A9: 001IV000015S85hYAC | B9: KSB CHATEAUROUX | C9: KSB SAS | D9: CHATEAUROUX | E9: France | G9: 36000 | I9: Allée de Sagan | J9: 0012p00004RmixTAAR | K9: KSBS-01588 | L9: 56 980 189 700 103 | M9: KSB SAS | N9: . | P9: Facture originale électronique à | Q9: . | S9: alexandra.rongy@ksb.com | T9: FR20569801897 | V9: =VLOOKUP(J9,'records (2)'!$A:$Z,16,FALSE) -> thomas.bruneau@ksb.com
A10: 001IV000015S50OYAS | B10: DANFOSS | C10: DANFOSS COMMERCIAL COMPRESSORS sa | D10: TREVOUX | E10: France | F10: Comptabilité | G10: 1600 | I10: ZI de Reyrieux - BP331 | J10: 0012p00004SxGjuAAF | K10: DFOS-01629 | L10: 71 378 027 800 030 | M10: DANFOSS COMMERCIAL COMPRESSORS sa | N10: . | P10: Facture originale électronique à | Q10: . | S10: amelie.chesneau@danfoss.com | T10: FR80713780278 | V10: =VLOOKUP(J10,'records (2)'!$A:$Z,16,FALSE) -> recrutementdpsii@danfoss.com
A11: 001IV000015RyDwYAK | B11: FRANCOS - (SISLEY) | C11: FRANCOS sasu | D11: BLOIS | E11: France | G11: 41000 | I11: 1 Rue des Mardeaux | J11: 001SZ000004b5HnYAI | K11: FRCS-01805 | L11: 45 098 234 300 011 | M11: FRANCOS sasu | N11: . | P11: Facture originale électronique à | Q11: . | S11: amelie.rousselot@francos.fr | T11: FR62450982343 | V11: =VLOOKUP(J11,'records (2)'!$A:$Z,16,FALSE) -> amelie.rousselot@sisley.fr
A12: 001IV000015S2eKYAS | B12: VOESTALPINE | C12: VOESTALPINE AUTOMOTIVE COMPONENTS FONTAINE sa | D12: FONTAINE | E12: France | G12: 90150 | I12: Zac de l'Aéroparc | J12: 001SZ000001pKNXYA2 | K12: VSTP-01868 | L12: 53 552 031 600 014 | M12: VOESTALPINE AUTOMOTIVE COMPONENTS FONTAINE sa | N12: . | P12: Facture originale électronique à | Q12: . | S12: andrea.cametti@voestalpine.com | T12: FR12535520316 | V12: =VLOOKUP(J12,'records (2)'!$A:$Z,16,FALSE) -> christine.bontemps@voestalpine.com
A13: 001IV000015S8j3YAC | B13: LESAFFRE - BIO SPRINGER | C13: BIO SPRINGER sa | D13: MAISONS-ALFORT | E13: France | F13: Ressources Humaines | G13: 94700 | I13: 103 Rue Jean Jaurès | J13: 001SZ000003YcdpYAC | K13: LBSP-01837 | L13: 54 209 199 600 026 | M13: BIO SPRINGER sa | N13: . | P13: Facture originale électronique à | Q13: . | S13: ap.biospringer@lesaffre.com | T13: FR93542091996 | V13: =VLOOKUP(J13,'records (2)'!$A:$Z,16,FALSE) -> m.perez@lesaffre.com
A14: 001IV000015S8jFYAS | B14: NEMERA | C14: NEMERA LA VERPILIERE sas | D14: LA VERPILLIERE | E14: France | G14: 38290 | I14: 20 Avenue de la Gare | J14: 001SZ00000BFAySYAX | K14: NMRV-01867 | L14: 38 805 696 200 029 | M14: NEMERA LA VERPILIERE sas | N14: . | P14: Facture originale électronique à | Q14: . | S14: ap.invoicesnemeralaverpilliere@nemera.net | T14: FR81388056962 | V14: =VLOOKUP(J14,'records (2)'!$A:$Z,16,FALSE) -> frver.comptafournisseurs@nemera.net
A15: 001IV000015S862YAC | B15: KSB LA ROCHE CHALAIS | C15: KSB SAS | D15: GENNEVILLIERS | E15: France | F15: Comptabilité fournisseurs | G15: 92230 | I15: 4 Allée des Barbanniers | J15: 0012p00004UIt7LAAT | K15: KSBR-01791 | L15: 56 980 189 700 632 | M15: KSB SAS | N15: . | P15: Facture originale électronique à | Q15: . | S15: ap_invoices_fr@ksb.com | T15: FR20569801897 | V15: =VLOOKUP(J15,'records (2)'!$A:$Z,16,FALSE) -> herve.decroos@ksb.com
A16: 001IV000015S2SUYA0 | B16: INVACARE FRANCE OPERATIONS | C16: INVACARE FRANCE OPERATIONS SAS | D16: FONDETTES | E16: France | G16: 37230 | I16: Route de Saint- Roch | J16: 001SZ0000059VWTYA2 | K16: IVCF-01793 | L16: 34 841 873 200 049 | M16: INVACARE FRANCE OPERATIONS SAS | N16: . | P16: Facture originale électronique à | Q16: . | S16: ap3110ivcfranceoperations@invacare.com | T16: FR19348418732 | V16: =VLOOKUP(J16,'records (2)'!$A:$Z,16,FALSE) -> ap3110ivcfranceoperations@invacare.com
A17: 001IV000015RyECYA0 | B17: CHEMVIRON PARENTIS SAS | C17: CHEMVRION PARENTIS SAS | D17: PARIS | E17: France | G17: 75017 | I17: 58 Avenue de Wagram | J17: 001SZ00000YI0h9YAD | K17: CHVP-01985 | L17: 93 026 705 900 028 | M17: CHEMVRION PARENTIS SAS | N17: . | P17: Facture originale électronique à | Q17: . | S17: apchemvironparentis.ccc@kuraray.com | T17: FR27930267059 | V17: =VLOOKUP(J17,'records (2)'!$A:$Z,16,FALSE) -> catherine.bogemans@kuraray.com
A18: 001IV000015RzTQYA0 | B18: ASTRAZENECA | C18: ASTRA ZENECA DUNKERQUE PRODUCTION scs | D18: DUNKERQUE | E18: France | G18: 59640 | I18: 224 Avenue de la Dordogne | J18: 001SZ00000Lspr7YAB | K18: ASTZ-01930 | L18: 44 813 963 400 019 | M18: ASTRA ZENECA DUNKERQUE PRODUCTION scs | N18: . | P18: Facture originale électronique à: | Q18: . | S18: apinvoicesdunkerque@astrazeneca.com | T18: FR78448139634 | V18: =VLOOKUP(J18,'records (2)'!$A:$Z,16,FALSE) -> apinvoicesdunkerque@astrazeneca.com
A19: 001IV000015RhU5YAK | B19: BALL PACKAGING GROUPE | C19: BALL PACKAGING EUROPE FRANCE sasu | D19: BIERNE | E19: France | G19: 59380 | I19: Zone d'Entreprises de Bergues | J19: 0012p00004MygGUAAZ | K19: BPEF-01789 | L19: 34 951 600 500 015 | M19: BALL PACKAGING EUROPE FRANCE sasu | N19: . | P19: Facture originale électronique à | Q19: . | S19: apinvoicesfr@ball.com | T19: FR46349516005 | V19: =VLOOKUP(J19,'records (2)'!$A:$Z,16,FALSE) -> erwan.morvan@ball.com
A20: 001IV000015S8irYAC | B20: PLASTIVALOIRE | C20: PLASTIQUES DU VAL DE LOIRE sa | D20: LANGEAIS | E20: France | F20: Comptabilité & ressources Humaines | G20: 37130 | I20: 1 route de la Retaudière - E.I. Nord - BP 38 | J20: 0012p00004Sfc9aAAB | K20: PLVL-01764 | L20: 64 480 016 100 015 | M20: PLASTIQUES DU VAL DE LOIRE sa | N20: . | P20: Facture originale électronique à | Q20: . | S20: compta.groupe@plastivaloire.com | T20: FR14644800161 | V20: =VLOOKUP(J20,'records (2)'!$A:$Z,16,FALSE) -> aurelie.boissonneau@plastivaloire.com
A21: 001IV000015RzTcYAK | B21: CHARLES RIVER LABORATOIRE FRANCE CRLF sasu | C21: CHARLES RIVER LABORATORIES FRANCE - C.R.L.F. sasu | D21: SAINT GERMAIN NUELLES | E21: France | F21: COMPTABILITE | G21: 69210 | I21: 327 Impasse du Domaine Rozier | J21: 0012p00004UHMmUAAX | K21: CHRV-01811 | L21: 8 665 004 100 022 | M21: CHARLES RIVER LABORATORIES FRANCE - C.R.L.F. sasu | N21: . | P21: Facture originale électronique à | Q21: . | S21: ARBCOMPTACRF@crl.com | T21: FR29086650041 | V21: =VLOOKUP(J21,'records (2)'!$A:$Z,16,FALSE) -> arbcomptacrf@crl.com
A22: 001IV000015S2SIYA0 | B22: RESTONIS | C22: RESTONIS sasu | D22: IVRY SUR SEINE | E22: France | G22: 94200 | I22: 12 rue Jean Marie Poulmarch | J22: 0012p00004MRAVrAAP | K22: RTNS-01679 | L22: 53 117 081 900 019 | M22: RESTONIS sasu | N22: . | P22: Facture originale électronique à | Q22: . | S22: ass.gestion@restonis.fr | T22: FR58531170819 | V22: =VLOOKUP(J22,'records (2)'!$A:$Z,16,FALSE) -> jennifer.chippaux@restonis.fr
A23: 001IV000015S8j2YAC | B23: NYRSTAR FRANCE | C23: NYRSTAR FRANCE sasu | D23: AUBY | E23: France | G23: 59950 | I23: Rue Jean Jacques Rousseau | J23: 001SZ000002xEQqYAM | K23: NSTF-01804 | L23: 49 083 728 300 020 | M23: NYRSTAR FRANCE sasu | N23: . | P23: Facture originale électronique à | Q23: . | S23: auby.comptafactures@nyrstar.com | T23: FR63490837283 | V23: =VLOOKUP(J23,'records (2)'!$A:$Z,16,FALSE) -> alexis.dohein@nyrstar.com
A24: 001IV000015S8jKYAS | B24: INEOS AUTOMOTIVE S.A.S | C24: INEOS AUTOMOTIVE SAS | D24: HAMBACH | E24: France | F24: Service comptabilité | G24: 57913 | I24: Europôle de Sarreguemines | J24: 001SZ00000PZ6aTYAT | K24: INEA-01968 | L24: 40 311 943 100 027 | M24: INEOS AUTOMOTIVE SAS | N24: . | P24: Facture originale électronique à | Q24: . | T24: FR38403119431 | V24: =VLOOKUP(J24,'records (2)'!$A:$Z,16,FALSE) -> automotive.compta@ineos.com
A25: 001IV000015S867YAC | B25: BERRY GLOBAL - PROMENS - (EX PGI) | C25: PROMENS SA | D25: BELLIGNAT | E25: France | G25: 1100 | I25: 5 Rue Castellion | J25: 001SZ000003ZJXVYA4 | K25: PRMS-01766 | L25: 75 920 045 400 156 | M25: PROMENS SA | N25: . | P25: Facture originale électronique à | Q25: . | S25: alexandraGrossat@berryglobal.com | T25: FR52759200454 | V25: =VLOOKUP(J25,'records (2)'!$A:$Z,16,FALSE) -> alexandragrossat@berryglobal.com
A26: 001IV000015RewNYAS | B26: CAREA GROUPE | C26: CAREA FACADE sasu | D26: OMBREE D'ANJOU | E26: France | G26: 49520 | I26: ZA DE BEL AIR Bel-Air-de-Combrée - COMBREE | J26: 0012p00004UHRUgAAP | K26: CARG-01700 | L26: 33 408 975 200 102 | M26: CAREA FACADE sasu | N26: . | P26: Facture originale électronique à | Q26: . | S26: bcouet@carea.fr | T26: FR84334089752 | V26: =VLOOKUP(J26,'records (2)'!$A:$Z,16,FALSE) -> bcouet@carea.fr
A27: 001IV000015S8j9YAC | B27: OTERRA FRANCE | C27: OTERRA FRANCE SAS | D27: COSSE-LE-VIVIEN | E27: France | G27: 53230 | I27: Rue Ambroise Paré | J27: 001SZ000005HETVYA4 | K27: OTRF-01794 | L27: 89 070 836 500 030 | M27: OTERRA FRANCE SAS | N27: . | P27: Facture originale électronique à | Q27: . | S27: beatrice.chretien@oterra.com | T27: FR50890708365 | V27: =VLOOKUP(J27,'records (2)'!$A:$Z,16,FALSE) -> beatrice.chretien@oterra.com
A28: 001IV000015S6a7YAC | B28: GROUPE RIOLAND | C28: GROUPE RIOLAND sas | D28: BAUDRES | E28: France | G28: 36110 | I28: 24 La Barre | J28: 0012p00004OML8JAAX | K28: GRLD-01542 | L28: 3 375 447 200 051 | M28: GROUPE RIOLAND sas | N28: . | P28: Facture originale électronique à | Q28: . | S28: benoit.pinon@grouperioland.fr | T28: FR53337544720 | V28: =VLOOKUP(J28,'records (2)'!$A:$Z,16,FALSE) -> benoit.pinon@grouperioland.fr
A29: 001IV000015RyE5YAK | B29: DPS BEAUNE (Groupe Dalloz) | C29: DPS BEAUNE sas | D29: BEAUNE | E29: France | G29: 21200 | I29: 156 Route de Dijon | J29: 001SZ00000CP6rMYAT | K29: DPSB-01896 | L29: 83 969 459 300 014 | M29: DPS BEAUNE sas | N29: . | P29: Facture originale électronique à | Q29: . | S29: besma.ammari@dps-beaune.com | T29: FR96839694593 | V29: =VLOOKUP(J29,'records (2)'!$A:$Z,16,FALSE) -> lea.monaci@dps-beaune.com
A30: 001IV000015S8ilYAC | B30: SHERPA LOGISTIQUE (CALIDA GROUP) | C30: SHERPA LOGISTIQUE sas | D30: ST RAMBERT D'ALBON | E30: France | G30: 26140 | I30: ZI du Cappa | J30: 0012p00004QckxBAAR | K30: SHRP-01576 | L30: 43 953 100 500 015 | M30: SHERPA LOGISTIQUE sas | N30: . | P30: Facture originale électronique à | Q30: . | S30: bjumelart@sherpa-logistique.fr | T30: FR53439531005 | V30: =VLOOKUP(J30,'records (2)'!$A:$Z,16,FALSE) -> bjumelart@sherpa-logistique.fr
A31: 001IV000015S85zYAC | B31: SMT ROTAREX - (SOCIETE DE MECANIQUE DES TILLES) | C31: SOCIETE DE MECANIQUE DES TILLES sas | D31: GENLIS | E31: France | G31: 21110 | I31: 5 Rue de Labergement | J31: 0012p00004TnExuAAF | K31: SMTR-01650 | L31: 71 204 754 700 021 | M31: SOCIETE DE MECANIQUE DES TILLES sas | N31: . | P31: Facture originale électronique à | Q31: . | S31: bon.nathalie@rotarex.com | T31: FR20712047547 | V31: =VLOOKUP(J31,'records (2)'!$A:$Z,16,FALSE) -> bon.nathalie@rotarex.com
A32: 001IV000015S8imYAC | B32: BONNEFOY SAS | C32: J.C. BONNEFOY sas | D32: SAONE | E32: France | G32: 25660 | I32: ZI- 14 Rue de l'Industrie - BP28 | J32: 0012p00004QdCmrAAF | K32: BNFY-01575 | L32: 30 142 262 200 029 | M32: J.C. BONNEFOY sas | N32: . | P32: Facture originale électronique à | Q32: . | S32: bonnefoy.achats@groupe-bonnefoy.fr | T32: FR25301422622 | V32: =VLOOKUP(J32,'records (2)'!$A:$Z,16,FALSE) -> c.gosse@groupe-bonnefoy.fr
A33: 001IV000015S508YAC | B33: VIANT MEDICAL - (CHAUMONT) | C33: VIANT CHAUMONT SAS | D33: CHAUMONT | E33: France | F33: Finance | G33: 52000 | I33: 4 rue Renée et Louis Landanger | J33: 0012p00004NgQ3uAAF | K33: VMDC-01524 | L33: 49 923 501 800 011 | M33: VIANT CHAUMONT SAS | P33: Facture originale électronique à | Q33: . | S33: bruno.gratas@viantmedical.com | T33: FR40499235018 | V33: =VLOOKUP(J33,'records (2)'!$A:$Z,16,FALSE) -> bruno.gratas@viantmedical.com
A34: 001IV000015S50QYAS | B34: ANGDM | C34: AGENCE NATIONALE POUR LA GARANTIE DES DROITS DES MINEURS - ANGDM | D34: NOYELLES SOUS LENS | E34: France | F34: CENTRE DE GESTION | G34: 62221 | I34: 110 Avenue de la fosse 23 | J34: 0012p00004TzX0NAAV | K34: ANGD-01672 | L34: 18 009 253 800 024 | M34: AGENCE NATIONALE POUR LA GARANTIE DES DROITS DES MINEURS - ANGDM | N34: . | P34: Facture originale électronique à | Q34: . | S34: bureau.formation@angdm.fr | T34: FR42180092538 | V34: =VLOOKUP(J34,'records (2)'!$A:$Z,16,FALSE) -> stephanie.lemarchand@angdm.fr
A35: 001IV000015S8j0YAC | B35: SOCAMEL | C35: SOCAMEL TECHNOLOGIES sas | D35: RENAGE | E35: France | G35: 38140 | I35: Descente Allivet | J35: 001SZ0000021G4qYAE | K35: SCML-01713 | L35: 7 050 301 600 035 | M35: SOCAMEL TECHNOLOGIES sas | N35: . | P35: Facture originale électronique à | Q35: . | S35: c.latil@socamel.com | T35: FR75070503016 | V35: =VLOOKUP(J35,'records (2)'!$A:$Z,16,FALSE) -> c.latil@socamel.com
A36: 001IV000015RzTjYAK | B36: HEINZ | C36: H.J. HEINZ FRANCE sasu | D36: SECLIN | E36: France | G36: 59113 | I36: 18 Rue Marx Dormoy | J36: 001SZ000003WtXqYAK | K36: HJHZ-01770 | L36: 48 300 532 800 040 | M36: H.J. HEINZ FRANCE sasu | N36: . | P36: Facture originale électronique à | Q36: . | S36: camille.meurin@kraftheinz.com | T36: FR23483005328 | V36: =VLOOKUP(J36,'records (2)'!$A:$Z,16,FALSE) -> camille.meurin@kraftheinz.com
A37: 001IV000015S8ioYAC | B37: MMP PACKETIS | C37: MMP PACKETIS SAS | D37: CHAZELLES | E37: France | G37: 16380 | I37: Treille | J37: 0012p00004QwpRfAAJ | K37: MMPP-01589 | L37: 40 322 193 000 023 | M37: MMP PACKETIS SAS | N37: . | P37: Facture originale électronique à | Q37: . | S37: carole.tardieu@mm.group | T37: FR45403221930 | V37: =VLOOKUP(J37,'records (2)'!$A:$Z,16,FALSE) -> david.jubien@mm.group
A38: 001IV000015S8nKYAS | B38: MOY PARK | C38: MOY PARK FRANCE sas | D38: HENIN-BEAUMONT | E38: France | G38: 72110 | I38: 712 Chemin de Noyelles | J38: 001SZ000008DnhTYAS | K38: MOYP-01828 | L38: 44 457 512 000 019 | M38: MOY PARK FRANCE sas | N38: . | Q38: ceap.invoices@moypar | S38: Facture originale électronique à | T38: FR10444575120 | V38: =VLOOKUP(J38,'records (2)'!$A:$Z,16,FALSE) -> carine.capelle@moypark.com
A39: 001IV000015SAFiYAO | B39: BANQUE POPULAIRE MEDITERRANEE | C39: BANQUE POPULAIRE MEDITERRANEE sa | D39: NICE | E39: France | G39: 6200 | I39: 457 Promenade des Anglais - BP 241 | J39: 0012p00004Ovfx1AAB | K39: BPMD-01549 | L39: 5 880 148 101 264 | M39: BANQUE POPULAIRE MEDITERRANEE sa | N39: . | P39: Facture originale électronique à | Q39: . | S39: cecile.geoffroy@bpmed.fr | T39: FR61058801481 | V39: =VLOOKUP(J39,'records (2)'!$A:$Z,16,FALSE) -> cecile.geoffroy@bpmed.fr
A40: 001IV000015S8ipYAC | B40: CAISSE D'EPARGNE BOURGOGNE FRANCHE COMTE (CEBFC) | C40: CAISSE D'EPARGNE ET DE PREVOYANCE DE BOURGOGNE FRANCHE-COMTE sa - CEBFC | D40: DIJON | E40: France | G40: 21000 | I40: 1 Rond Point de la Nation | J40: 0012p00004RLlIQAA1 | K40: CEBF-01654 | L40: 35 248 334 100 017 | M40: CAISSE D'EPARGNE ET DE PREVOYANCE DE BOURGOGNE FRANCHE-COMTE sa - CEBFC | N40: . | P40: Facture originale électronique à | Q40: . | S40: cecile.pencole-lehaut@cebfc.caisse-epargne.fr | T40: FR73352483341 | V40: =VLOOKUP(J40,'records (2)'!$A:$Z,16,FALSE) -> celine.ballot@cebfc.caisse-epargne.fr
A41: 001IV000015SADqYAO | B41: THUASNE | C41: THUASNE sas | D41: SAINT-ETIENNE Cedex 2 | E41: France | G41: 42100 | I41: 27 Rue de la Jomayere | J41: 001SZ000003NGlbYAG | K41: THUA-01777 | L41: 54 209 118 600 040 | M41: THUASNE sas | N41: . | P41: Facture originale électronique à | Q41: . | S41: celine.champion@thuasne.fr | T41: FR88542091186 | V41: =VLOOKUP(J41,'records (2)'!$A:$Z,16,FALSE) -> celine.champion@thuasne.fr
A42: 001IV000015S6a6YAC | B42: FMGC Groupe | C42: FONDERIE ET MECANIQUE GENERALE CASTELBRIANTAISE sa - FMGC | D42: SOUDAN | E42: France | G42: 44110 | I42: ZI Hochepie | J42: 0012p00004OLmuHAAT | K42: FMGC-01539 | L42: 86 680 121 000 026 | M42: FONDERIE ET MECANIQUE GENERALE CASTELBRIANTAISE sa - FMGC | N42: . | P42: Facture originale électronique à | Q42: . | S42: celine.chevrel@fmgc.net | T42: FR94866801210 | V42: =VLOOKUP(J42,'records (2)'!$A:$Z,16,FALSE) -> nadine.crouilbois@fmgc.net
A43: 001IV000015SAHxYAO | B43: VERNET | C43: VERNET sas | D43: ARPAJON Cedex | E43: France | G43: 91291 | I43: 21-27 route d'Arpajon | J43: 001SZ000001N3caYAC | K43: VRNT-01701 | L43: 30 852 882 700 022 | M43: VERNET sas | N43: . | P43: Facture originale electronique à | Q43: . | S43: cerutti@vernet.fr | T43: FR77308528827 | V43: =VLOOKUP(J43,'records (2)'!$A:$Z,16,FALSE) -> ribeiro@vernet.fr
A44: 001IV000015S8jIYAS | B44: DAGARD | C44: DAGARD sas | D44: BOUSSAC | E44: France | G44: 23600 | I44: Route du Stade | J44: 001SZ00000Oced1YAB | K44: DGRD-01933 | L44: 99 575 028 800 012 | M44: DAGARD sas | N44: . | P44: Facture originale électronique à | Q44: . | S44: cfournisseurs@dagard.com | T44: FR76995750288 | V44: =VLOOKUP(J44,'records (2)'!$A:$Z,16,FALSE) -> cfournisseurs@dagard.com
A45: 001IV000015S85lYAC | B45: REINE DE DIJON | C45: REINE DE DIJON sas | D45: FLEUREY-SUR-OUCHE | E45: France | G45: 21410 | I45: 1 Rue des Combets | J45: 0012p00004S28b2AAB | K45: RDDJ-01721 | L45: 39 425 627 500 022 | M45: REINE DE DIJON sas | N45: . | P45: Facture originale électronique à | Q45: . | S45: cguichard@reinededijon.fr | T45: FR16394256275 | V45: =VLOOKUP(J45,'records (2)'!$A:$Z,16,FALSE) -> cguichard@reinededijon.fr
A46: 001IV000015S2eEYAS | B46: GROUPE EUREDEN - (ex GROUPE D'AUCY - PEP sas) | C46: PEP sasu | D46: PLOERMEL | E46: France | G46: 56800 | I46: ZI de Camagnon | J46: 0012p00004RB7pqAAD | K46: GPEP-01591 | L46: 42 080 049 200 027 | M46: PEP sasu | N46: . | P46: Facture originale électronique à | Q46: . | S46: charline.leberrigaud@eureden.com | T46: FR32420800492 | V46: =VLOOKUP(J46,'records (2)'!$A:$Z,16,FALSE) -> regine.oger@eureden.com
A47: 001IV000015S8jEYAS | B47: TEXELIS | C47: TEXELIS sasu | D47: LIMOGES CEDEX 1 | E47: France | G47: 87011 | I47: 72 Route du Palais | J47: 001SZ000009VR6pYAG | K47: TXLS-01877 | L47: 50 169 841 900 022 | M47: TEXELIS sasu | N47: . | P47: Facture originale électronique à | Q47: . | S47: charlotte.maillard@texelis.com | T47: FR07501698419 | V47: =VLOOKUP(J47,'records (2)'!$A:$Z,16,FALSE) -> magalie.dauge@texelis.com
A48: 001IV000015RewKYAS | B48: CORDEN PHARMA CHENOVE | C48: CORDEN PHARMA CHENOVE sasu | D48: CHENOVE | E48: France | G48: 21300 | I48: 47 rue de Longvic | J48: 0012p00004TGasWAAT | K48: CPCH-01648 | L48: 42 118 181 900 010 | M48: CORDEN PHARMA CHENOVE sasu | N48: . | P48: Facture originale électronique à | Q48: . | S48: chenove.comptabilite@cordenpharma.com | T48: FR92421181819 | V48: =VLOOKUP(J48,'records (2)'!$A:$Z,16,FALSE) -> chenove.comptabilite@cordenpharma.com
A49: 001IV000015S2e8YAC | B49: REYNAERS ALUMINIUM | C49: REYNAERS ALUMINIUM sasu | D49: HAM | E49: France | G49: 80400 | I49: Route de Brouchy | J49: 0012p00004NeUaTAAV | K49: RNRA-01573 | L49: 39 922 726 300 072 | M49: REYNAERS ALUMINIUM sasu | N49: . | P49: Facture originale électronique à | Q49: . | S49: chm@reynaers.com | T49: FR06399227263 | V49: =VLOOKUP(J49,'records (2)'!$A:$Z,16,FALSE) -> chm@reynaers.com
A50: 001IV000015S9HBYA0 | B50: SMURFIT WESTROCK FRANCE | C50: SMURFIT WESTROCK FRANCE sas | D50: SAINT MANDE | E50: France | F50: Christophe BARON | G50: 94160 | I50: 5 avenue du général de Gaulle | J50: 001SZ000009ueaJYAQ | K50: SMWF-01900 | L50: 49 325 490 800 020 | M50: SMURFIT WESTROCK FRANCE sas | N50: . | P50: Facture originale électronique à | Q50: . | S50: christophe.baron@smurfitwestrock.fr | T50: FR54493254908 | V50: =VLOOKUP(J50,'records (2)'!$A:$Z,16,FALSE) -> christophe.baron@smurfitwestrock.fr
A51: 001IV000015S2eZYAS | B51: EURIAL ULTRA-FRAIS - Château Salins | C51: EURIAL ULTRA FRAIS sasu | D51: CHATEAU SALINS | E51: France | G51: 57170 | I51: Avenue des Saulniers | J51: 0012p00004Rel0OAAR | K51: EUFR-01878 | L51: 70 558 010 800 102 | M51: EURIAL ULTRA FRAIS sasu | N51: . | P51: Facture originale électronique à | Q51: . | S51: christophe.renoncial@eurial.eu | T51: FR31705580108 | V51: =VLOOKUP(J51,'records (2)'!$A:$Z,16,FALSE) -> christophe.renoncial@eurial.eu
A52: 001IV000015S2SRYA0 | B52: GUERLAIN sas | C52: GUERLAIN sas | D52: CHARTRES | E52: France | G52: 28000 | I52: 4 Avenue Gustave Eiffel | J52: 001SZ000001Eu4zYAC | K52: GRLN-01835 | L52: 58 202 226 500 224 | M52: GUERLAIN sas | N52: . | P52: Facture originale électronique à | Q52: . | S52: clanotte@guerlain.fr | T52: FR71582022265 | V52: =VLOOKUP(J52,'records (2)'!$A:$Z,16,FALSE) -> nbonnat@guerlain.fr
A53: 001IV000015S85uYAC | B53: FAIVELEY TECH BOURGOIN | C53: FAIVELEY TECH BOURGOIN sasu | D53: BOURGOIN JALLIEU | E53: France | G53: 38307 | I53: 107 allée de Chardillonnay - Maubec - CS 51001 | J53: 0012p00004SzOBnAAN | K53: FVTB-01760 | L53: 38 955 376 900 040 | M53: FAIVELEY TECH BOURGOIN sasu | N53: . | P53: Facture originale électronique à | Q53: . | S53: compta.bourgoin@faiveley.fr | T53: FR81389553769 | V53: =VLOOKUP(J53,'records (2)'!$A:$Z,16,FALSE) -> emmanuelle.dubois@faiveleytech.fr
A54: 001IV000015S85wYAC | B54: FLOWBIRD - (ex PARKEON) | C54: FLOWBIRD sasu | D54: BESANCON | E54: France | G54: 25000 | I54: 6 Rue Isaac Newton | J54: 0012p00004TmXQzAAN | K54: FLWB-01860 | L54: 44 471 927 200 148 | M54: FLOWBIRD sasu | N54: . | P54: Facture originale électronique à | Q54: . | S54: compta.factures.fournisseurs@flowbird.group | T54: FR40444719272 | V54: =VLOOKUP(J54,'records (2)'!$A:$Z,16,FALSE) -> veronique.croizier@flowbird.group
A55: 001IV000015S2eMYAS | B55: EUREDEN (Société : AUBRET) | C55: AUBRET sasu | D55: VALLONS-DE-L'ERDRE | E55: France | G55: 44540 | I55: ZI BP12 - Saint- Mars La Jaille | J55: 001SZ000005MYg6YAG | K55: ABRT-01799 | L55: 78 818 295 400 024 | M55: AUBRET sasu | N55: . | P55: Facture originale électronique à | Q55: . | S55: compta.fournisseur@euroden.com | T55: FR50788182954 | V55: =VLOOKUP(J55,'records (2)'!$A:$Z,16,FALSE) -> compta.fournisseurs@eureden.com
A56: 001IV000015SAFfYAO | B56: JEAN LARNAUDIE | C56: JEAN LARNAUDIE snc | D56: FIGEAC | E56: France | G56: 46100 | I56: 76 rue des Artisans | J56: 0012p00004Nh9b2AAB | K56: JLAR-01605 | L56: 41 025 258 900 024 | M56: JEAN LARNAUDIE snc | N56: . | P56: Facture originale électronique à | Q56: . | S56: compta.fournisseur@larnaudie.com | T56: FR51410252589 | V56: =VLOOKUP(J56,'records (2)'!$A:$Z,16,FALSE) -> compta.fournisseur@larnaudie.com
A57: 001IV000015S6a4YAC | B57: CARBODY | C57: CARBODY sas | D57: WITRY LES REIMS | E57: France | G57: 51420 | I57: 17 rue du moulin Florent | J57: 0012p00004NhQTFAA3 | K57: CBDY-01514 | L57: 57 204 050 900 067 | M57: CARBODY sas | P57: Facture originale électronique à | Q57: . | S57: compta.fournisseurs@carbody.eu | T57: FR61572040509 | V57: =VLOOKUP(J57,'records (2)'!$A:$Z,16,FALSE) -> kaoutar.elamrani@carbody.eu
A58: 001IV000015S86DYAS | B58: MDS sa | C58: MDS sa | D58: DOURDAN | E58: France | G58: 91410 | I58: 22 Rue Robert Benoist | J58: 001SZ00000AKbAeYAL | K58: MDSX-01864 | L58: 34 422 476 100 025 | M58: MDS sa | N58: . | P58: Facture originale électronique à | Q58: . | S58: compta.fournisseurs@mdsfrance.fr | T58: FR73344224761 | V58: =VLOOKUP(J58,'records (2)'!$A:$Z,16,FALSE) -> compta.fournisseurs@mdsfrance.fr
A59: 001IV000015RzTeYAK | B59: SOUCHIER BOULLET GROUPE | C59: SOUCHIER - BOULLET sas | D59: HERICOURT | E59: France | G59: 70400 | I59: 11 Rue du 47ème Régiment d'Artillerie | J59: 0012p00004UIiDrAAL | K59: SCHB-01662 | L59: 66 201 466 100 067 | M59: SOUCHIER - BOULLET sas | N59: . | P59: Facture originale électronique à | Q59: . | S59: compta.fournisseurs@souchier-boullet.com | T59: FR35662014661 | V59: =VLOOKUP(J59,'records (2)'!$A:$Z,16,FALSE) -> compta.fournisseurs@souchier-boullet.com
A60: 001IV000015S2eUYAS | B60: WESER | C60: WESER sas | D60: MAZIERES DE TOURAINE | E60: France | G60: 37130 | I60: 1 Route de Cléré | J60: 0012p00004RJUKLAA5 | K60: WESR-01594 | L60: 65 480 102 600 018 | M60: WESER sas | N60: . | P60: Facture originale électronique à | Q60: . | S60: compta.fournisseurs@weser.fr | T60: FR24654801026 | V60: =VLOOKUP(J60,'records (2)'!$A:$Z,16,FALSE) -> compta.fournisseurs@weser.fr
A61: 001IV000015S2eFYAS | B61: SAEM ENERGIES | C61: SAEM sas | D61: CUSSET | E61: France | F61: SAEM ENERGIES | G61: 3300 | I61: 2 Boulevard Jean Lafaure | J61: 0012p00004RBJMwAAP | K61: SAEM-01806 | L61: 80 133 952 400 010 | M61: SAEM sas | N61: . | P61: Facture originale électronique à | Q61: . | S61: compta.saem@engie.com | T61: FR72801339524 | V61: =VLOOKUP(J61,'records (2)'!$A:$Z,16,FALSE) -> remi.lucenet@engie.com
A62: 001IV000015S2eNYAS | B62: BONGARD | C62: BONGARD sas | D62: HOLTZHEIM | E62: France | F62: Comptabilité | G62: 67810 | I62: 32 route de Wolfisheim | J62: 0012p00004MRCLYAA5 | K62: BGRD-01647 | L62: 58 295 030 900 051 | M62: BONGARD sas | N62: . | P62: Facture originale électronique à | Q62: . | S62: compta@afebakery.fr | T62: FR12582950309 | V62: =VLOOKUP(J62,'records (2)'!$A:$Z,16,FALSE) -> sylviekremer@bongard.fr
